Workbook
Name critCategory: Dash_Calc!$H$7
Name critRegion: Dash_Calc!$H$5
Name dEnd: Dash_Calc!$H$10
Name dStart: Dash_Calc!$H$9
Name lstCategory: Dash_Calc!$B$5:$B$13
Name lstMonth: Dash_Calc!$C$5:$C$17
Name lstRegion: Dash_Calc!$A$5:$A$9
Name lstScenario: Dash_Calc!$E$5:$E$8
Name selCategory: Dashboard!$G$6
Name selMonth: Dashboard!$K$6
Name selRegion: Dashboard!$C$6
Name selScenario: Dashboard!$O$6

Sheet README
A1: CareTech Commercial Analytics & Financial Modelling Capstone (v2)
A2: Synthetic data only. No service-user, employee or supplier personal data. Built for the Junior Data Analyst (Commercial) role.
A4: Business problem
A5: A growing Commercial team receives procurement, fleet, workforce, agency and finance extracts from separate systems. The extracts disagree on naming, carry duplicates and gaps, and are reported by hand. The team needs one trusted view of spend, a savings tracker it can defend, and a 2026 model that shows what pay, agency and sourcing decisions do to EBITDA.
A7: Workflow
A8: Raw CSV extracts -> VBA consolidation -> Excel Tables -> formula cleansing & DQ flags -> reconciliation -> analysis -> driver-based model -> savings tracker -> interactive dashboard -> VBA refresh & PDF report pack
A10: Sheet guide (click to open)
A11: Sheet | B11: Layer | C11: What it shows | D11: JD requirement evidenced
A12: Dashboard | B12: Presentation | C12: Interactive executive view: 4 selectors, 15 KPI cards, 4 live insight sentences, 8 charts. | D12: Recurring commercial reports; explaining findings to non-analysts
A13: Financial_Model | B13: Model | C13: Driver-based 2026 forecast, 4 scenarios, EBITDA bridge, monthly phasing, budget comparison, two sensitivity grids. | D13: Cost models and scenario analysis
A14: Savings_Tracker | B14: Model | C14: Category targets vs realised YTD, run-rate forecast, RAG status, cross-check to the model. | D14: Savings trackers
A15: Site_Performance | B15: Analysis | C15: Budget vs actual Opex and EBITDA margin by site with RAG and ranking. | D15: Finance data; variance analysis
A16: Ops_Analysis | B16: Analysis | C16: Fleet cost per mile, overtime and absence, agency rates and share of staff cost. | D16: Fleet, workforce and agency data
A17: Supplier_Analysis | B17: Analysis | C17: Supplier spend, rank, Pareto concentration and contract compliance. | D17: Supplier spend analysis
A18: Pivot_Analysis | B18: Analysis | C18: Formula cross-tabs by category, region and month. | D18: Lookups, pivots and formulas
A19: Actual_Pivot | B19: Analysis | C19: Genuine PivotTable on the cleaned table, used to validate the formulas. | D19: PivotTables
A20: Data_Quality | B20: Control | C20: Exception counts, treatment rules, reconciliations with PASS/FAIL, live exception log. | D20: Cleanse, validate, quality-assure
A21: Cleaned_Procurement | B21: Transform | C21: Formula-cleaned procurement layer: trimmed, standardised, enriched and flagged. | D21: Consistency across disparate systems
A22: Dash_Calc | B22: Engine | C22: Filtered measures and chart series behind the Dashboard. | D22: Maintainable, auditable build
... A26: Methodology | B26: Docs | C26: Assumptions, GDPR approach, limitations. | D26: GDPR-first approach
A28: Colour convention
A29: Blue text on yellow = input you can change
A30: Green text = link to another sheet
A31: Black text = calculation (do not overwrite)
A33: Five-minute demo
A34: 1. Dashboard: set Region = Wales, Month = Oct-2025. Every card, chart and sentence updates.
A35: 2. Switch scenario to Conservative: 2026 EBITDA, the bridge and the scenario chart move together.
A36: 3. Data_Quality: show the flagged exceptions and the PASS reconciliations to the finance ledger.
A37: 4. Financial_Model: walk the bridge and the sensitivity grids (payroll matters more than procurement).
A38: 5. Alt+F8 -> ExportRegionalReportPack: one PDF per region in a few seconds.

Sheet Dashboard
B2: COMMERCIAL ANALYTICS | EXECUTIVE DASHBOARD
B3: ="2025 actuals | Region: "&Dash_Calc!$H$47&" | Category: "&selCategory&" | Period: "&Dash_Calc!$H$48&" | 2026 scenario: "&selScenario -> 2025 actuals | Region: all regions | Category: All | Period: FY 2025 | 2026 scenario: Base
B4: Last refreshed: run RefreshCommercialModel (Alt+F8) to stamp this line.
B6: Region | C6: All | F6: Category | G6: All | J6: Month | K6: All | N6: 2026 scenario | O6: Base
B7: Pick from the yellow drop-downs. Region, category and month filter the actuals; the scenario drives the 2026 model. Category affects procurement cards and the supplier chart only.
B9: FINANCE (region + month filter)
B10: Revenue | E10: Actual Opex | H10: EBITDA | K10: EBITDA margin | N10: Opex vs budget
B11: =Dash_Calc!$H$13 -> 86476517 | E11: =Dash_Calc!$H$14 -> 60352965 | H11: =Dash_Calc!$H$16 -> 26123553 | K11: =Dash_Calc!$H$17 -> 0.3020884 | N11: =Dash_Calc!$H$18 -> 48856.977
B12: ="Share of group: "&TEXT(IFERROR(Dash_Calc!$H$13/Dash_Calc!$H$22,0),"0%") -> Share of group: 100% | E12: ="Budget: "&TEXT(Dash_Calc!$H$15/1000000,"£0.0")&"m" -> Budget: £60.4m | H12: ="Payroll = "&TEXT(IFERROR(Dash_Calc!$H$20/Dash_Calc!$H$13,0),"0%")&" of revenue" -> Payroll = 44% of revenue | K12: ="Group 2025: "&TEXT(Dash_Calc!$H$46,"0.0%") -> Group 2025: 30.2% | N12: =IF(Dash_Calc!$H$18>=0,"Favourable ","Adverse ")&TEXT(Dash_Calc!$H$19,"+0.0%;-0.0%") -> Favourable +0.1%
B13: PROCUREMENT (region + category + month filter)
B14: Procurement spend | E14: Savings potential | H14: Off-contract share | K14: Average invoice | N14: Data-quality exceptions
B15: =Dash_Calc!$H$23 -> 13922682 | E15: =Dash_Calc!$H$24 -> 782438.95 | H15: =Dash_Calc!$H$26 -> 0.82410798 | K15: =Dash_Calc!$H$29 -> 7734.8232 | N15: =Dash_Calc!$H$28 -> 6
B16: =TEXT(Dash_Calc!$H$27,"#,##0")&" invoices" -> 1,800 invoices | E16: =TEXT(IFERROR(Dash_Calc!$H$24/Dash_Calc!$H$23,0),"0.0%")&" of spend at target rates" -> 5.6% of spend at target rates | H16: =TEXT(Dash_Calc!$H$25/1000000,"£0.00")&"m not under contract" -> £11.47m not under contract | K16: ="Across "&TEXT(Dash_Calc!$H$27,"#,##0")&" invoices" -> Across 1,800 invoices | N16: ="Logged on Data_Quality, none deleted" -> Logged on Data_Quality, none deleted
B17: OPERATIONS (region + month) & 2026 MODEL (group, scenario)
B18: Fleet cost per mile | E18: Agency % of staff cost | H18: Overtime % of payroll | K18: 2026 EBITDA | N18: 2026 EBITDA margin
B19: =Dash_Calc!$H$33 -> 0.72741135 | E19: =Dash_Calc!$H$38 -> 0.033981885 | H19: =Dash_Calc!$H$36 -> 0.029296458 | K19: =Dash_Calc!$H$40 -> 28098167 | N19: =Dash_Calc!$H$41 -> 0.31545875
B20: =TEXT(Dash_Calc!$H$31,"#,##0")&" miles" -> 1,212,529 miles | E20: =TEXT(Dash_Calc!$H$37/1000,"£#,##0")&"k agency spend" -> £1,341k agency spend | H20: =TEXT(Dash_Calc!$H$35/1000,"£#,##0")&"k overtime" -> £1,117k overtime | K20: =IF(Dash_Calc!$H$43>=0,"+","-")&TEXT(ABS(Dash_Calc!$H$43)/1000000,"£0.0")&"m vs 2025" -> +£2.0m vs 2025 | N20: =selScenario&" scenario" -> Base scenario
B22: WHAT THE NUMBERS SAY
B23: =Dash_Calc!$H$51 -> Largest spend category in all regions, FY 2025: Agency Labour at £3,193,367 (23% of procurement spend).
B24: =Dash_Calc!$H$52 -> Top supplier for this selection is NurseLink at £1,161,388; 82% of selected spend is off-contract (£11,473,793). Category targets applied to this spend are worth £782,439.
B25: =Dash_Calc!$H$53 -> Opex for all regions, FY 2025 is £48,857 under budget (+0.1%); EBITDA margin 30.2% against a group 2025 margin of 30.2%.
B26: =Dash_Calc!$H$54 -> 2026 Base scenario: EBITDA £28.1m (31.5% margin), up £2.0m on 2025. The savings tracker forecasts 81% of the category target.
B96: Charts read from Dash_Calc, so they redraw whenever a selector changes. Source logic: Financial_Model, Savings_Tracker, Cleaned_Procurement, raw tables.

Sheet Financial_Model
A1: 2026 Driver-Based Financial Model
A2: Blue = input, green = link to another sheet, black = calculation. Scenario is chosen on the Dashboard control panel.
A3: Selected scenario | B3: =selScenario -> Base
A5: Driver | B5: Conservative | C5: Base | D5: Aggressive | E5: Custom | F5: Selected | H5: Savings plan cross-check
A6: Revenue growth | B6: 0.01 | C6: 0.03 | D6: 0.05 | E6: 0.03 | F6: =CHOOSE(MATCH($B$3,$B$5:$E$5,0),B6,C6,D6,E6) -> 0.03 | H6: Top-down: procurement saving in selected scenario | I6: =-D17 -> 556680.77
A7: Procurement savings | B7: 0.02 | C7: 0.04 | D7: 0.07 | E7: 0.04 | F7: =CHOOSE(MATCH($B$3,$B$5:$E$5,0),B7,C7,D7,E7) -> 0.04 | H7: Bottom-up: category targets (Savings_Tracker) | I7: =Savings_Tracker!E15 -> 782438.95
A8: Agency rate inflation | B8: 0.06 | C8: 0.05 | D8: 0.03 | E8: 0.05 | F8: =CHOOSE(MATCH($B$3,$B$5:$E$5,0),B8,C8,D8,E8) -> 0.05 | H8: Delivery: full-year forecast (Savings_Tracker) | I8: =Savings_Tracker!G15 -> 631350
A9: Fleet efficiency | B9: 0.01 | C9: 0.03 | D9: 0.05 | E9: 0.03 | F9: =CHOOSE(MATCH($B$3,$B$5:$E$5,0),B9,C9,D9,E9) -> 0.03 | H9: Forecast delivery minus model assumption | I9: =I8-I6 -> 74669.226
A10: Payroll inflation | B10: 0.035 | C10: 0.025 | D10: 0.02 | E10: 0.025 | F10: =CHOOSE(MATCH($B$3,$B$5:$E$5,0),B10,C10,D10,E10) -> 0.025 | H10: =IF(I9>=0,"Savings delivery supports the "&$B$3&" assumption.","Model assumes "&TEXT(-I9,"£#,##0")&" more procurement saving than the tracker is forecasting: treat "&$B$3&" as a stretch.") -> Savings delivery supports the Base assumption.
A11: Other Opex inflation | B11: 0.04 | C11: 0.03 | D11: 0.02 | E11: 0.03 | F11: =CHOOSE(MATCH($B$3,$B$5:$E$5,0),B11,C11,D11,E11) -> 0.03
A13: 2026 budget uplift on 2025 budget | B13: 0.03
A15: Metric | B15: 2025 Actual | C15: 2026 Forecast | D15: Change | E15: % Change | F15: Driver applied
A16: Revenue | B16: =SUM(Finance_Raw!E:E) -> 86476517 | C16: =B16*(1+$F$6) -> 89070813 | D16: =C16-B16 -> 2594295.5 | E16: =IFERROR(D16/B16,0) -> 0.03 | F16: x (1 + revenue growth)
A17: Procurement | B17: =SUM(Finance_Raw!G:G) -> 13917019 | C17: =B17*(1-$F$7) -> 13360339 | D17: =C17-B17 -> -556680.77 | E17: =IFERROR(D17/B17,0) -> -0.04 | F17: x (1 - procurement savings)
A18: Agency | B18: =SUM(Finance_Raw!I:I) -> 1341086 | C18: =B18*(1+$F$8) -> 1408140.3 | D18: =C18-B18 -> 67054.3 | E18: =IFERROR(D18/B18,0) -> 0.05 | F18: x (1 + agency rate inflation)
A19: Fleet | B19: =SUM(Finance_Raw!H:H) -> 882007.36 | C19: =B19*(1-$F$9) -> 855547.14 | D19: =C19-B19 -> -26460.221 | E19: =IFERROR(D19/B19,0) -> -0.03 | F19: x (1 - fleet efficiency)
A20: Payroll | B20: =SUM(Finance_Raw!F:F) -> 38123646 | C20: =B20*(1+$F$10) -> 39076737 | D20: =C20-B20 -> 953091.15 | E20: =IFERROR(D20/B20,0) -> 0.025 | F20: x (1 + payroll inflation)
A21: Other Opex | B21: =SUM(Finance_Raw!J:J) -> 6089205.9 | C21: =B21*(1+$F$11) -> 6271882.1 | D21: =C21-B21 -> 182676.18 | E21: =IFERROR(D21/B21,0) -> 0.03 | F21: x (1 + other Opex inflation)
A22: Total Opex | B22: =SUM(B17:B21) -> 60352965 | C22: =SUM(C17:C21) -> 60972645 | D22: =C22-B22 -> 619680.64 | E22: =IFERROR(D22/B22,0) -> 0.010267609
A23: EBITDA | B23: =B16-B22 -> 26123553 | C23: =C16-C22 -> 28098167 | D23: =C23-B23 -> 1974614.9 | E23: =IFERROR(D23/B23,0) -> 0.075587533 | F23: =IF(ROUND(C23-INDEX($B$36:$E$36,MATCH($B$3,$B$28:$E$28,0)),0)=0,"Check: PASS","Check: FAIL") -> Check: PASS
A24: EBITDA margin | B24: =IFERROR(B23/B16,0) -> 0.3020884 | C24: =IFERROR(C23/C16,0) -> 0.31545875 | D24: =C24-B24 -> 0.013370354
A25: Budget Opex | B25: =SUM(Finance_Raw!K:K) -> 60401822 | C25: =B25*(1+$B$13) -> 62213876 | D25: =C25-B25 -> 1812054.7
A26: Opex vs budget (+ = under) | B26: =B25-B22 -> 48856.977 | C26: =C25-C22 -> 1241231
A28: Scenario comparison | B28: Conservative | C28: Base | D28: Aggressive | E28: Custom
A29: Revenue | B29: =$B$16*(1+B$6) -> 87341282 | C29: =$B$16*(1+C$6) -> 89070813 | D29: =$B$16*(1+D$6) -> 90800343 | E29: =$B$16*(1+E$6) -> 89070813
A30: Procurement | B30: =$B$17*(1-B$7) -> 13638679 | C30: =$B$17*(1-C$7) -> 13360339 | D30: =$B$17*(1-D$7) -> 12942828 | E30: =$B$17*(1-E$7) -> 13360339
A31: Agency | B31: =$B$18*(1+B$8) -> 1421551.2 | C31: =$B$18*(1+C$8) -> 1408140.3 | D31: =$B$18*(1+D$8) -> 1381318.6 | E31: =$B$18*(1+E$8) -> 1408140.3
A32: Fleet | B32: =$B$19*(1-B$9) -> 873187.29 | C32: =$B$19*(1-C$9) -> 855547.14 | D32: =$B$19*(1-D$9) -> 837906.99 | E32: =$B$19*(1-E$9) -> 855547.14
A33: Payroll | B33: =$B$20*(1+B$10) -> 39457974 | C33: =$B$20*(1+C$10) -> 39076737 | D33: =$B$20*(1+D$10) -> 38886119 | E33: =$B$20*(1+E$10) -> 39076737
A34: Other Opex | B34: =$B$21*(1+B$11) -> 6332774.2 | C34: =$B$21*(1+C$11) -> 6271882.1 | D34: =$B$21*(1+D$11) -> 6210990 | E34: =$B$21*(1+E$11) -> 6271882.1
A35: Total Opex | B35: =SUM(B30:B34) -> 61724165 | C35: =SUM(C30:C34) -> 60972645 | D35: =SUM(D30:D34) -> 60259163 | E35: =SUM(E30:E34) -> 60972645
A36: EBITDA | B36: =B29-B35 -> 25617117 | C36: =C29-C35 -> 28098167 | D36: =D29-D35 -> 30541180 | E36: =E29-E35 -> 28098167
A37: EBITDA margin | B37: =IFERROR(B36/B29,0) -> 0.29329907 | C37: =IFERROR(C36/C29,0) -> 0.31545875 | D37: =IFERROR(D36/D29,0) -> 0.33635534 | E37: =IFERROR(E36/E29,0) -> 0.31545875
A38: EBITDA vs 2025 | B38: =B36-$B$23 -> -506435.38 | C38: =C36-$B$23 -> 1974614.9 | D38: =D36-$B$23 -> 4417628 | E38: =E36-$B$23 -> 1974614.9
A41: EBITDA bridge 2025 -> 2026 | B41: Value | C41: Base | D41: Increase | E41: Decrease | F41: Total | G41: Running
A42: 2025 EBITDA | B42: =B23 -> 26123553 | C42: =0 -> 0 | D42: =0 -> 0 | E42: =0 -> 0 | F42: =B42 -> 26123553 | G42: =B42 -> 26123553 | H42: Base/Increase/Decrease/Total feed the stacked-column waterfall on the Dashboard.
A43: Revenue growth | B43: =D16 -> 2594295.5 | C43: =MIN(G42,G43) -> 26123553 | D43: =MAX(B43,0) -> 2594295.5 | E43: =MAX(-B43,0) -> 0 | F43: =0 -> 0 | G43: =G42+B43 -> 28717848
A44: Procurement savings | B44: =-D17 -> 556680.77 | C44: =MIN(G43,G44) -> 28717848 | D44: =MAX(B44,0) -> 556680.77 | E44: =MAX(-B44,0) -> 0 | F44: =0 -> 0 | G44: =G43+B44 -> 29274529
A45: Agency rate inflation | B45: =-D18 -> -67054.3 | C45: =MIN(G44,G45) -> 29207474 | D45: =MAX(B45,0) -> 0 | E45: =MAX(-B45,0) -> 67054.3 | F45: =0 -> 0 | G45: =G44+B45 -> 29207474
A46: Fleet efficiency | B46: =-D19 -> 26460.221 | C46: =MIN(G45,G46) -> 29207474 | D46: =MAX(B46,0) -> 26460.221 | E46: =MAX(-B46,0) -> 0 | F46: =0 -> 0 | G46: =G45+B46 -> 29233935
A47: Payroll inflation | B47: =-D20 -> -953091.15 | C47: =MIN(G46,G47) -> 28280844 | D47: =MAX(B47,0) -> 0 | E47: =MAX(-B47,0) -> 953091.15 | F47: =0 -> 0 | G47: =G46+B47 -> 28280844
A48: Other Opex inflation | B48: =-D21 -> -182676.18 | C48: =MIN(G47,G48) -> 28098167 | D48: =MAX(B48,0) -> 0 | E48: =MAX(-B48,0) -> 182676.18 | F48: =0 -> 0 | G48: =G47+B48 -> 28098167
A49: 2026 EBITDA | B49: =C23 -> 28098167 | C49: =0 -> 0 | D49: =0 -> 0 | E49: =0 -> 0 | F49: =B49 -> 28098167 | G49: =G48 -> 28098167 | H49: =IF(ROUND(G48-B49,0)=0,"Bridge ties: PASS","Bridge FAIL") -> Bridge ties: PASS
A52: Month (2026) | B52: 2025 Revenue | C52: 2026 Revenue | D52: 2026 Opex | E52: 2026 EBITDA | F52: Margin | G52: 2026 Budget Opex | H52: Fcst vs budget
A53: 46023 | B53: =SUMIFS(Finance_Raw!$E:$E,Finance_Raw!$A:$A,DATE(YEAR($A53)-1,MONTH($A53),1)) -> 6859245.2 | C53: =B53*(1+$F$6) -> 7065022.6 | D53: =SUMIFS(Finance_Raw!$G:$G,Finance_Raw!$A:$A,DATE(YEAR($A53)-1,MONTH($A53),1))*(1-$F$7)+SUMIFS(Finance_Raw!$I:$I,Finance_Raw!$A:$A,DATE(YEAR($A53)-1,MONTH($A53),1))*(1+$F$8)+SUMIFS(Finance_Raw!$H:$H,Finance_Raw!$A:$A,DATE(YEAR($A53)-1,MONTH($A53),1))*(1-$F$9)+SUMIFS(Finance_Raw!$F:$F,Finance_Raw!$A:$A,DATE(YEAR($A53)-1,MONTH($A53),1))*(1+$F$10)+SUMIFS(Finance_Raw!$J:$J,Finance_Raw!$A:$A,DATE(YEAR($A53)-1,MONTH($A53),1))*(1+$F$11) -> 4882180.3 | E53: =C53-D53 -> 2182842.3 | F53: =IFERROR(E53/C53,0) -> 0.30896466 | G53: =SUMIFS(Finance_Raw!$K:$K,Finance_Raw!$A:$A,DATE(YEAR($A53)-1,MONTH($A53),1))*(1+$B$13) -> 4981171.4 | H53: =G53-D53 -> 98991.127
A54: 46054 | B54: =SUMIFS(Finance_Raw!$E:$E,Finance_Raw!$A:$A,DATE(YEAR($A54)-1,MONTH($A54),1)) -> 7476589.8 | C54: =B54*(1+$F$6) -> 7700887.5 | D54: =SUMIFS(Finance_Raw!$G:$G,Finance_Raw!$A:$A,DATE(YEAR($A54)-1,MONTH($A54),1))*(1-$F$7)+SUMIFS(Finance_Raw!$I:$I,Finance_Raw!$A:$A,DATE(YEAR($A54)-1,MONTH($A54),1))*(1+$F$8)+SUMIFS(Finance_Raw!$H:$H,Finance_Raw!$A:$A,DATE(YEAR($A54)-1,MONTH($A54),1))*(1-$F$9)+SUMIFS(Finance_Raw!$F:$F,Finance_Raw!$A:$A,DATE(YEAR($A54)-1,MONTH($A54),1))*(1+$F$10)+SUMIFS(Finance_Raw!$J:$J,Finance_Raw!$A:$A,DATE(YEAR($A54)-1,MONTH($A54),1))*(1+$F$11) -> 5298655.9 | E54: =C54-D54 -> 2402231.6 | F54: =IFERROR(E54/C54,0) -> 0.31194217 | G54: =SUMIFS(Finance_Raw!$K:$K,Finance_Raw!$A:$A,DATE(YEAR($A54)-1,MONTH($A54),1))*(1+$B$13) -> 5425050.9 | H54: =G54-D54 -> 126395.02
A55: 46082 | B55: =SUMIFS(Finance_Raw!$E:$E,Finance_Raw!$A:$A,DATE(YEAR($A55)-1,MONTH($A55),1)) -> 7345583.3 | C55: =B55*(1+$F$6) -> 7565950.8 | D55: =SUMIFS(Finance_Raw!$G:$G,Finance_Raw!$A:$A,DATE(YEAR($A55)-1,MONTH($A55),1))*(1-$F$7)+SUMIFS(Finance_Raw!$I:$I,Finance_Raw!$A:$A,DATE(YEAR($A55)-1,MONTH($A55),1))*(1+$F$8)+SUMIFS(Finance_Raw!$H:$H,Finance_Raw!$A:$A,DATE(YEAR($A55)-1,MONTH($A55),1))*(1-$F$9)+SUMIFS(Finance_Raw!$F:$F,Finance_Raw!$A:$A,DATE(YEAR($A55)-1,MONTH($A55),1))*(1+$F$10)+SUMIFS(Finance_Raw!$J:$J,Finance_Raw!$A:$A,DATE(YEAR($A55)-1,MONTH($A55),1))*(1+$F$11) -> 5132220.6 | E55: =C55-D55 -> 2433730.3 | F55: =IFERROR(E55/C55,0) -> 0.32166879 | G55: =SUMIFS(Finance_Raw!$K:$K,Finance_Raw!$A:$A,DATE(YEAR($A55)-1,MONTH($A55),1))*(1+$B$13) -> 5248672.3 | H55: =G55-D55 -> 116451.73
A56: 46113 | B56: =SUMIFS(Finance_Raw!$E:$E,Finance_Raw!$A:$A,DATE(YEAR($A56)-1,MONTH($A56),1)) -> 7658852.2 | C56: =B56*(1+$F$6) -> 7888617.8 | D56: =SUMIFS(Finance_Raw!$G:$G,Finance_Raw!$A:$A,DATE(YEAR($A56)-1,MONTH($A56),1))*(1-$F$7)+SUMIFS(Finance_Raw!$I:$I,Finance_Raw!$A:$A,DATE(YEAR($A56)-1,MONTH($A56),1))*(1+$F$8)+SUMIFS(Finance_Raw!$H:$H,Finance_Raw!$A:$A,DATE(YEAR($A56)-1,MONTH($A56),1))*(1-$F$9)+SUMIFS(Finance_Raw!$F:$F,Finance_Raw!$A:$A,DATE(YEAR($A56)-1,MONTH($A56),1))*(1+$F$10)+SUMIFS(Finance_Raw!$J:$J,Finance_Raw!$A:$A,DATE(YEAR($A56)-1,MONTH($A56),1))*(1+$F$11) -> 5332055.3 | E56: =C56-D56 -> 2556562.5 | F56: =IFERROR(E56/C56,0) -> 0.32408244 | G56: =SUMIFS(Finance_Raw!$K:$K,Finance_Raw!$A:$A,DATE(YEAR($A56)-1,MONTH($A56),1))*(1+$B$13) -> 5393766.6 | H56: =G56-D56 -> 61711.298
A57: 46143 | B57: =SUMIFS(Finance_Raw!$E:$E,Finance_Raw!$A:$A,DATE(YEAR($A57)-1,MONTH($A57),1)) -> 6576496.4 | C57: =B57*(1+$F$6) -> 6773791.3 | D57: =SUMIFS(Finance_Raw!$G:$G,Finance_Raw!$A:$A,DATE(YEAR($A57)-1,MONTH($A57),1))*(1-$F$7)+SUMIFS(Finance_Raw!$I:$I,Finance_Raw!$A:$A,DATE(YEAR($A57)-1,MONTH($A57),1))*(1+$F$8)+SUMIFS(Finance_Raw!$H:$H,Finance_Raw!$A:$A,DATE(YEAR($A57)-1,MONTH($A57),1))*(1-$F$9)+SUMIFS(Finance_Raw!$F:$F,Finance_Raw!$A:$A,DATE(YEAR($A57)-1,MONTH($A57),1))*(1+$F$10)+SUMIFS(Finance_Raw!$J:$J,Finance_Raw!$A:$A,DATE(YEAR($A57)-1,MONTH($A57),1))*(1+$F$11) -> 4597062.1 | E57: =C57-D57 -> 2176729.2 | F57: =IFERROR(E57/C57,0) -> 0.32134577 | G57: =SUMIFS(Finance_Raw!$K:$K,Finance_Raw!$A:$A,DATE(YEAR($A57)-1,MONTH($A57),1))*(1+$B$13) -> 4699501 | H57: =G57-D57 -> 102438.85
A58: 46174 | B58: =SUMIFS(Finance_Raw!$E:$E,Finance_Raw!$A:$A,DATE(YEAR($A58)-1,MONTH($A58),1)) -> 7065637.8 | C58: =B58*(1+$F$6) -> 7277607 | D58: =SUMIFS(Finance_Raw!$G:$G,Finance_Raw!$A:$A,DATE(YEAR($A58)-1,MONTH($A58),1))*(1-$F$7)+SUMIFS(Finance_Raw!$I:$I,Finance_Raw!$A:$A,DATE(YEAR($A58)-1,MONTH($A58),1))*(1+$F$8)+SUMIFS(Finance_Raw!$H:$H,Finance_Raw!$A:$A,DATE(YEAR($A58)-1,MONTH($A58),1))*(1-$F$9)+SUMIFS(Finance_Raw!$F:$F,Finance_Raw!$A:$A,DATE(YEAR($A58)-1,MONTH($A58),1))*(1+$F$10)+SUMIFS(Finance_Raw!$J:$J,Finance_Raw!$A:$A,DATE(YEAR($A58)-1,MONTH($A58),1))*(1+$F$11) -> 4973152.4 | E58: =C58-D58 -> 2304454.6 | F58: =IFERROR(E58/C58,0) -> 0.31665004 | G58: =SUMIFS(Finance_Raw!$K:$K,Finance_Raw!$A:$A,DATE(YEAR($A58)-1,MONTH($A58),1))*(1+$B$13) -> 5054557.9 | H58: =G58-D58 -> 81405.532
A59: 46204 | B59: =SUMIFS(Finance_Raw!$E:$E,Finance_Raw!$A:$A,DATE(YEAR($A59)-1,MONTH($A59),1)) -> 6953277 | C59: =B59*(1+$F$6) -> 7161875.3 | D59: =SUMIFS(Finance_Raw!$G:$G,Finance_Raw!$A:$A,DATE(YEAR($A59)-1,MONTH($A59),1))*(1-$F$7)+SUMIFS(Finance_Raw!$I:$I,Finance_Raw!$A:$A,DATE(YEAR($A59)-1,MONTH($A59),1))*(1+$F$8)+SUMIFS(Finance_Raw!$H:$H,Finance_Raw!$A:$A,DATE(YEAR($A59)-1,MONTH($A59),1))*(1-$F$9)+SUMIFS(Finance_Raw!$F:$F,Finance_Raw!$A:$A,DATE(YEAR($A59)-1,MONTH($A59),1))*(1+$F$10)+SUMIFS(Finance_Raw!$J:$J,Finance_Raw!$A:$A,DATE(YEAR($A59)-1,MONTH($A59),1))*(1+$F$11) -> 4916046.2 | E59: =C59-D59 -> 2245829.1 | F59: =IFERROR(E59/C59,0) -> 0.31358115 | G59: =SUMIFS(Finance_Raw!$K:$K,Finance_Raw!$A:$A,DATE(YEAR($A59)-1,MONTH($A59),1))*(1+$B$13) -> 5045173 | H59: =G59-D59 -> 129126.77
A60: 46235 | B60: =SUMIFS(Finance_Raw!$E:$E,Finance_Raw!$A:$A,DATE(YEAR($A60)-1,MONTH($A60),1)) -> 7044378.2 | C60: =B60*(1+$F$6) -> 7255709.5 | D60: =SUMIFS(Finance_Raw!$G:$G,Finance_Raw!$A:$A,DATE(YEAR($A60)-1,MONTH($A60),1))*(1-$F$7)+SUMIFS(Finance_Raw!$I:$I,Finance_Raw!$A:$A,DATE(YEAR($A60)-1,MONTH($A60),1))*(1+$F$8)+SUMIFS(Finance_Raw!$H:$H,Finance_Raw!$A:$A,DATE(YEAR($A60)-1,MONTH($A60),1))*(1-$F$9)+SUMIFS(Finance_Raw!$F:$F,Finance_Raw!$A:$A,DATE(YEAR($A60)-1,MONTH($A60),1))*(1+$F$10)+SUMIFS(Finance_Raw!$J:$J,Finance_Raw!$A:$A,DATE(YEAR($A60)-1,MONTH($A60),1))*(1+$F$11) -> 5041592.1 | E60: =C60-D60 -> 2214117.4 | F60: =IFERROR(E60/C60,0) -> 0.30515519 | G60: =SUMIFS(Finance_Raw!$K:$K,Finance_Raw!$A:$A,DATE(YEAR($A60)-1,MONTH($A60),1))*(1+$B$13) -> 5143658.5 | H60: =G60-D60 -> 102066.39
A61: 46266 | B61: =SUMIFS(Finance_Raw!$E:$E,Finance_Raw!$A:$A,DATE(YEAR($A61)-1,MONTH($A61),1)) -> 6899634.7 | C61: =B61*(1+$F$6) -> 7106623.7 | D61: =SUMIFS(Finance_Raw!$G:$G,Finance_Raw!$A:$A,DATE(YEAR($A61)-1,MONTH($A61),1))*(1-$F$7)+SUMIFS(Finance_Raw!$I:$I,Finance_Raw!$A:$A,DATE(YEAR($A61)-1,MONTH($A61),1))*(1+$F$8)+SUMIFS(Finance_Raw!$H:$H,Finance_Raw!$A:$A,DATE(YEAR($A61)-1,MONTH($A61),1))*(1-$F$9)+SUMIFS(Finance_Raw!$F:$F,Finance_Raw!$A:$A,DATE(YEAR($A61)-1,MONTH($A61),1))*(1+$F$10)+SUMIFS(Finance_Raw!$J:$J,Finance_Raw!$A:$A,DATE(YEAR($A61)-1,MONTH($A61),1))*(1+$F$11) -> 4877532 | E61: =C61-D61 -> 2229091.7 | F61: =IFERROR(E61/C61,0) -> 0.31366395 | G61: =SUMIFS(Finance_Raw!$K:$K,Finance_Raw!$A:$A,DATE(YEAR($A61)-1,MONTH($A61),1))*(1+$B$13) -> 4996523 | H61: =G61-D61 -> 118990.96
A62: 46296 | B62: =SUMIFS(Finance_Raw!$E:$E,Finance_Raw!$A:$A,DATE(YEAR($A62)-1,MONTH($A62),1)) -> 8051254.3 | C62: =B62*(1+$F$6) -> 8292791.9 | D62: =SUMIFS(Finance_Raw!$G:$G,Finance_Raw!$A:$A,DATE(YEAR($A62)-1,MONTH($A62),1))*(1-$F$7)+SUMIFS(Finance_Raw!$I:$I,Finance_Raw!$A:$A,DATE(YEAR($A62)-1,MONTH($A62),1))*(1+$F$8)+SUMIFS(Finance_Raw!$H:$H,Finance_Raw!$A:$A,DATE(YEAR($A62)-1,MONTH($A62),1))*(1-$F$9)+SUMIFS(Finance_Raw!$F:$F,Finance_Raw!$A:$A,DATE(YEAR($A62)-1,MONTH($A62),1))*(1+$F$10)+SUMIFS(Finance_Raw!$J:$J,Finance_Raw!$A:$A,DATE(YEAR($A62)-1,MONTH($A62),1))*(1+$F$11) -> 5602224.8 | E62: =C62-D62 -> 2690567.1 | F62: =IFERROR(E62/C62,0) -> 0.32444647 | G62: =SUMIFS(Finance_Raw!$K:$K,Finance_Raw!$A:$A,DATE(YEAR($A62)-1,MONTH($A62),1))*(1+$B$13) -> 5759438.9 | H62: =G62-D62 -> 157214.08
A63: 46327 | B63: =SUMIFS(Finance_Raw!$E:$E,Finance_Raw!$A:$A,DATE(YEAR($A63)-1,MONTH($A63),1)) -> 6479152 | C63: =B63*(1+$F$6) -> 6673526.6 | D63: =SUMIFS(Finance_Raw!$G:$G,Finance_Raw!$A:$A,DATE(YEAR($A63)-1,MONTH($A63),1))*(1-$F$7)+SUMIFS(Finance_Raw!$I:$I,Finance_Raw!$A:$A,DATE(YEAR($A63)-1,MONTH($A63),1))*(1+$F$8)+SUMIFS(Finance_Raw!$H:$H,Finance_Raw!$A:$A,DATE(YEAR($A63)-1,MONTH($A63),1))*(1-$F$9)+SUMIFS(Finance_Raw!$F:$F,Finance_Raw!$A:$A,DATE(YEAR($A63)-1,MONTH($A63),1))*(1+$F$10)+SUMIFS(Finance_Raw!$J:$J,Finance_Raw!$A:$A,DATE(YEAR($A63)-1,MONTH($A63),1))*(1+$F$11) -> 4661944.3 | E63: =C63-D63 -> 2011582.3 | F63: =IFERROR(E63/C63,0) -> 0.30142718 | G63: =SUMIFS(Finance_Raw!$K:$K,Finance_Raw!$A:$A,DATE(YEAR($A63)-1,MONTH($A63),1))*(1+$B$13) -> 4723560.1 | H63: =G63-D63 -> 61615.827
A64: 46357 | B64: =SUMIFS(Finance_Raw!$E:$E,Finance_Raw!$A:$A,DATE(YEAR($A64)-1,MONTH($A64),1)) -> 8066416.4 | C64: =B64*(1+$F$6) -> 8308408.8 | D64: =SUMIFS(Finance_Raw!$G:$G,Finance_Raw!$A:$A,DATE(YEAR($A64)-1,MONTH($A64),1))*(1-$F$7)+SUMIFS(Finance_Raw!$I:$I,Finance_Raw!$A:$A,DATE(YEAR($A64)-1,MONTH($A64),1))*(1+$F$8)+SUMIFS(Finance_Raw!$H:$H,Finance_Raw!$A:$A,DATE(YEAR($A64)-1,MONTH($A64),1))*(1-$F$9)+SUMIFS(Finance_Raw!$F:$F,Finance_Raw!$A:$A,DATE(YEAR($A64)-1,MONTH($A64),1))*(1+$F$10)+SUMIFS(Finance_Raw!$J:$J,Finance_Raw!$A:$A,DATE(YEAR($A64)-1,MONTH($A64),1))*(1+$F$11) -> 5657979.3 | E64: =C64-D64 -> 2650429.5 | F64: =IFERROR(E64/C64,0) -> 0.31900567 | G64: =SUMIFS(Finance_Raw!$K:$K,Finance_Raw!$A:$A,DATE(YEAR($A64)-1,MONTH($A64),1))*(1+$B$13) -> 5742802.8 | H64: =G64-D64 -> 84823.416
A65: FY 2026 | B65: =SUM(B53:B64) -> 86476517 | C65: =SUM(C53:C64) -> 89070813 | D65: =SUM(D53:D64) -> 60972645 | E65: =SUM(E53:E64) -> 28098167 | F65: =IFERROR(E65/C65,0) -> 0.31545875 | G65: =SUM(G53:G64) -> 62213876 | H65: =SUM(H53:H64) -> 1241231 | I65: =IF(AND(ROUND(C65-C16,0)=0,ROUND(D65-C22,0)=0),"Ties to annual: PASS","Ties to annual: FAIL") -> Ties to annual: PASS
A68: Sensitivity 1: 2026 EBITDA by revenue growth (rows) and procurement savings (columns); other drivers as selected | H68: Sensitivity 2: EBITDA by payroll inflation (rows) and agency rate inflation (columns)
A69: Growth \ Savings | B69: 0 | C69: 0.02 | D69: 0.04 | E69: 0.06 | F69: 0.08 | H69: Payroll \ Agency | I69: 0 | J69: 0.025 | K69: 0.05 | L69: 0.075 | M69: 0.1
A70: 0 | B70: =$B$16*(1+$A70)-($B$17*(1-B$69)+$C$18+$C$19+$C$20+$C$21) -> 24947191 | C70: =$B$16*(1+$A70)-($B$17*(1-C$69)+$C$18+$C$19+$C$20+$C$21) -> 25225531 | D70: =$B$16*(1+$A70)-($B$17*(1-D$69)+$C$18+$C$19+$C$20+$C$21) -> 25503872 | E70: =$B$16*(1+$A70)-($B$17*(1-E$69)+$C$18+$C$19+$C$20+$C$21) -> 25782212 | F70: =$B$16*(1+$A70)-($B$17*(1-F$69)+$C$18+$C$19+$C$20+$C$21) -> 26060553 | H70: 0.01 | I70: =$C$16-($C$17+$B$18*(1+I$69)+$C$19+$B$20*(1+$H70)+$C$21) -> 28737076 | J70: =$C$16-($C$17+$B$18*(1+J$69)+$C$19+$B$20*(1+$H70)+$C$21) -> 28703549 | K70: =$C$16-($C$17+$B$18*(1+K$69)+$C$19+$B$20*(1+$H70)+$C$21) -> 28670022 | L70: =$C$16-($C$17+$B$18*(1+L$69)+$C$19+$B$20*(1+$H70)+$C$21) -> 28636495 | M70: =$C$16-($C$17+$B$18*(1+M$69)+$C$19+$B$20*(1+$H70)+$C$21) -> 28602968
A71: 0.01 | B71: =$B$16*(1+$A71)-($B$17*(1-B$69)+$C$18+$C$19+$C$20+$C$21) -> 25811956 | C71: =$B$16*(1+$A71)-($B$17*(1-C$69)+$C$18+$C$19+$C$20+$C$21) -> 26090297 | D71: =$B$16*(1+$A71)-($B$17*(1-D$69)+$C$18+$C$19+$C$20+$C$21) -> 26368637 | E71: =$B$16*(1+$A71)-($B$17*(1-E$69)+$C$18+$C$19+$C$20+$C$21) -> 26646977 | F71: =$B$16*(1+$A71)-($B$17*(1-F$69)+$C$18+$C$19+$C$20+$C$21) -> 26925318 | H71: 0.015 | I71: =$C$16-($C$17+$B$18*(1+I$69)+$C$19+$B$20*(1+$H71)+$C$21) -> 28546458 | J71: =$C$16-($C$17+$B$18*(1+J$69)+$C$19+$B$20*(1+$H71)+$C$21) -> 28512931 | K71: =$C$16-($C$17+$B$18*(1+K$69)+$C$19+$B$20*(1+$H71)+$C$21) -> 28479404 | L71: =$C$16-($C$17+$B$18*(1+L$69)+$C$19+$B$20*(1+$H71)+$C$21) -> 28445877 | M71: =$C$16-($C$17+$B$18*(1+M$69)+$C$19+$B$20*(1+$H71)+$C$21) -> 28412350
A72: 0.02 | B72: =$B$16*(1+$A72)-($B$17*(1-B$69)+$C$18+$C$19+$C$20+$C$21) -> 26676721 | C72: =$B$16*(1+$A72)-($B$17*(1-C$69)+$C$18+$C$19+$C$20+$C$21) -> 26955062 | D72: =$B$16*(1+$A72)-($B$17*(1-D$69)+$C$18+$C$19+$C$20+$C$21) -> 27233402 | E72: =$B$16*(1+$A72)-($B$17*(1-E$69)+$C$18+$C$19+$C$20+$C$21) -> 27511743 | F72: =$B$16*(1+$A72)-($B$17*(1-F$69)+$C$18+$C$19+$C$20+$C$21) -> 27790083 | H72: 0.02 | I72: =$C$16-($C$17+$B$18*(1+I$69)+$C$19+$B$20*(1+$H72)+$C$21) -> 28355840 | J72: =$C$16-($C$17+$B$18*(1+J$69)+$C$19+$B$20*(1+$H72)+$C$21) -> 28322313 | K72: =$C$16-($C$17+$B$18*(1+K$69)+$C$19+$B$20*(1+$H72)+$C$21) -> 28288786 | L72: =$C$16-($C$17+$B$18*(1+L$69)+$C$19+$B$20*(1+$H72)+$C$21) -> 28255258 | M72: =$C$16-($C$17+$B$18*(1+M$69)+$C$19+$B$20*(1+$H72)+$C$21) -> 28221731
A73: 0.03 | B73: =$B$16*(1+$A73)-($B$17*(1-B$69)+$C$18+$C$19+$C$20+$C$21) -> 27541487 | C73: =$B$16*(1+$A73)-($B$17*(1-C$69)+$C$18+$C$19+$C$20+$C$21) -> 27819827 | D73: =$B$16*(1+$A73)-($B$17*(1-D$69)+$C$18+$C$19+$C$20+$C$21) -> 28098167 | E73: =$B$16*(1+$A73)-($B$17*(1-E$69)+$C$18+$C$19+$C$20+$C$21) -> 28376508 | F73: =$B$16*(1+$A73)-($B$17*(1-F$69)+$C$18+$C$19+$C$20+$C$21) -> 28654848 | H73: 0.025 | I73: =$C$16-($C$17+$B$18*(1+I$69)+$C$19+$B$20*(1+$H73)+$C$21) -> 28165222 | J73: =$C$16-($C$17+$B$18*(1+J$69)+$C$19+$B$20*(1+$H73)+$C$21) -> 28131695 | K73: =$C$16-($C$17+$B$18*(1+K$69)+$C$19+$B$20*(1+$H73)+$C$21) -> 28098167 | L73: =$C$16-($C$17+$B$18*(1+L$69)+$C$19+$B$20*(1+$H73)+$C$21) -> 28064640 | M73: =$C$16-($C$17+$B$18*(1+M$69)+$C$19+$B$20*(1+$H73)+$C$21) -> 28031113
A74: 0.04 | B74: =$B$16*(1+$A74)-($B$17*(1-B$69)+$C$18+$C$19+$C$20+$C$21) -> 28406252 | C74: =$B$16*(1+$A74)-($B$17*(1-C$69)+$C$18+$C$19+$C$20+$C$21) -> 28684592 | D74: =$B$16*(1+$A74)-($B$17*(1-D$69)+$C$18+$C$19+$C$20+$C$21) -> 28962933 | E74: =$B$16*(1+$A74)-($B$17*(1-E$69)+$C$18+$C$19+$C$20+$C$21) -> 29241273 | F74: =$B$16*(1+$A74)-($B$17*(1-F$69)+$C$18+$C$19+$C$20+$C$21) -> 29519613 | H74: 0.03 | I74: =$C$16-($C$17+$B$18*(1+I$69)+$C$19+$B$20*(1+$H74)+$C$21) -> 27974603 | J74: =$C$16-($C$17+$B$18*(1+J$69)+$C$19+$B$20*(1+$H74)+$C$21) -> 27941076 | K74: =$C$16-($C$17+$B$18*(1+K$69)+$C$19+$B$20*(1+$H74)+$C$21) -> 27907549 | L74: =$C$16-($C$17+$B$18*(1+L$69)+$C$19+$B$20*(1+$H74)+$C$21) -> 27874022 | M74: =$C$16-($C$17+$B$18*(1+M$69)+$C$19+$B$20*(1+$H74)+$C$21) -> 27840495
A75: 0.05 | B75: =$B$16*(1+$A75)-($B$17*(1-B$69)+$C$18+$C$19+$C$20+$C$21) -> 29271017 | C75: =$B$16*(1+$A75)-($B$17*(1-C$69)+$C$18+$C$19+$C$20+$C$21) -> 29549357 | D75: =$B$16*(1+$A75)-($B$17*(1-D$69)+$C$18+$C$19+$C$20+$C$21) -> 29827698 | E75: =$B$16*(1+$A75)-($B$17*(1-E$69)+$C$18+$C$19+$C$20+$C$21) -> 30106038 | F75: =$B$16*(1+$A75)-($B$17*(1-F$69)+$C$18+$C$19+$C$20+$C$21) -> 30384379 | H75: 0.035 | I75: =$C$16-($C$17+$B$18*(1+I$69)+$C$19+$B$20*(1+$H75)+$C$21) -> 27783985 | J75: =$C$16-($C$17+$B$18*(1+J$69)+$C$19+$B$20*(1+$H75)+$C$21) -> 27750458 | K75: =$C$16-($C$17+$B$18*(1+K$69)+$C$19+$B$20*(1+$H75)+$C$21) -> 27716931 | L75: =$C$16-($C$17+$B$18*(1+L$69)+$C$19+$B$20*(1+$H75)+$C$21) -> 27683404 | M75: =$C$16-($C$17+$B$18*(1+M$69)+$C$19+$B$20*(1+$H75)+$C$21) -> 27649877
A76: 0.06 | B76: =$B$16*(1+$A76)-($B$17*(1-B$69)+$C$18+$C$19+$C$20+$C$21) -> 30135782 | C76: =$B$16*(1+$A76)-($B$17*(1-C$69)+$C$18+$C$19+$C$20+$C$21) -> 30414123 | D76: =$B$16*(1+$A76)-($B$17*(1-D$69)+$C$18+$C$19+$C$20+$C$21) -> 30692463 | E76: =$B$16*(1+$A76)-($B$17*(1-E$69)+$C$18+$C$19+$C$20+$C$21) -> 30970803 | F76: =$B$16*(1+$A76)-($B$17*(1-F$69)+$C$18+$C$19+$C$20+$C$21) -> 31249144 | H76: 0.04 | I76: =$C$16-($C$17+$B$18*(1+I$69)+$C$19+$B$20*(1+$H76)+$C$21) -> 27593367 | J76: =$C$16-($C$17+$B$18*(1+J$69)+$C$19+$B$20*(1+$H76)+$C$21) -> 27559840 | K76: =$C$16-($C$17+$B$18*(1+K$69)+$C$19+$B$20*(1+$H76)+$C$21) -> 27526313 | L76: =$C$16-($C$17+$B$18*(1+L$69)+$C$19+$B$20*(1+$H76)+$C$21) -> 27492786 | M76: =$C$16-($C$17+$B$18*(1+M$69)+$C$19+$B$20*(1+$H76)+$C$21) -> 27459258
A78: ="Each 1pt of payroll inflation moves EBITDA by "&TEXT($B$20*0.01,"£#,##0")&", each 1pt of procurement saving is worth "&TEXT($B$17*0.01,"£#,##0")&" and each 1pt of agency rate inflation "&TEXT($B$18*0.01,"£#,##0")&". The payroll base is "&TEXT($B$20/$B$17,"0.0")&"x the procurement base, so pay settlements move EBITDA more than any sourcing deal." -> Each 1pt of payroll inflation moves EBITDA by £381,236, each 1pt of procurement saving is worth £139,170 and each 1pt of agency rate inflation £13,411. The payroll base is 2.7x the procurement base, so pay settlements move EBITDA more than any sourcing deal.

Sheet Savings_Tracker
A1: Commercial Savings Tracker (2026 plan vs delivery)
A2: Target = 2025 category spend x target %. Realised YTD values are the monthly input from the savings register (blue cells).
A4: Months elapsed (YTD to Aug-2026) | C4: 8
A5: Status thresholds: On Target >= 100% of target, Watch >= | C5: 0.75
A6: Category | B6: Owner | C6: 2025 Spend | D6: Target % | E6: Target saving | F6: Realised YTD | G6: FY forecast | H6: % of target | I6: Status | J6: Gap to target
A7: Medical Supplies | B7: =IFERROR(INDEX(Category_Targets!$C$2:$C$9,MATCH(A7,Category_Targets!$A$2:$A$9,0)),"") -> Procurement | C7: =SUMIFS(Cleaned_Procurement!$O$2:$O$1801,Cleaned_Procurement!$F$2:$F$1801,A7) -> 1097153 | D7: =IFERROR(INDEX(Category_Targets!$B$2:$B$9,MATCH(A7,Category_Targets!$A$2:$A$9,0)),0) -> 0.06 | E7: =C7*D7 -> 65829.181 | F7: 46100 | G7: =IFERROR(F7/$C$4*12,0) -> 69150 | H7: =IFERROR(G7/E7,0) -> 1.050446 | I7: =IF(H7>=1,"On Target",IF(H7>=$C$5,"Watch","Off Track")) -> On Target | J7: =E7-G7 -> -3320.8194
A8: Food & Catering | B8: =IFERROR(INDEX(Category_Targets!$C$2:$C$9,MATCH(A8,Category_Targets!$A$2:$A$9,0)),"") -> Procurement | C8: =SUMIFS(Cleaned_Procurement!$O$2:$O$1801,Cleaned_Procurement!$F$2:$F$1801,A8) -> 837713.63 | D8: =IFERROR(INDEX(Category_Targets!$B$2:$B$9,MATCH(A8,Category_Targets!$A$2:$A$9,0)),0) -> 0.04 | E8: =C8*D8 -> 33508.545 | F8: 20100 | G8: =IFERROR(F8/$C$4*12,0) -> 30150 | H8: =IFERROR(G8/E8,0) -> 0.89977049 | I8: =IF(H8>=1,"On Target",IF(H8>=$C$5,"Watch","Off Track")) -> Watch | J8: =E8-G8 -> 3358.5452
A9: Facilities | B9: =IFERROR(INDEX(Category_Targets!$C$2:$C$9,MATCH(A9,Category_Targets!$A$2:$A$9,0)),"") -> Facilities | C9: =SUMIFS(Cleaned_Procurement!$O$2:$O$1801,Cleaned_Procurement!$F$2:$F$1801,A9) -> 2128780.9 | D9: =IFERROR(INDEX(Category_Targets!$B$2:$B$9,MATCH(A9,Category_Targets!$A$2:$A$9,0)),0) -> 0.05 | E9: =C9*D9 -> 106439.05 | F9: 49700 | G9: =IFERROR(F9/$C$4*12,0) -> 74550 | H9: =IFERROR(G9/E9,0) -> 0.70040086 | I9: =IF(H9>=1,"On Target",IF(H9>=$C$5,"Watch","Off Track")) -> Off Track | J9: =E9-G9 -> 31889.046
A10: Utilities | B10: =IFERROR(INDEX(Category_Targets!$C$2:$C$9,MATCH(A10,Category_Targets!$A$2:$A$9,0)),"") -> Procurement | C10: =SUMIFS(Cleaned_Procurement!$O$2:$O$1801,Cleaned_Procurement!$F$2:$F$1801,A10) -> 2401261.6 | D10: =IFERROR(INDEX(Category_Targets!$B$2:$B$9,MATCH(A10,Category_Targets!$A$2:$A$9,0)),0) -> 0.03 | E10: =C10*D10 -> 72037.848 | F10: 52800 | G10: =IFERROR(F10/$C$4*12,0) -> 79200 | H10: =IFERROR(G10/E10,0) -> 1.0994221 | I10: =IF(H10>=1,"On Target",IF(H10>=$C$5,"Watch","Off Track")) -> On Target | J10: =E10-G10 -> -7162.152
A11: IT & Telecoms | B11: =IFERROR(INDEX(Category_Targets!$C$2:$C$9,MATCH(A11,Category_Targets!$A$2:$A$9,0)),"") -> IT | C11: =SUMIFS(Cleaned_Procurement!$O$2:$O$1801,Cleaned_Procurement!$F$2:$F$1801,A11) -> 2505155.2 | D11: =IFERROR(INDEX(Category_Targets!$B$2:$B$9,MATCH(A11,Category_Targets!$A$2:$A$9,0)),0) -> 0.08 | E11: =C11*D11 -> 200412.41 | F11: 106900 | G11: =IFERROR(F11/$C$4*12,0) -> 160350 | H11: =IFERROR(G11/E11,0) -> 0.80010014 | I11: =IF(H11>=1,"On Target",IF(H11>=$C$5,"Watch","Off Track")) -> Watch | J11: =E11-G11 -> 40062.414
A12: Vehicle & Fuel | B12: =IFERROR(INDEX(Category_Targets!$C$2:$C$9,MATCH(A12,Category_Targets!$A$2:$A$9,0)),"") -> Fleet | C12: =SUMIFS(Cleaned_Procurement!$O$2:$O$1801,Cleaned_Procurement!$F$2:$F$1801,A12) -> 1030620.3 | D12: =IFERROR(INDEX(Category_Targets!$B$2:$B$9,MATCH(A12,Category_Targets!$A$2:$A$9,0)),0) -> 0.05 | E12: =C12*D12 -> 51531.015 | F12: 32600 | G12: =IFERROR(F12/$C$4*12,0) -> 48900 | H12: =IFERROR(G12/E12,0) -> 0.94894308 | I12: =IF(H12>=1,"On Target",IF(H12>=$C$5,"Watch","Off Track")) -> Watch | J12: =E12-G12 -> 2631.015
A13: Agency Labour | B13: =IFERROR(INDEX(Category_Targets!$C$2:$C$9,MATCH(A13,Category_Targets!$A$2:$A$9,0)),"") -> Workforce | C13: =SUMIFS(Cleaned_Procurement!$O$2:$O$1801,Cleaned_Procurement!$F$2:$F$1801,A13) -> 3193367.1 | D13: =IFERROR(INDEX(Category_Targets!$B$2:$B$9,MATCH(A13,Category_Targets!$A$2:$A$9,0)),0) -> 0.07 | E13: =C13*D13 -> 223535.7 | F13: 89400 | G13: =IFERROR(F13/$C$4*12,0) -> 134100 | H13: =IFERROR(G13/E13,0) -> 0.59990418 | I13: =IF(H13>=1,"On Target",IF(H13>=$C$5,"Watch","Off Track")) -> Off Track | J13: =E13-G13 -> 89435.7
A14: Office & Training | B14: =IFERROR(INDEX(Category_Targets!$C$2:$C$9,MATCH(A14,Category_Targets!$A$2:$A$9,0)),"") -> Commercial | C14: =SUMIFS(Cleaned_Procurement!$O$2:$O$1801,Cleaned_Procurement!$F$2:$F$1801,A14) -> 728629.96 | D14: =IFERROR(INDEX(Category_Targets!$B$2:$B$9,MATCH(A14,Category_Targets!$A$2:$A$9,0)),0) -> 0.04 | E14: =C14*D14 -> 29145.198 | F14: 23300 | G14: =IFERROR(F14/$C$4*12,0) -> 34950 | H14: =IFERROR(G14/E14,0) -> 1.1991684 | I14: =IF(H14>=1,"On Target",IF(H14>=$C$5,"Watch","Off Track")) -> On Target | J14: =E14-G14 -> -5804.8016
A15: Total | C15: =SUM(C7:C14) -> 13922682 | D15: =IFERROR(E15/C15,0) -> 0.056198868 | E15: =SUM(E7:E14) -> 782438.95 | F15: =SUM(F7:F14) -> 420900 | G15: =SUM(G7:G14) -> 631350 | H15: =IFERROR(G15/E15,0) -> 0.80690002 | I15: =IF(H15>=1,"On Target",IF(H15>=$C$5,"Watch","Off Track")) -> Watch | J15: =SUM(J7:J14) -> 151088.95
A17: Status count
A18: On Target | B18: =COUNTIF($I$7:$I$14,A18) -> 3
A19: Watch | B19: =COUNTIF($I$7:$I$14,A19) -> 3
A20: Off Track | B20: =COUNTIF($I$7:$I$14,A20) -> 2
A22: ="Biggest gap: "&INDEX(A7:A14,MATCH(MAX(J7:J14),J7:J14,0))&" is forecast "&TEXT(MAX(J7:J14),"£#,##0")&" short of target. Plan delivers "&TEXT(H15,"0%")&" of the "&TEXT(E15,"£#,##0")&" target." -> Biggest gap: Agency Labour is forecast £89,436 short of target. Plan delivers 81% of the £782,439 target.

Sheet Site_Performance
A1: Site Performance: Budget vs Actual Opex and EBITDA (2025)
A2: Variance = Budget - Actual (positive is favourable). RAG thresholds are inputs.
A4: SiteID | B4: Site | C4: Region | D4: Revenue | E4: Actual Opex | F4: Budget Opex | G4: Variance | H4: Var % | I4: EBITDA margin | J4: Margin rank | K4: Status | L4: RAG thresholds
A5: =Sites!A2 -> S001 | B5: =Sites!B2 -> Preston Care & Education Centre | C5: =Sites!C2 -> North | D5: =SUMIFS(Finance_Raw!$E:$E,Finance_Raw!$B:$B,A5) -> 4539947.5 | E5: =SUMIFS(Finance_Raw!$L:$L,Finance_Raw!$B:$B,A5) -> 3138939.4 | F5: =SUMIFS(Finance_Raw!$K:$K,Finance_Raw!$B:$B,A5) -> 3118796.1 | G5: =F5-E5 -> -20143.333 | H5: =IFERROR(G5/F5,0) -> -0.0064586888 | I5: =IFERROR((D5-E5)/D5,0) -> 0.30859567 | J5: =RANK(I5,$I$5:$I$24,0) -> 4 | K5: =IF(H5<$N$5,"Red",IF(H5<$N$6,"Amber","Green")) -> Amber | L5: Red if overspend worse than | N5: -0.01
A6: =Sites!A3 -> S002 | B6: =Sites!B3 -> Manchester Care & Education Centre | C6: =Sites!C3 -> North | D6: =SUMIFS(Finance_Raw!$E:$E,Finance_Raw!$B:$B,A6) -> 4350391.7 | E6: =SUMIFS(Finance_Raw!$L:$L,Finance_Raw!$B:$B,A6) -> 3074525.5 | F6: =SUMIFS(Finance_Raw!$K:$K,Finance_Raw!$B:$B,A6) -> 3061502.2 | G6: =F6-E6 -> -13023.317 | H6: =IFERROR(G6/F6,0) -> -0.0042538976 | I6: =IFERROR((D6-E6)/D6,0) -> 0.29327617 | J6: =RANK(I6,$I$5:$I$24,0) -> 18 | K6: =IF(H6<$N$5,"Red",IF(H6<$N$6,"Amber","Green")) -> Amber | L6: Amber if overspend worse than | N6: 0
A7: =Sites!A4 -> S003 | B7: =Sites!B4 -> Leeds Care & Education Centre | C7: =Sites!C4 -> North | D7: =SUMIFS(Finance_Raw!$E:$E,Finance_Raw!$B:$B,A7) -> 4134779.6 | E7: =SUMIFS(Finance_Raw!$L:$L,Finance_Raw!$B:$B,A7) -> 2879265.3 | F7: =SUMIFS(Finance_Raw!$K:$K,Finance_Raw!$B:$B,A7) -> 2864950.6 | G7: =F7-E7 -> -14314.657 | H7: =IFERROR(G7/F7,0) -> -0.0049964758 | I7: =IFERROR((D7-E7)/D7,0) -> 0.30364722 | J7: =RANK(I7,$I$5:$I$24,0) -> 10 | K7: =IF(H7<$N$5,"Red",IF(H7<$N$6,"Amber","Green")) -> Amber
A8: =Sites!A5 -> S004 | B8: =Sites!B5 -> Newcastle Care & Education Centre | C8: =Sites!C5 -> North | D8: =SUMIFS(Finance_Raw!$E:$E,Finance_Raw!$B:$B,A8) -> 4200462.6 | E8: =SUMIFS(Finance_Raw!$L:$L,Finance_Raw!$B:$B,A8) -> 2957894.8 | F8: =SUMIFS(Finance_Raw!$K:$K,Finance_Raw!$B:$B,A8) -> 2968153.1 | G8: =F8-E8 -> 10258.353 | H8: =IFERROR(G8/F8,0) -> 0.0034561402 | I8: =IFERROR((D8-E8)/D8,0) -> 0.2958169 | J8: =RANK(I8,$I$5:$I$24,0) -> 15 | K8: =IF(H8<$N$5,"Red",IF(H8<$N$6,"Amber","Green")) -> Green
A9: =Sites!A6 -> S005 | B9: =Sites!B6 -> Sheffield Care & Education Centre | C9: =Sites!C6 -> North | D9: =SUMIFS(Finance_Raw!$E:$E,Finance_Raw!$B:$B,A9) -> 4381089 | E9: =SUMIFS(Finance_Raw!$L:$L,Finance_Raw!$B:$B,A9) -> 3097200.8 | F9: =SUMIFS(Finance_Raw!$K:$K,Finance_Raw!$B:$B,A9) -> 3107939.5 | G9: =F9-E9 -> 10738.757 | H9: =IFERROR(G9/F9,0) -> 0.0034552656 | I9: =IFERROR((D9-E9)/D9,0) -> 0.2930523 | J9: =RANK(I9,$I$5:$I$24,0) -> 19 | K9: =IF(H9<$N$5,"Red",IF(H9<$N$6,"Amber","Green")) -> Green
A10: =Sites!A7 -> S006 | B10: =Sites!B7 -> Birmingham Care & Education Centre | C10: =Sites!C7 -> Midlands | D10: =SUMIFS(Finance_Raw!$E:$E,Finance_Raw!$B:$B,A10) -> 4302157.3 | E10: =SUMIFS(Finance_Raw!$L:$L,Finance_Raw!$B:$B,A10) -> 2999128.9 | F10: =SUMIFS(Finance_Raw!$K:$K,Finance_Raw!$B:$B,A10) -> 2991112.8 | G10: =F10-E10 -> -8016.1267 | H10: =IFERROR(G10/F10,0) -> -0.0026799814 | I10: =IFERROR((D10-E10)/D10,0) -> 0.30287791 | J10: =RANK(I10,$I$5:$I$24,0) -> 11 | K10: =IF(H10<$N$5,"Red",IF(H10<$N$6,"Amber","Green")) -> Amber
A11: =Sites!A8 -> S007 | B11: =Sites!B8 -> Nottingham Care & Education Centre | C11: =Sites!C8 -> Midlands | D11: =SUMIFS(Finance_Raw!$E:$E,Finance_Raw!$B:$B,A11) -> 4817411.2 | E11: =SUMIFS(Finance_Raw!$L:$L,Finance_Raw!$B:$B,A11) -> 3311125.2 | F11: =SUMIFS(Finance_Raw!$K:$K,Finance_Raw!$B:$B,A11) -> 3322611.7 | G11: =F11-E11 -> 11486.46 | H11: =IFERROR(G11/F11,0) -> 0.0034570576 | I11: =IFERROR((D11-E11)/D11,0) -> 0.3126754 | J11: =RANK(I11,$I$5:$I$24,0) -> 1 | K11: =IF(H11<$N$5,"Red",IF(H11<$N$6,"Amber","Green")) -> Green
A12: =Sites!A9 -> S008 | B12: =Sites!B9 -> Leicester Care & Education Centre | C12: =Sites!C9 -> Midlands | D12: =SUMIFS(Finance_Raw!$E:$E,Finance_Raw!$B:$B,A12) -> 4703410.5 | E12: =SUMIFS(Finance_Raw!$L:$L,Finance_Raw!$B:$B,A12) -> 3272108.8 | F12: =SUMIFS(Finance_Raw!$K:$K,Finance_Raw!$B:$B,A12) -> 3251343.4 | G12: =F12-E12 -> -20765.33 | H12: =IFERROR(G12/F12,0) -> -0.0063866923 | I12: =IFERROR((D12-E12)/D12,0) -> 0.30431146 | J12: =RANK(I12,$I$5:$I$24,0) -> 9 | K12: =IF(H12<$N$5,"Red",IF(H12<$N$6,"Amber","Green")) -> Amber
A13: =Sites!A10 -> S009 | B13: =Sites!B10 -> Derby Care & Education Centre | C13: =Sites!C10 -> Midlands | D13: =SUMIFS(Finance_Raw!$E:$E,Finance_Raw!$B:$B,A13) -> 4279128.7 | E13: =SUMIFS(Finance_Raw!$L:$L,Finance_Raw!$B:$B,A13) -> 3005077.6 | F13: =SUMIFS(Finance_Raw!$K:$K,Finance_Raw!$B:$B,A13) -> 2989752.7 | G13: =F13-E13 -> -15324.877 | H13: =IFERROR(G13/F13,0) -> -0.0051258008 | I13: =IFERROR((D13-E13)/D13,0) -> 0.29773611 | J13: =RANK(I13,$I$5:$I$24,0) -> 14 | K13: =IF(H13<$N$5,"Red",IF(H13<$N$6,"Amber","Green")) -> Amber
A14: =Sites!A11 -> S010 | B14: =Sites!B11 -> Coventry Care & Education Centre | C14: =Sites!C11 -> Midlands | D14: =SUMIFS(Finance_Raw!$E:$E,Finance_Raw!$B:$B,A14) -> 4038599.6 | E14: =SUMIFS(Finance_Raw!$L:$L,Finance_Raw!$B:$B,A14) -> 2816401.3 | F14: =SUMIFS(Finance_Raw!$K:$K,Finance_Raw!$B:$B,A14) -> 2835552 | G14: =F14-E14 -> 19150.647 | H14: =IFERROR(G14/F14,0) -> 0.0067537633 | I14: =IFERROR((D14-E14)/D14,0) -> 0.30262923 | J14: =RANK(I14,$I$5:$I$24,0) -> 12 | K14: =IF(H14<$N$5,"Red",IF(H14<$N$6,"Amber","Green")) -> Green
A15: =Sites!A12 -> S011 | B15: =Sites!B12 -> London Care & Education Centre | C15: =Sites!C12 -> South | D15: =SUMIFS(Finance_Raw!$E:$E,Finance_Raw!$B:$B,A15) -> 4422526.7 | E15: =SUMIFS(Finance_Raw!$L:$L,Finance_Raw!$B:$B,A15) -> 3059307.4 | F15: =SUMIFS(Finance_Raw!$K:$K,Finance_Raw!$B:$B,A15) -> 3064550.7 | G15: =F15-E15 -> 5243.3367 | H15: =IFERROR(G15/F15,0) -> 0.0017109642 | I15: =IFERROR((D15-E15)/D15,0) -> 0.30824445 | J15: =RANK(I15,$I$5:$I$24,0) -> 5 | K15: =IF(H15<$N$5,"Red",IF(H15<$N$6,"Amber","Green")) -> Green
A16: =Sites!A13 -> S012 | B16: =Sites!B13 -> Bristol Care & Education Centre | C16: =Sites!C13 -> South | D16: =SUMIFS(Finance_Raw!$E:$E,Finance_Raw!$B:$B,A16) -> 4289982.2 | E16: =SUMIFS(Finance_Raw!$L:$L,Finance_Raw!$B:$B,A16) -> 2963438.8 | F16: =SUMIFS(Finance_Raw!$K:$K,Finance_Raw!$B:$B,A16) -> 2994092.4 | G16: =F16-E16 -> 30653.617 | H16: =IFERROR(G16/F16,0) -> 0.010238033 | I16: =IFERROR((D16-E16)/D16,0) -> 0.30921887 | J16: =RANK(I16,$I$5:$I$24,0) -> 3 | K16: =IF(H16<$N$5,"Red",IF(H16<$N$6,"Amber","Green")) -> Green
A17: =Sites!A14 -> S013 | B17: =Sites!B14 -> Reading Care & Education Centre | C17: =Sites!C14 -> South | D17: =SUMIFS(Finance_Raw!$E:$E,Finance_Raw!$B:$B,A17) -> 4471092.7 | E17: =SUMIFS(Finance_Raw!$L:$L,Finance_Raw!$B:$B,A17) -> 3097431.9 | F17: =SUMIFS(Finance_Raw!$K:$K,Finance_Raw!$B:$B,A17) -> 3101674.4 | G17: =F17-E17 -> 4242.4367 | H17: =IFERROR(G17/F17,0) -> 0.0013677892 | I17: =IFERROR((D17-E17)/D17,0) -> 0.30723155 | J17: =RANK(I17,$I$5:$I$24,0) -> 6 | K17: =IF(H17<$N$5,"Red",IF(H17<$N$6,"Amber","Green")) -> Green
A18: =Sites!A15 -> S014 | B18: =Sites!B15 -> Southampton Care & Education Centre | C18: =Sites!C15 -> South | D18: =SUMIFS(Finance_Raw!$E:$E,Finance_Raw!$B:$B,A18) -> 4273113.4 | E18: =SUMIFS(Finance_Raw!$L:$L,Finance_Raw!$B:$B,A18) -> 2968785.6 | F18: =SUMIFS(Finance_Raw!$K:$K,Finance_Raw!$B:$B,A18) -> 2974770 | G18: =F18-E18 -> 5984.32 | H18: =IFERROR(G18/F18,0) -> 0.0020116917 | I18: =IFERROR((D18-E18)/D18,0) -> 0.30524061 | J18: =RANK(I18,$I$5:$I$24,0) -> 8 | K18: =IF(H18<$N$5,"Red",IF(H18<$N$6,"Amber","Green")) -> Green
... A24: =Sites!A21 -> S020 | B24: =Sites!B21 -> Bangor Care & Education Centre | C24: =Sites!C21 -> Wales | D24: =SUMIFS(Finance_Raw!$E:$E,Finance_Raw!$B:$B,A24) -> 4785341.9 | E24: =SUMIFS(Finance_Raw!$L:$L,Finance_Raw!$B:$B,A24) -> 3304982.8 | F24: =SUMIFS(Finance_Raw!$K:$K,Finance_Raw!$B:$B,A24) -> 3304204.3 | G24: =F24-E24 -> -778.49333 | H24: =IFERROR(G24/F24,0) -> -0.0002356069 | I24: =IFERROR((D24-E24)/D24,0) -> 0.30935285 | J24: =RANK(I24,$I$5:$I$24,0) -> 2 | K24: =IF(H24<$N$5,"Red",IF(H24<$N$6,"Amber","Green")) -> Amber
A25: Total | D25: =SUM(D5:D24) -> 86476517 | E25: =SUM(E5:E24) -> 60352965 | F25: =SUM(F5:F24) -> 60401822 | G25: =SUM(G5:G24) -> 48856.977 | H25: =IFERROR(G25/F25,0) -> 0.00080886595 | I25: =IFERROR((D25-E25)/D25,0) -> 0.3020884
A27: ="Sites over budget: "&COUNTIF(K5:K24,"Red")&" red, "&COUNTIF(K5:K24,"Amber")&" amber. Weakest margin: "&INDEX(B5:B24,MATCH(20,J5:J24,0))&" ("&TEXT(MIN(I5:I24),"0.0%")&"); strongest: "&INDEX(B5:B24,MATCH(1,J5:J24,0))&" ("&TEXT(MAX(I5:I24),"0.0%")&")." -> Sites over budget: 0 red, 8 amber. Weakest margin: Brighton Care & Education Centre (28.9%); strongest: Nottingham Care & Education Centre (31.3%).

Sheet Ops_Analysis
A1: Fleet, Workforce & Agency Analysis (2025, monthly)
A2: Unit-cost KPIs that commercial teams track: cost per mile, overtime share, agency share of staff cost, absence per FTE.
A4: Month | B4: Miles | C4: Fuel cost | D4: Total fleet cost | E4: Cost / mile | F4: FTE | G4: Total payroll | H4: Overtime cost | I4: OT % payroll | J4: Absence days | K4: Absence / FTE | L4: Agency hours | M4: Agency spend | N4: Avg agency rate | O4: Agency % staff cost
A5: 45658 | B5: =SUMIFS(Fleet_Raw!$G:$G,Fleet_Raw!$A:$A,$A5) -> 97426 | C5: =SUMIFS(Fleet_Raw!$I:$I,Fleet_Raw!$A:$A,$A5) -> 15380.86 | D5: =SUMIFS(Fleet_Raw!$L:$L,Fleet_Raw!$A:$A,$A5) -> 70737.9 | E5: =IFERROR(D5/B5,0) -> 0.72606799 | F5: =SUMIFS(Workforce_Raw!$F:$F,Workforce_Raw!$A:$A,$A5) -> 1059.7 | G5: =SUMIFS(Workforce_Raw!$L:$L,Workforce_Raw!$A:$A,$A5) -> 3034099.2 | H5: =SUMIFS(Workforce_Raw!$I:$I,Workforce_Raw!$A:$A,$A5) -> 86782.57 | I5: =IFERROR(H5/G5,0) -> 0.028602416 | J5: =SUMIFS(Workforce_Raw!$J:$J,Workforce_Raw!$A:$A,$A5) -> 512.7 | K5: =IFERROR(J5/F5,0) -> 0.48381617 | L5: =SUMIFS(Agency_Raw!$G:$G,Agency_Raw!$A:$A,$A5) -> 3650 | M5: =SUMIFS(Agency_Raw!$I:$I,Agency_Raw!$A:$A,$A5) -> 107437 | N5: =IFERROR(M5/L5,0) -> 29.434795 | O5: =IFERROR(M5/(M5+G5),0) -> 0.034198873
A6: 45689 | B6: =SUMIFS(Fleet_Raw!$G:$G,Fleet_Raw!$A:$A,$A6) -> 100940 | C6: =SUMIFS(Fleet_Raw!$I:$I,Fleet_Raw!$A:$A,$A6) -> 15703.06 | D6: =SUMIFS(Fleet_Raw!$L:$L,Fleet_Raw!$A:$A,$A6) -> 75544.4 | E6: =IFERROR(D6/B6,0) -> 0.74840896 | F6: =SUMIFS(Workforce_Raw!$F:$F,Workforce_Raw!$A:$A,$A6) -> 1243.9 | G6: =SUMIFS(Workforce_Raw!$L:$L,Workforce_Raw!$A:$A,$A6) -> 3447818.4 | H6: =SUMIFS(Workforce_Raw!$I:$I,Workforce_Raw!$A:$A,$A6) -> 96726.69 | I6: =IFERROR(H6/G6,0) -> 0.028054462 | J6: =SUMIFS(Workforce_Raw!$J:$J,Workforce_Raw!$A:$A,$A6) -> 621.5 | K6: =IFERROR(J6/F6,0) -> 0.49963823 | L6: =SUMIFS(Agency_Raw!$G:$G,Agency_Raw!$A:$A,$A6) -> 3915 | M6: =SUMIFS(Agency_Raw!$I:$I,Agency_Raw!$A:$A,$A6) -> 121421 | N6: =IFERROR(M6/L6,0) -> 31.014304 | O6: =IFERROR(M6/(M6+G6),0) -> 0.034018733
A7: 45717 | B7: =SUMIFS(Fleet_Raw!$G:$G,Fleet_Raw!$A:$A,$A7) -> 101802 | C7: =SUMIFS(Fleet_Raw!$I:$I,Fleet_Raw!$A:$A,$A7) -> 15989.06 | D7: =SUMIFS(Fleet_Raw!$L:$L,Fleet_Raw!$A:$A,$A7) -> 74481.71 | E7: =IFERROR(D7/B7,0) -> 0.73163307 | F7: =SUMIFS(Workforce_Raw!$F:$F,Workforce_Raw!$A:$A,$A7) -> 1129 | G7: =SUMIFS(Workforce_Raw!$L:$L,Workforce_Raw!$A:$A,$A7) -> 3105246.8 | H7: =SUMIFS(Workforce_Raw!$I:$I,Workforce_Raw!$A:$A,$A7) -> 96705.13 | I7: =IFERROR(H7/G7,0) -> 0.031142494 | J7: =SUMIFS(Workforce_Raw!$J:$J,Workforce_Raw!$A:$A,$A7) -> 567.5 | K7: =IFERROR(J7/F7,0) -> 0.50265722 | L7: =SUMIFS(Agency_Raw!$G:$G,Agency_Raw!$A:$A,$A7) -> 3446 | M7: =SUMIFS(Agency_Raw!$I:$I,Agency_Raw!$A:$A,$A7) -> 103588 | N7: =IFERROR(M7/L7,0) -> 30.06036 | O7: =IFERROR(M7/(M7+G7),0) -> 0.032282123
A8: 45748 | B8: =SUMIFS(Fleet_Raw!$G:$G,Fleet_Raw!$A:$A,$A8) -> 108281 | C8: =SUMIFS(Fleet_Raw!$I:$I,Fleet_Raw!$A:$A,$A8) -> 17231.37 | D8: =SUMIFS(Fleet_Raw!$L:$L,Fleet_Raw!$A:$A,$A8) -> 78410.89 | E8: =IFERROR(D8/B8,0) -> 0.72414265 | F8: =SUMIFS(Workforce_Raw!$F:$F,Workforce_Raw!$A:$A,$A8) -> 1164 | G8: =SUMIFS(Workforce_Raw!$L:$L,Workforce_Raw!$A:$A,$A8) -> 3307047.1 | H8: =SUMIFS(Workforce_Raw!$I:$I,Workforce_Raw!$A:$A,$A8) -> 96930.42 | I8: =IFERROR(H8/G8,0) -> 0.029310263 | J8: =SUMIFS(Workforce_Raw!$J:$J,Workforce_Raw!$A:$A,$A8) -> 575 | K8: =IFERROR(J8/F8,0) -> 0.49398625 | L8: =SUMIFS(Agency_Raw!$G:$G,Agency_Raw!$A:$A,$A8) -> 4275 | M8: =SUMIFS(Agency_Raw!$I:$I,Agency_Raw!$A:$A,$A8) -> 132145 | N8: =IFERROR(M8/L8,0) -> 30.911111 | O8: =IFERROR(M8/(M8+G8),0) -> 0.038423268
A9: 45778 | B9: =SUMIFS(Fleet_Raw!$G:$G,Fleet_Raw!$A:$A,$A9) -> 107794 | C9: =SUMIFS(Fleet_Raw!$I:$I,Fleet_Raw!$A:$A,$A9) -> 17162.95 | D9: =SUMIFS(Fleet_Raw!$L:$L,Fleet_Raw!$A:$A,$A9) -> 76044.3 | E9: =IFERROR(D9/B9,0) -> 0.70545949 | F9: =SUMIFS(Workforce_Raw!$F:$F,Workforce_Raw!$A:$A,$A9) -> 1062 | G9: =SUMIFS(Workforce_Raw!$L:$L,Workforce_Raw!$A:$A,$A9) -> 2990128.1 | H9: =SUMIFS(Workforce_Raw!$I:$I,Workforce_Raw!$A:$A,$A9) -> 87244.73 | I9: =IFERROR(H9/G9,0) -> 0.02917759 | J9: =SUMIFS(Workforce_Raw!$J:$J,Workforce_Raw!$A:$A,$A9) -> 541.7 | K9: =IFERROR(J9/F9,0) -> 0.51007533 | L9: =SUMIFS(Agency_Raw!$G:$G,Agency_Raw!$A:$A,$A9) -> 3122 | M9: =SUMIFS(Agency_Raw!$I:$I,Agency_Raw!$A:$A,$A9) -> 99849 | N9: =IFERROR(M9/L9,0) -> 31.982383 | O9: =IFERROR(M9/(M9+G9),0) -> 0.032313832
A10: 45809 | B10: =SUMIFS(Fleet_Raw!$G:$G,Fleet_Raw!$A:$A,$A10) -> 98456 | C10: =SUMIFS(Fleet_Raw!$I:$I,Fleet_Raw!$A:$A,$A10) -> 15588.25 | D10: =SUMIFS(Fleet_Raw!$L:$L,Fleet_Raw!$A:$A,$A10) -> 71812.63 | E10: =IFERROR(D10/B10,0) -> 0.72938805 | F10: =SUMIFS(Workforce_Raw!$F:$F,Workforce_Raw!$A:$A,$A10) -> 1107.2 | G10: =SUMIFS(Workforce_Raw!$L:$L,Workforce_Raw!$A:$A,$A10) -> 3139595.7 | H10: =SUMIFS(Workforce_Raw!$I:$I,Workforce_Raw!$A:$A,$A10) -> 93237.38 | I10: =IFERROR(H10/G10,0) -> 0.029697257 | J10: =SUMIFS(Workforce_Raw!$J:$J,Workforce_Raw!$A:$A,$A10) -> 555.5 | K10: =IFERROR(J10/F10,0) -> 0.50171604 | L10: =SUMIFS(Agency_Raw!$G:$G,Agency_Raw!$A:$A,$A10) -> 3325 | M10: =SUMIFS(Agency_Raw!$I:$I,Agency_Raw!$A:$A,$A10) -> 106117 | N10: =IFERROR(M10/L10,0) -> 31.914887 | O10: =IFERROR(M10/(M10+G10),0) -> 0.032694514
A11: 45839 | B11: =SUMIFS(Fleet_Raw!$G:$G,Fleet_Raw!$A:$A,$A11) -> 89990 | C11: =SUMIFS(Fleet_Raw!$I:$I,Fleet_Raw!$A:$A,$A11) -> 14538.67 | D11: =SUMIFS(Fleet_Raw!$L:$L,Fleet_Raw!$A:$A,$A11) -> 68464.21 | E11: =IFERROR(D11/B11,0) -> 0.76079798 | F11: =SUMIFS(Workforce_Raw!$F:$F,Workforce_Raw!$A:$A,$A11) -> 1030.6 | G11: =SUMIFS(Workforce_Raw!$L:$L,Workforce_Raw!$A:$A,$A11) -> 2935268.2 | H11: =SUMIFS(Workforce_Raw!$I:$I,Workforce_Raw!$A:$A,$A11) -> 76968.2 | I11: =IFERROR(H11/G11,0) -> 0.026221863 | J11: =SUMIFS(Workforce_Raw!$J:$J,Workforce_Raw!$A:$A,$A11) -> 510.6 | K11: =IFERROR(J11/F11,0) -> 0.49543955 | L11: =SUMIFS(Agency_Raw!$G:$G,Agency_Raw!$A:$A,$A11) -> 3831 | M11: =SUMIFS(Agency_Raw!$I:$I,Agency_Raw!$A:$A,$A11) -> 118232 | N11: =IFERROR(M11/L11,0) -> 30.861916 | O11: =IFERROR(M11/(M11+G11),0) -> 0.038720155
A12: 45870 | B12: =SUMIFS(Fleet_Raw!$G:$G,Fleet_Raw!$A:$A,$A12) -> 102951 | C12: =SUMIFS(Fleet_Raw!$I:$I,Fleet_Raw!$A:$A,$A12) -> 16353.71 | D12: =SUMIFS(Fleet_Raw!$L:$L,Fleet_Raw!$A:$A,$A12) -> 76668.93 | E12: =IFERROR(D12/B12,0) -> 0.74471282 | F12: =SUMIFS(Workforce_Raw!$F:$F,Workforce_Raw!$A:$A,$A12) -> 1169.8 | G12: =SUMIFS(Workforce_Raw!$L:$L,Workforce_Raw!$A:$A,$A12) -> 3316445.3 | H12: =SUMIFS(Workforce_Raw!$I:$I,Workforce_Raw!$A:$A,$A12) -> 99012 | I12: =IFERROR(H12/G12,0) -> 0.029854857 | J12: =SUMIFS(Workforce_Raw!$J:$J,Workforce_Raw!$A:$A,$A12) -> 581 | K12: =IFERROR(J12/F12,0) -> 0.4966661 | L12: =SUMIFS(Agency_Raw!$G:$G,Agency_Raw!$A:$A,$A12) -> 3215 | M12: =SUMIFS(Agency_Raw!$I:$I,Agency_Raw!$A:$A,$A12) -> 99862 | N12: =IFERROR(M12/L12,0) -> 31.061275 | O12: =IFERROR(M12/(M12+G12),0) -> 0.029230977
A13: 45901 | B13: =SUMIFS(Fleet_Raw!$G:$G,Fleet_Raw!$A:$A,$A13) -> 96045 | C13: =SUMIFS(Fleet_Raw!$I:$I,Fleet_Raw!$A:$A,$A13) -> 15328.05 | D13: =SUMIFS(Fleet_Raw!$L:$L,Fleet_Raw!$A:$A,$A13) -> 67510.39 | E13: =IFERROR(D13/B13,0) -> 0.70290374 | F13: =SUMIFS(Workforce_Raw!$F:$F,Workforce_Raw!$A:$A,$A13) -> 1113.7 | G13: =SUMIFS(Workforce_Raw!$L:$L,Workforce_Raw!$A:$A,$A13) -> 3167691.7 | H13: =SUMIFS(Workforce_Raw!$I:$I,Workforce_Raw!$A:$A,$A13) -> 87250.03 | I13: =IFERROR(H13/G13,0) -> 0.027543725 | J13: =SUMIFS(Workforce_Raw!$J:$J,Workforce_Raw!$A:$A,$A13) -> 533.3 | K13: =IFERROR(J13/F13,0) -> 0.47885427 | L13: =SUMIFS(Agency_Raw!$G:$G,Agency_Raw!$A:$A,$A13) -> 3980 | M13: =SUMIFS(Agency_Raw!$I:$I,Agency_Raw!$A:$A,$A13) -> 120617 | N13: =IFERROR(M13/L13,0) -> 30.305779 | O13: =IFERROR(M13/(M13+G13),0) -> 0.036680559
A14: 45931 | B14: =SUMIFS(Fleet_Raw!$G:$G,Fleet_Raw!$A:$A,$A14) -> 104371 | C14: =SUMIFS(Fleet_Raw!$I:$I,Fleet_Raw!$A:$A,$A14) -> 16513.5 | D14: =SUMIFS(Fleet_Raw!$L:$L,Fleet_Raw!$A:$A,$A14) -> 74269.95 | E14: =IFERROR(D14/B14,0) -> 0.71159565 | F14: =SUMIFS(Workforce_Raw!$F:$F,Workforce_Raw!$A:$A,$A14) -> 1177.8 | G14: =SUMIFS(Workforce_Raw!$L:$L,Workforce_Raw!$A:$A,$A14) -> 3324296.6 | H14: =SUMIFS(Workforce_Raw!$I:$I,Workforce_Raw!$A:$A,$A14) -> 108904.98 | I14: =IFERROR(H14/G14,0) -> 0.032760307 | J14: =SUMIFS(Workforce_Raw!$J:$J,Workforce_Raw!$A:$A,$A14) -> 587.3 | K14: =IFERROR(J14/F14,0) -> 0.49864154 | L14: =SUMIFS(Agency_Raw!$G:$G,Agency_Raw!$A:$A,$A14) -> 3462 | M14: =SUMIFS(Agency_Raw!$I:$I,Agency_Raw!$A:$A,$A14) -> 103394 | N14: =IFERROR(M14/L14,0) -> 29.865396 | O14: =IFERROR(M14/(M14+G14),0) -> 0.030164332
A15: 45962 | B15: =SUMIFS(Fleet_Raw!$G:$G,Fleet_Raw!$A:$A,$A15) -> 99939 | C15: =SUMIFS(Fleet_Raw!$I:$I,Fleet_Raw!$A:$A,$A15) -> 15667.1 | D15: =SUMIFS(Fleet_Raw!$L:$L,Fleet_Raw!$A:$A,$A15) -> 74181.37 | E15: =IFERROR(D15/B15,0) -> 0.74226648 | F15: =SUMIFS(Workforce_Raw!$F:$F,Workforce_Raw!$A:$A,$A15) -> 1095.2 | G15: =SUMIFS(Workforce_Raw!$L:$L,Workforce_Raw!$A:$A,$A15) -> 3031071.7 | H15: =SUMIFS(Workforce_Raw!$I:$I,Workforce_Raw!$A:$A,$A15) -> 91455.04 | I15: =IFERROR(H15/G15,0) -> 0.03017251 | J15: =SUMIFS(Workforce_Raw!$J:$J,Workforce_Raw!$A:$A,$A15) -> 538.4 | K15: =IFERROR(J15/F15,0) -> 0.49159971 | L15: =SUMIFS(Agency_Raw!$G:$G,Agency_Raw!$A:$A,$A15) -> 3417 | M15: =SUMIFS(Agency_Raw!$I:$I,Agency_Raw!$A:$A,$A15) -> 109315 | N15: =IFERROR(M15/L15,0) -> 31.991513 | O15: =IFERROR(M15/(M15+G15),0) -> 0.034809407
A16: 45992 | B16: =SUMIFS(Fleet_Raw!$G:$G,Fleet_Raw!$A:$A,$A16) -> 104534 | C16: =SUMIFS(Fleet_Raw!$I:$I,Fleet_Raw!$A:$A,$A16) -> 16488.05 | D16: =SUMIFS(Fleet_Raw!$L:$L,Fleet_Raw!$A:$A,$A16) -> 73880.68 | E16: =IFERROR(D16/B16,0) -> 0.7067622 | F16: =SUMIFS(Workforce_Raw!$F:$F,Workforce_Raw!$A:$A,$A16) -> 1206.5 | G16: =SUMIFS(Workforce_Raw!$L:$L,Workforce_Raw!$A:$A,$A16) -> 3324937.3 | H16: =SUMIFS(Workforce_Raw!$I:$I,Workforce_Raw!$A:$A,$A16) -> 95670.62 | I16: =IFERROR(H16/G16,0) -> 0.028773662 | J16: =SUMIFS(Workforce_Raw!$J:$J,Workforce_Raw!$A:$A,$A16) -> 596.4 | K16: =IFERROR(J16/F16,0) -> 0.49432242 | L16: =SUMIFS(Agency_Raw!$G:$G,Agency_Raw!$A:$A,$A16) -> 3898 | M16: =SUMIFS(Agency_Raw!$I:$I,Agency_Raw!$A:$A,$A16) -> 119109 | N16: =IFERROR(M16/L16,0) -> 30.556439 | O16: =IFERROR(M16/(M16+G16),0) -> 0.03458403
A17: FY 2025 | B17: =SUM(B5:B16) -> 1212529 | C17: =SUM(C5:C16) -> 191944.63 | D17: =SUM(D5:D16) -> 882007.36 | E17: =IFERROR(D17/B17,0) -> 0.72741135 | F17: =AVERAGE(F5:F16) -> 1129.95 | G17: =SUM(G5:G16) -> 38123646 | H17: =SUM(H5:H16) -> 1116887.8 | I17: =IFERROR(H17/G17,0) -> 0.029296458 | J17: =SUM(J5:J16) -> 6720.9 | K17: =IFERROR(J17/F17,0) -> 5.9479623 | L17: =SUM(L5:L16) -> 43536 | M17: =SUM(M5:M16) -> 1341086 | N17: =IFERROR(M17/L17,0) -> 30.80407 | O17: =IFERROR(M17/(M17+G17),0) -> 0.033981885
A20: By region | J20: Cost per mile by vehicle type
A21: Region | B21: Fleet cost | C21: Cost / mile | D21: Payroll | E21: OT % payroll | F21: Agency spend | G21: Agency % staff cost | H21: Absence / FTE | J21: Vehicle type | K21: Miles | L21: Total cost | M21: Cost / mile
A22: North | B22: =SUMIFS(Fleet_Raw!$L:$L,Fleet_Raw!$D:$D,A22) -> 217356.61 | C22: =IFERROR(B22/SUMIFS(Fleet_Raw!$G:$G,Fleet_Raw!$D:$D,A22),0) -> 0.70925416 | D22: =SUMIFS(Workforce_Raw!$L:$L,Workforce_Raw!$D:$D,A22) -> 9715710 | E22: =IFERROR(SUMIFS(Workforce_Raw!$I:$I,Workforce_Raw!$D:$D,A22)/D22,0) -> 0.030082033 | F22: =SUMIFS(Agency_Raw!$I:$I,Agency_Raw!$D:$D,A22) -> 344891 | G22: =IFERROR(F22/(F22+D22),0) -> 0.034281352 | H22: =IFERROR(SUMIFS(Workforce_Raw!$J:$J,Workforce_Raw!$D:$D,A22)/(SUMIFS(Workforce_Raw!$F:$F,Workforce_Raw!$D:$D,A22)/12),0) -> 5.9661135 | J22: Car | K22: =SUMIFS(Fleet_Raw!$G:$G,Fleet_Raw!$F:$F,J22) -> 280500 | L22: =SUMIFS(Fleet_Raw!$L:$L,Fleet_Raw!$F:$F,J22) -> 192618.59 | M22: =IFERROR(L22/K22,0) -> 0.68669729
A23: Midlands | B23: =SUMIFS(Fleet_Raw!$L:$L,Fleet_Raw!$D:$D,A23) -> 211540.15 | C23: =IFERROR(B23/SUMIFS(Fleet_Raw!$G:$G,Fleet_Raw!$D:$D,A23),0) -> 0.7440449 | D23: =SUMIFS(Workforce_Raw!$L:$L,Workforce_Raw!$D:$D,A23) -> 9763624.5 | E23: =IFERROR(SUMIFS(Workforce_Raw!$I:$I,Workforce_Raw!$D:$D,A23)/D23,0) -> 0.029567176 | F23: =SUMIFS(Agency_Raw!$I:$I,Agency_Raw!$D:$D,A23) -> 361621 | G23: =IFERROR(F23/(F23+D23),0) -> 0.035714788 | H23: =IFERROR(SUMIFS(Workforce_Raw!$J:$J,Workforce_Raw!$D:$D,A23)/(SUMIFS(Workforce_Raw!$F:$F,Workforce_Raw!$D:$D,A23)/12),0) -> 5.8570724 | J23: Van | K23: =SUMIFS(Fleet_Raw!$G:$G,Fleet_Raw!$F:$F,J23) -> 323951 | L23: =SUMIFS(Fleet_Raw!$L:$L,Fleet_Raw!$F:$F,J23) -> 234814.65 | M23: =IFERROR(L23/K23,0) -> 0.7248462
A24: South | B24: =SUMIFS(Fleet_Raw!$L:$L,Fleet_Raw!$D:$D,A24) -> 215340 | C24: =IFERROR(B24/SUMIFS(Fleet_Raw!$G:$G,Fleet_Raw!$D:$D,A24),0) -> 0.74304111 | D24: =SUMIFS(Workforce_Raw!$L:$L,Workforce_Raw!$D:$D,A24) -> 9333500.1 | E24: =IFERROR(SUMIFS(Workforce_Raw!$I:$I,Workforce_Raw!$D:$D,A24)/D24,0) -> 0.029021814 | F24: =SUMIFS(Agency_Raw!$I:$I,Agency_Raw!$D:$D,A24) -> 327359 | G24: =IFERROR(F24/(F24+D24),0) -> 0.033885082 | H24: =IFERROR(SUMIFS(Workforce_Raw!$J:$J,Workforce_Raw!$D:$D,A24)/(SUMIFS(Workforce_Raw!$F:$F,Workforce_Raw!$D:$D,A24)/12),0) -> 5.933522 | J24: MPV | K24: =SUMIFS(Fleet_Raw!$G:$G,Fleet_Raw!$F:$F,J24) -> 297722 | L24: =SUMIFS(Fleet_Raw!$L:$L,Fleet_Raw!$F:$F,J24) -> 202571 | M24: =IFERROR(L24/K24,0) -> 0.68040319
A25: Wales | B25: =SUMIFS(Fleet_Raw!$L:$L,Fleet_Raw!$D:$D,A25) -> 237770.6 | C25: =IFERROR(B25/SUMIFS(Fleet_Raw!$G:$G,Fleet_Raw!$D:$D,A25),0) -> 0.71628222 | D25: =SUMIFS(Workforce_Raw!$L:$L,Workforce_Raw!$D:$D,A25) -> 9310811.6 | E25: =IFERROR(SUMIFS(Workforce_Raw!$I:$I,Workforce_Raw!$D:$D,A25)/D25,0) -> 0.02846815 | F25: =SUMIFS(Agency_Raw!$I:$I,Agency_Raw!$D:$D,A25) -> 307215 | G25: =IFERROR(F25/(F25+D25),0) -> 0.031941584 | H25: =IFERROR(SUMIFS(Workforce_Raw!$J:$J,Workforce_Raw!$D:$D,A25)/(SUMIFS(Workforce_Raw!$F:$F,Workforce_Raw!$D:$D,A25)/12),0) -> 6.0373787 | J25: Minibus | K25: =SUMIFS(Fleet_Raw!$G:$G,Fleet_Raw!$F:$F,J25) -> 310356 | L25: =SUMIFS(Fleet_Raw!$L:$L,Fleet_Raw!$F:$F,J25) -> 252003.12 | M25: =IFERROR(L25/K25,0) -> 0.81198082
A28: Agency rate by agency and role (average £/hour)
A29: Agency | B29: Registered Nurse | C29: Senior Support Worker | D29: Support Worker | E29: Total spend
A30: CareTemps | B30: =IFERROR(SUMIFS(Agency_Raw!$I:$I,Agency_Raw!$E:$E,$A30,Agency_Raw!$F:$F,B$29)/SUMIFS(Agency_Raw!$G:$G,Agency_Raw!$E:$E,$A30,Agency_Raw!$F:$F,B$29),0) -> 42 | C30: =IFERROR(SUMIFS(Agency_Raw!$I:$I,Agency_Raw!$E:$E,$A30,Agency_Raw!$F:$F,C$29)/SUMIFS(Agency_Raw!$G:$G,Agency_Raw!$E:$E,$A30,Agency_Raw!$F:$F,C$29),0) -> 28 | D30: =IFERROR(SUMIFS(Agency_Raw!$I:$I,Agency_Raw!$E:$E,$A30,Agency_Raw!$F:$F,D$29)/SUMIFS(Agency_Raw!$G:$G,Agency_Raw!$E:$E,$A30,Agency_Raw!$F:$F,D$29),0) -> 23 | E30: =SUMIFS(Agency_Raw!$I:$I,Agency_Raw!$E:$E,$A30) -> 347539
A31: HealthStaffing | B31: =IFERROR(SUMIFS(Agency_Raw!$I:$I,Agency_Raw!$E:$E,$A31,Agency_Raw!$F:$F,B$29)/SUMIFS(Agency_Raw!$G:$G,Agency_Raw!$E:$E,$A31,Agency_Raw!$F:$F,B$29),0) -> 42 | C31: =IFERROR(SUMIFS(Agency_Raw!$I:$I,Agency_Raw!$E:$E,$A31,Agency_Raw!$F:$F,C$29)/SUMIFS(Agency_Raw!$G:$G,Agency_Raw!$E:$E,$A31,Agency_Raw!$F:$F,C$29),0) -> 28 | D31: =IFERROR(SUMIFS(Agency_Raw!$I:$I,Agency_Raw!$E:$E,$A31,Agency_Raw!$F:$F,D$29)/SUMIFS(Agency_Raw!$G:$G,Agency_Raw!$E:$E,$A31,Agency_Raw!$F:$F,D$29),0) -> 23 | E31: =SUMIFS(Agency_Raw!$I:$I,Agency_Raw!$E:$E,$A31) -> 514753
A32: NurseLink | B32: =IFERROR(SUMIFS(Agency_Raw!$I:$I,Agency_Raw!$E:$E,$A32,Agency_Raw!$F:$F,B$29)/SUMIFS(Agency_Raw!$G:$G,Agency_Raw!$E:$E,$A32,Agency_Raw!$F:$F,B$29),0) -> 42 | C32: =IFERROR(SUMIFS(Agency_Raw!$I:$I,Agency_Raw!$E:$E,$A32,Agency_Raw!$F:$F,C$29)/SUMIFS(Agency_Raw!$G:$G,Agency_Raw!$E:$E,$A32,Agency_Raw!$F:$F,C$29),0) -> 28 | D32: =IFERROR(SUMIFS(Agency_Raw!$I:$I,Agency_Raw!$E:$E,$A32,Agency_Raw!$F:$F,D$29)/SUMIFS(Agency_Raw!$G:$G,Agency_Raw!$E:$E,$A32,Agency_Raw!$F:$F,D$29),0) -> 23 | E32: =SUMIFS(Agency_Raw!$I:$I,Agency_Raw!$E:$E,$A32) -> 478794
A34: =IF(AND(MAX(B30:B32)=MIN(B30:B32),MAX(C30:C32)=MIN(C30:C32),MAX(D30:D32)=MIN(D30:D32)),"All three agencies charge identical rates by role, so the lever is volume and grade mix rather than rate: registered nurses are "&TEXT(SUMIFS(Agency_Raw!$I:$I,Agency_Raw!$F:$F,"Registered Nurse")/SUM(Agency_Raw!$I:$I),"0%")&" of agency spend.","Nurse rates range from "&TEXT(MIN(B30:B32),"£0.00")&" to "&TEXT(MAX(B30:B32),"£0.00")&"/hr across agencies: a rate-card conversation worth having.") -> All three agencies charge identical rates by role, so the lever is volume and grade mix rather than rate: registered nurses are 44% of agency spend.

Sheet Supplier_Analysis
A1: Supplier Spend, Concentration & Contract Compliance (2025)
A2: Supplier list is driven by the Supplier_Lookup master; ranking uses RANK and INDEX/MATCH.
A4: Supplier | B4: Category | C4: Contracted | D4: Spend | E4: Invoices | F4: Avg invoice | G4: Share | H4: Rank | I4: Avg terms (days) | K4: Top 10 suppliers (Pareto)
A5: =Supplier_Lookup!A2 -> AutoCare | B5: =Supplier_Lookup!B2 -> Vehicle & Fuel | C5: =Supplier_Lookup!C2 -> N | D5: =SUMIFS(Cleaned_Procurement!$O$2:$O$1801,Cleaned_Procurement!$E$2:$E$1801,A5) -> 284264.57 | E5: =COUNTIFS(Cleaned_Procurement!$E$2:$E$1801,A5) -> 57 | F5: =IFERROR(D5/E5,0) -> 4987.0977 | G5: =IFERROR(D5/$D$29,0) -> 0.020418398 | H5: =RANK(D5,$D$5:$D$28,0) -> 20 | I5: =IFERROR(AVERAGEIFS(Cleaned_Procurement!$K$2:$K$1801,Cleaned_Procurement!$E$2:$E$1801,A5),0) -> 49.210526 | K5: Rank | L5: Supplier | M5: Spend | N5: Share | O5: Cumulative | P5: Contracted
A6: =Supplier_Lookup!A3 -> BuildCare | B6: =Supplier_Lookup!B3 -> Facilities | C6: =Supplier_Lookup!C3 -> N | D6: =SUMIFS(Cleaned_Procurement!$O$2:$O$1801,Cleaned_Procurement!$E$2:$E$1801,A6) -> 647209.95 | E6: =COUNTIFS(Cleaned_Procurement!$E$2:$E$1801,A6) -> 68 | F6: =IFERROR(D6/E6,0) -> 9517.7934 | G6: =IFERROR(D6/$D$29,0) -> 0.046488349 | H6: =RANK(D6,$D$5:$D$28,0) -> 10 | I6: =IFERROR(AVERAGEIFS(Cleaned_Procurement!$K$2:$K$1801,Cleaned_Procurement!$E$2:$E$1801,A6),0) -> 43.897059 | K6: 1 | L6: =INDEX($A$5:$A$28,MATCH(K6,$H$5:$H$28,0)) -> NurseLink | M6: =INDEX($D$5:$D$28,MATCH(K6,$H$5:$H$28,0)) -> 1161388.4 | N6: =IFERROR(M6/$D$29,0) -> 0.083421198 | O6: =SUM($N$6:N6) -> 0.083421198 | P6: =INDEX($C$5:$C$28,MATCH(K6,$H$5:$H$28,0)) -> N
A7: =Supplier_Lookup!A4 -> CareMed | B7: =Supplier_Lookup!B4 -> Medical Supplies | C7: =Supplier_Lookup!C4 -> N | D7: =SUMIFS(Cleaned_Procurement!$O$2:$O$1801,Cleaned_Procurement!$E$2:$E$1801,A7) -> 311670.19 | E7: =COUNTIFS(Cleaned_Procurement!$E$2:$E$1801,A7) -> 62 | F7: =IFERROR(D7/E7,0) -> 5026.9385 | G7: =IFERROR(D7/$D$29,0) -> 0.022386913 | H7: =RANK(D7,$D$5:$D$28,0) -> 18 | I7: =IFERROR(AVERAGEIFS(Cleaned_Procurement!$K$2:$K$1801,Cleaned_Procurement!$E$2:$E$1801,A7),0) -> 47.419355 | K7: 2 | L7: =INDEX($A$5:$A$28,MATCH(K7,$H$5:$H$28,0)) -> HealthStaffing | M7: =INDEX($D$5:$D$28,MATCH(K7,$H$5:$H$28,0)) -> 1072844.7 | N7: =IFERROR(M7/$D$29,0) -> 0.077061205 | O7: =SUM($N$6:N7) -> 0.1604824 | P7: =INDEX($C$5:$C$28,MATCH(K7,$H$5:$H$28,0)) -> N
A8: =Supplier_Lookup!A5 -> CareTemps | B8: =Supplier_Lookup!B5 -> Agency Labour | C8: =Supplier_Lookup!C5 -> N | D8: =SUMIFS(Cleaned_Procurement!$O$2:$O$1801,Cleaned_Procurement!$E$2:$E$1801,A8) -> 959134.04 | E8: =COUNTIFS(Cleaned_Procurement!$E$2:$E$1801,A8) -> 73 | F8: =IFERROR(D8/E8,0) -> 13138.822 | G8: =IFERROR(D8/$D$29,0) -> 0.068893499 | H8: =RANK(D8,$D$5:$D$28,0) -> 4 | I8: =IFERROR(AVERAGEIFS(Cleaned_Procurement!$K$2:$K$1801,Cleaned_Procurement!$E$2:$E$1801,A8),0) -> 45.205479 | K8: 3 | L8: =INDEX($A$5:$A$28,MATCH(K8,$H$5:$H$28,0)) -> PowerDirect | M8: =INDEX($D$5:$D$28,MATCH(K8,$H$5:$H$28,0)) -> 1048249.1 | N8: =IFERROR(M8/$D$29,0) -> 0.075294533 | O8: =SUM($N$6:N8) -> 0.23577694 | P8: =INDEX($C$5:$C$28,MATCH(K8,$H$5:$H$28,0)) -> N
A9: =Supplier_Lookup!A6 -> CleanWorks | B9: =Supplier_Lookup!B6 -> Facilities | C9: =Supplier_Lookup!C6 -> Y | D9: =SUMIFS(Cleaned_Procurement!$O$2:$O$1801,Cleaned_Procurement!$E$2:$E$1801,A9) -> 591363.92 | E9: =COUNTIFS(Cleaned_Procurement!$E$2:$E$1801,A9) -> 73 | F9: =IFERROR(D9/E9,0) -> 8100.8756 | G9: =IFERROR(D9/$D$29,0) -> 0.042476993 | H9: =RANK(D9,$D$5:$D$28,0) -> 11 | I9: =IFERROR(AVERAGEIFS(Cleaned_Procurement!$K$2:$K$1801,Cleaned_Procurement!$E$2:$E$1801,A9),0) -> 45.205479 | K9: 4 | L9: =INDEX($A$5:$A$28,MATCH(K9,$H$5:$H$28,0)) -> CareTemps | M9: =INDEX($D$5:$D$28,MATCH(K9,$H$5:$H$28,0)) -> 959134.04 | N9: =IFERROR(M9/$D$29,0) -> 0.068893499 | O9: =SUM($N$6:N9) -> 0.30467043 | P9: =INDEX($C$5:$C$28,MATCH(K9,$H$5:$H$28,0)) -> N
A10: =Supplier_Lookup!A7 -> ClinEquip | B10: =Supplier_Lookup!B7 -> Medical Supplies | C10: =Supplier_Lookup!C7 -> N | D10: =SUMIFS(Cleaned_Procurement!$O$2:$O$1801,Cleaned_Procurement!$E$2:$E$1801,A10) -> 359940.88 | E10: =COUNTIFS(Cleaned_Procurement!$E$2:$E$1801,A10) -> 67 | F10: =IFERROR(D10/E10,0) -> 5372.2519 | G10: =IFERROR(D10/$D$29,0) -> 0.025854141 | H10: =RANK(D10,$D$5:$D$28,0) -> 15 | I10: =IFERROR(AVERAGEIFS(Cleaned_Procurement!$K$2:$K$1801,Cleaned_Procurement!$E$2:$E$1801,A10),0) -> 43.880597 | K10: 5 | L10: =INDEX($A$5:$A$28,MATCH(K10,$H$5:$H$28,0)) -> SafeGuard FM | M10: =INDEX($D$5:$D$28,MATCH(K10,$H$5:$H$28,0)) -> 890207.06 | N10: =IFERROR(M10/$D$29,0) -> 0.063942553 | O10: =SUM($N$6:N10) -> 0.36861299 | P10: =INDEX($C$5:$C$28,MATCH(K10,$H$5:$H$28,0)) -> N
A11: =Supplier_Lookup!A8 -> CloudLink | B11: =Supplier_Lookup!B8 -> IT & Telecoms | C11: =Supplier_Lookup!C8 -> Y | D11: =SUMIFS(Cleaned_Procurement!$O$2:$O$1801,Cleaned_Procurement!$E$2:$E$1801,A11) -> 881477.21 | E11: =COUNTIFS(Cleaned_Procurement!$E$2:$E$1801,A11) -> 82 | F11: =IFERROR(D11/E11,0) -> 10749.722 | G11: =IFERROR(D11/$D$29,0) -> 0.063315498 | H11: =RANK(D11,$D$5:$D$28,0) -> 6 | I11: =IFERROR(AVERAGEIFS(Cleaned_Procurement!$K$2:$K$1801,Cleaned_Procurement!$E$2:$E$1801,A11),0) -> 44.634146 | K11: 6 | L11: =INDEX($A$5:$A$28,MATCH(K11,$H$5:$H$28,0)) -> CloudLink | M11: =INDEX($D$5:$D$28,MATCH(K11,$H$5:$H$28,0)) -> 881477.21 | N11: =IFERROR(M11/$D$29,0) -> 0.063315498 | O11: =SUM($N$6:N11) -> 0.43192848 | P11: =INDEX($C$5:$C$28,MATCH(K11,$H$5:$H$28,0)) -> Y
A12: =Supplier_Lookup!A9 -> FleetFuel | B12: =Supplier_Lookup!B9 -> Vehicle & Fuel | C12: =Supplier_Lookup!C9 -> Y | D12: =SUMIFS(Cleaned_Procurement!$O$2:$O$1801,Cleaned_Procurement!$E$2:$E$1801,A12) -> 314243.92 | E12: =COUNTIFS(Cleaned_Procurement!$E$2:$E$1801,A12) -> 74 | F12: =IFERROR(D12/E12,0) -> 4246.5395 | G12: =IFERROR(D12/$D$29,0) -> 0.022571781 | H12: =RANK(D12,$D$5:$D$28,0) -> 17 | I12: =IFERROR(AVERAGEIFS(Cleaned_Procurement!$K$2:$K$1801,Cleaned_Procurement!$E$2:$E$1801,A12),0) -> 44.797297 | K12: 7 | L12: =INDEX($A$5:$A$28,MATCH(K12,$H$5:$H$28,0)) -> NetServe | M12: =INDEX($D$5:$D$28,MATCH(K12,$H$5:$H$28,0)) -> 851726.08 | N12: =IFERROR(M12/$D$29,0) -> 0.061178508 | O12: =SUM($N$6:N12) -> 0.49310699 | P12: =INDEX($C$5:$C$28,MATCH(K12,$H$5:$H$28,0)) -> N
A13: =Supplier_Lookup!A10 -> FreshServe | B13: =Supplier_Lookup!B10 -> Food & Catering | C13: =Supplier_Lookup!C10 -> Y | D13: =SUMIFS(Cleaned_Procurement!$O$2:$O$1801,Cleaned_Procurement!$E$2:$E$1801,A13) -> 238615.67 | E13: =COUNTIFS(Cleaned_Procurement!$E$2:$E$1801,A13) -> 74 | F13: =IFERROR(D13/E13,0) -> 3224.5361 | G13: =IFERROR(D13/$D$29,0) -> 0.01713949 | H13: =RANK(D13,$D$5:$D$28,0) -> 22 | I13: =IFERROR(AVERAGEIFS(Cleaned_Procurement!$K$2:$K$1801,Cleaned_Procurement!$E$2:$E$1801,A13),0) -> 46.621622 | K13: 8 | L13: =INDEX($A$5:$A$28,MATCH(K13,$H$5:$H$28,0)) -> UK Energy Partners | M13: =INDEX($D$5:$D$28,MATCH(K13,$H$5:$H$28,0)) -> 833961.1 | N13: =IFERROR(M13/$D$29,0) -> 0.05990247 | O13: =SUM($N$6:N13) -> 0.55300946 | P13: =INDEX($C$5:$C$28,MATCH(K13,$H$5:$H$28,0)) -> N
A14: =Supplier_Lookup!A11 -> HealthStaffing | B14: =Supplier_Lookup!B11 -> Agency Labour | C14: =Supplier_Lookup!C11 -> N | D14: =SUMIFS(Cleaned_Procurement!$O$2:$O$1801,Cleaned_Procurement!$E$2:$E$1801,A14) -> 1072844.7 | E14: =COUNTIFS(Cleaned_Procurement!$E$2:$E$1801,A14) -> 85 | F14: =IFERROR(D14/E14,0) -> 12621.702 | G14: =IFERROR(D14/$D$29,0) -> 0.077061205 | H14: =RANK(D14,$D$5:$D$28,0) -> 2 | I14: =IFERROR(AVERAGEIFS(Cleaned_Procurement!$K$2:$K$1801,Cleaned_Procurement!$E$2:$E$1801,A14),0) -> 46.411765 | K14: 9 | L14: =INDEX($A$5:$A$28,MATCH(K14,$H$5:$H$28,0)) -> TeleCare IT | M14: =INDEX($D$5:$D$28,MATCH(K14,$H$5:$H$28,0)) -> 774305.94 | N14: =IFERROR(M14/$D$29,0) -> 0.055617508 | O14: =SUM($N$6:N14) -> 0.60862697 | P14: =INDEX($C$5:$C$28,MATCH(K14,$H$5:$H$28,0)) -> N
A15: =Supplier_Lookup!A12 -> KitchenPro | B15: =Supplier_Lookup!B12 -> Food & Catering | C15: =Supplier_Lookup!C12 -> N | D15: =SUMIFS(Cleaned_Procurement!$O$2:$O$1801,Cleaned_Procurement!$E$2:$E$1801,A15) -> 279264.56 | E15: =COUNTIFS(Cleaned_Procurement!$E$2:$E$1801,A15) -> 87 | F15: =IFERROR(D15/E15,0) -> 3209.9375 | G15: =IFERROR(D15/$D$29,0) -> 0.020059253 | H15: =RANK(D15,$D$5:$D$28,0) -> 21 | I15: =IFERROR(AVERAGEIFS(Cleaned_Procurement!$K$2:$K$1801,Cleaned_Procurement!$E$2:$E$1801,A15),0) -> 45.344828 | K15: 10 | L15: =INDEX($A$5:$A$28,MATCH(K15,$H$5:$H$28,0)) -> BuildCare | M15: =INDEX($D$5:$D$28,MATCH(K15,$H$5:$H$28,0)) -> 647209.95 | N15: =IFERROR(M15/$D$29,0) -> 0.046488349 | O15: =SUM($N$6:N15) -> 0.65511532 | P15: =INDEX($C$5:$C$28,MATCH(K15,$H$5:$H$28,0)) -> N
A16: =Supplier_Lookup!A13 -> LearnWell | B16: =Supplier_Lookup!B13 -> Office & Training | C16: =Supplier_Lookup!C13 -> N | D16: =SUMIFS(Cleaned_Procurement!$O$2:$O$1801,Cleaned_Procurement!$E$2:$E$1801,A16) -> 236027.71 | E16: =COUNTIFS(Cleaned_Procurement!$E$2:$E$1801,A16) -> 71 | F16: =IFERROR(D16/E16,0) -> 3324.3339 | G16: =IFERROR(D16/$D$29,0) -> 0.0169536 | H16: =RANK(D16,$D$5:$D$28,0) -> 23 | I16: =IFERROR(AVERAGEIFS(Cleaned_Procurement!$K$2:$K$1801,Cleaned_Procurement!$E$2:$E$1801,A16),0) -> 45.633803
A17: =Supplier_Lookup!A14 -> MediSure | B17: =Supplier_Lookup!B14 -> Medical Supplies | C17: =Supplier_Lookup!C14 -> Y | D17: =SUMIFS(Cleaned_Procurement!$O$2:$O$1801,Cleaned_Procurement!$E$2:$E$1801,A17) -> 423187.89 | E17: =COUNTIFS(Cleaned_Procurement!$E$2:$E$1801,A17) -> 75 | F17: =IFERROR(D17/E17,0) -> 5642.5052 | G17: =IFERROR(D17/$D$29,0) -> 0.030397101 | H17: =RANK(D17,$D$5:$D$28,0) -> 14 | I17: =IFERROR(AVERAGEIFS(Cleaned_Procurement!$K$2:$K$1801,Cleaned_Procurement!$E$2:$E$1801,A17),0) -> 46.4
A18: =Supplier_Lookup!A15 -> NetServe | B18: =Supplier_Lookup!B15 -> IT & Telecoms | C18: =Supplier_Lookup!C15 -> N | D18: =SUMIFS(Cleaned_Procurement!$O$2:$O$1801,Cleaned_Procurement!$E$2:$E$1801,A18) -> 851726.08 | E18: =COUNTIFS(Cleaned_Procurement!$E$2:$E$1801,A18) -> 86 | F18: =IFERROR(D18/E18,0) -> 9903.7916 | G18: =IFERROR(D18/$D$29,0) -> 0.061178508 | H18: =RANK(D18,$D$5:$D$28,0) -> 7 | I18: =IFERROR(AVERAGEIFS(Cleaned_Procurement!$K$2:$K$1801,Cleaned_Procurement!$E$2:$E$1801,A18),0) -> 47.790698 | K18: Findings (live)
A19: =Supplier_Lookup!A16 -> NourishCo | B19: =Supplier_Lookup!B16 -> Food & Catering | C19: =Supplier_Lookup!C16 -> N | D19: =SUMIFS(Cleaned_Procurement!$O$2:$O$1801,Cleaned_Procurement!$E$2:$E$1801,A19) -> 319833.4 | E19: =COUNTIFS(Cleaned_Procurement!$E$2:$E$1801,A19) -> 87 | F19: =IFERROR(D19/E19,0) -> 3676.246 | G19: =IFERROR(D19/$D$29,0) -> 0.022973267 | H19: =RANK(D19,$D$5:$D$28,0) -> 16 | I19: =IFERROR(AVERAGEIFS(Cleaned_Procurement!$K$2:$K$1801,Cleaned_Procurement!$E$2:$E$1801,A19),0) -> 42.586207 | K19: ="Top 5 suppliers account for "&TEXT(O10,"0%")&" of attributed spend; top 10 for "&TEXT(O15,"0%")&"." -> Top 5 suppliers account for 37% of attributed spend; top 10 for 66%.
A20: =Supplier_Lookup!A17 -> NurseLink | B20: =Supplier_Lookup!B17 -> Agency Labour | C20: =Supplier_Lookup!C17 -> N | D20: =SUMIFS(Cleaned_Procurement!$O$2:$O$1801,Cleaned_Procurement!$E$2:$E$1801,A20) -> 1161388.4 | E20: =COUNTIFS(Cleaned_Procurement!$E$2:$E$1801,A20) -> 84 | F20: =IFERROR(D20/E20,0) -> 13826.052 | G20: =IFERROR(D20/$D$29,0) -> 0.083421198 | H20: =RANK(D20,$D$5:$D$28,0) -> 1 | I20: =IFERROR(AVERAGEIFS(Cleaned_Procurement!$K$2:$K$1801,Cleaned_Procurement!$E$2:$E$1801,A20),0) -> 45.178571 | K20: ="Off-contract spend: "&TEXT(SUMIFS(Cleaned_Procurement!O2:O1801,Cleaned_Procurement!M2:M1801,"N"),"£#,##0")&" ("&TEXT(SUMIFS(Cleaned_Procurement!O2:O1801,Cleaned_Procurement!M2:M1801,"N")/SUM(Cleaned_Procurement!O2:O1801),"0%")&" of total), the main lever for the savings plan." -> Off-contract spend: £11,473,793 (82% of total), the main lever for the savings plan.
A21: =Supplier_Lookup!A18 -> OfficePlus | B21: =Supplier_Lookup!B18 -> Office & Training | C21: =Supplier_Lookup!C18 -> N | D21: =SUMIFS(Cleaned_Procurement!$O$2:$O$1801,Cleaned_Procurement!$E$2:$E$1801,A21) -> 294325.78 | E21: =COUNTIFS(Cleaned_Procurement!$E$2:$E$1801,A21) -> 82 | F21: =IFERROR(D21/E21,0) -> 3589.3388 | G21: =IFERROR(D21/$D$29,0) -> 0.021141083 | H21: =RANK(D21,$D$5:$D$28,0) -> 19 | I21: =IFERROR(AVERAGEIFS(Cleaned_Procurement!$K$2:$K$1801,Cleaned_Procurement!$E$2:$E$1801,A21),0) -> 46.280488 | K21: ="Largest single supplier: "&L6&" at "&TEXT(M6,"£#,##0")&IF(P6="N",", not under contract.",", under contract.") -> Largest single supplier: NurseLink at £1,161,388, not under contract.
A22: =Supplier_Lookup!A19 -> PowerDirect | B22: =Supplier_Lookup!B19 -> Utilities | C22: =Supplier_Lookup!C19 -> N | D22: =SUMIFS(Cleaned_Procurement!$O$2:$O$1801,Cleaned_Procurement!$E$2:$E$1801,A22) -> 1048249.1 | E22: =COUNTIFS(Cleaned_Procurement!$E$2:$E$1801,A22) -> 87 | F22: =IFERROR(D22/E22,0) -> 12048.84 | G22: =IFERROR(D22/$D$29,0) -> 0.075294533 | H22: =RANK(D22,$D$5:$D$28,0) -> 3 | I22: =IFERROR(AVERAGEIFS(Cleaned_Procurement!$K$2:$K$1801,Cleaned_Procurement!$E$2:$E$1801,A22),0) -> 44.482759
A23: =Supplier_Lookup!A20 -> PrintCo | B23: =Supplier_Lookup!B20 -> Office & Training | C23: =Supplier_Lookup!C20 -> N | D23: =SUMIFS(Cleaned_Procurement!$O$2:$O$1801,Cleaned_Procurement!$E$2:$E$1801,A23) -> 197576.58 | E23: =COUNTIFS(Cleaned_Procurement!$E$2:$E$1801,A23) -> 68 | F23: =IFERROR(D23/E23,0) -> 2905.5379 | G23: =IFERROR(D23/$D$29,0) -> 0.014191699 | H23: =RANK(D23,$D$5:$D$28,0) -> 24 | I23: =IFERROR(AVERAGEIFS(Cleaned_Procurement!$K$2:$K$1801,Cleaned_Procurement!$E$2:$E$1801,A23),0) -> 44.117647
A24: =Supplier_Lookup!A21 -> RoadReady | B24: =Supplier_Lookup!B21 -> Vehicle & Fuel | C24: =Supplier_Lookup!C21 -> N | D24: =SUMIFS(Cleaned_Procurement!$O$2:$O$1801,Cleaned_Procurement!$E$2:$E$1801,A24) -> 432111.81 | E24: =COUNTIFS(Cleaned_Procurement!$E$2:$E$1801,A24) -> 90 | F24: =IFERROR(D24/E24,0) -> 4801.2423 | G24: =IFERROR(D24/$D$29,0) -> 0.031038096 | H24: =RANK(D24,$D$5:$D$28,0) -> 13 | I24: =IFERROR(AVERAGEIFS(Cleaned_Procurement!$K$2:$K$1801,Cleaned_Procurement!$E$2:$E$1801,A24),0) -> 44.5
A25: =Supplier_Lookup!A22 -> SafeGuard FM | B25: =Supplier_Lookup!B22 -> Facilities | C25: =Supplier_Lookup!C22 -> N | D25: =SUMIFS(Cleaned_Procurement!$O$2:$O$1801,Cleaned_Procurement!$E$2:$E$1801,A25) -> 890207.06 | E25: =COUNTIFS(Cleaned_Procurement!$E$2:$E$1801,A25) -> 76 | F25: =IFERROR(D25/E25,0) -> 11713.251 | G25: =IFERROR(D25/$D$29,0) -> 0.063942553 | H25: =RANK(D25,$D$5:$D$28,0) -> 5 | I25: =IFERROR(AVERAGEIFS(Cleaned_Procurement!$K$2:$K$1801,Cleaned_Procurement!$E$2:$E$1801,A25),0) -> 44.802632
A26: =Supplier_Lookup!A23 -> TeleCare IT | B26: =Supplier_Lookup!B23 -> IT & Telecoms | C26: =Supplier_Lookup!C23 -> N | D26: =SUMIFS(Cleaned_Procurement!$O$2:$O$1801,Cleaned_Procurement!$E$2:$E$1801,A26) -> 774305.94 | E26: =COUNTIFS(Cleaned_Procurement!$E$2:$E$1801,A26) -> 72 | F26: =IFERROR(D26/E26,0) -> 10754.249 | G26: =IFERROR(D26/$D$29,0) -> 0.055617508 | H26: =RANK(D26,$D$5:$D$28,0) -> 9 | I26: =IFERROR(AVERAGEIFS(Cleaned_Procurement!$K$2:$K$1801,Cleaned_Procurement!$E$2:$E$1801,A26),0) -> 44.375
A27: =Supplier_Lookup!A24 -> UK Energy Partners | B27: =Supplier_Lookup!B24 -> Utilities | C27: =Supplier_Lookup!C24 -> N | D27: =SUMIFS(Cleaned_Procurement!$O$2:$O$1801,Cleaned_Procurement!$E$2:$E$1801,A27) -> 833961.1 | E27: =COUNTIFS(Cleaned_Procurement!$E$2:$E$1801,A27) -> 66 | F27: =IFERROR(D27/E27,0) -> 12635.774 | G27: =IFERROR(D27/$D$29,0) -> 0.05990247 | H27: =RANK(D27,$D$5:$D$28,0) -> 8 | I27: =IFERROR(AVERAGEIFS(Cleaned_Procurement!$K$2:$K$1801,Cleaned_Procurement!$E$2:$E$1801,A27),0) -> 44.545455
A28: =Supplier_Lookup!A25 -> WaterGrid | B28: =Supplier_Lookup!B25 -> Utilities | C28: =Supplier_Lookup!C25 -> N | D28: =SUMIFS(Cleaned_Procurement!$O$2:$O$1801,Cleaned_Procurement!$E$2:$E$1801,A28) -> 519051.38 | E28: =COUNTIFS(Cleaned_Procurement!$E$2:$E$1801,A28) -> 53 | F28: =IFERROR(D28/E28,0) -> 9793.4223 | G28: =IFERROR(D28/$D$29,0) -> 0.037282866 | H28: =RANK(D28,$D$5:$D$28,0) -> 12 | I28: =IFERROR(AVERAGEIFS(Cleaned_Procurement!$K$2:$K$1801,Cleaned_Procurement!$E$2:$E$1801,A28),0) -> 48.113208
A29: Total | D29: =SUM(D5:D28) -> 13921982 | E29: =SUM(E5:E28) -> 1799
A30: Unattributed (missing supplier) | D30: =SUM(Cleaned_Procurement!O2:O1801)-D29 -> 699.89

Sheet Pivot_Analysis
A1: Pivot-Style Commercial Analysis – Refreshable Formula Summary
A2: v2 fix: Contracted spend now reads the real Contracted flag (column M); Wales potential saving no longer errors because NetSpend_Clean is always numeric.
A3: Spend by Category
A4: Category | B4: Spend | C4: % of Total | D4: Target Savings | E4: Potential Saving | F4: Contracted Spend | G4: Non-Contracted Spend
A5: Medical Supplies | B5: =SUMIFS(Cleaned_Procurement!$O:$O,Cleaned_Procurement!$F:$F,A5) -> 1097153 | C5: =IFERROR(B5/SUM($B$5:$B$12),0) -> 0.078803282 | D5: =IFERROR(INDEX(Category_Targets!$B$2:$B$9,MATCH(A5,Category_Targets!$A$2:$A$9,0)),0) -> 0.06 | E5: =B5*D5 -> 65829.181 | F5: =SUMIFS(Cleaned_Procurement!$O:$O,Cleaned_Procurement!$F:$F,A5,Cleaned_Procurement!$M:$M,"Y") -> 425541.94 | G5: =B5-F5 -> 671611.07
A6: Food & Catering | B6: =SUMIFS(Cleaned_Procurement!$O:$O,Cleaned_Procurement!$F:$F,A6) -> 837713.63 | C6: =IFERROR(B6/SUM($B$5:$B$12),0) -> 0.060168985 | D6: =IFERROR(INDEX(Category_Targets!$B$2:$B$9,MATCH(A6,Category_Targets!$A$2:$A$9,0)),0) -> 0.04 | E6: =B6*D6 -> 33508.545 | F6: =SUMIFS(Cleaned_Procurement!$O:$O,Cleaned_Procurement!$F:$F,A6,Cleaned_Procurement!$M:$M,"Y") -> 238615.67 | G6: =B6-F6 -> 599097.96
A7: Facilities | B7: =SUMIFS(Cleaned_Procurement!$O:$O,Cleaned_Procurement!$F:$F,A7) -> 2128780.9 | C7: =IFERROR(B7/SUM($B$5:$B$12),0) -> 0.15290021 | D7: =IFERROR(INDEX(Category_Targets!$B$2:$B$9,MATCH(A7,Category_Targets!$A$2:$A$9,0)),0) -> 0.05 | E7: =B7*D7 -> 106439.05 | F7: =SUMIFS(Cleaned_Procurement!$O:$O,Cleaned_Procurement!$F:$F,A7,Cleaned_Procurement!$M:$M,"Y") -> 591363.92 | G7: =B7-F7 -> 1537417
A8: Utilities | B8: =SUMIFS(Cleaned_Procurement!$O:$O,Cleaned_Procurement!$F:$F,A8) -> 2401261.6 | C8: =IFERROR(B8/SUM($B$5:$B$12),0) -> 0.1724712 | D8: =IFERROR(INDEX(Category_Targets!$B$2:$B$9,MATCH(A8,Category_Targets!$A$2:$A$9,0)),0) -> 0.03 | E8: =B8*D8 -> 72037.848 | F8: =SUMIFS(Cleaned_Procurement!$O:$O,Cleaned_Procurement!$F:$F,A8,Cleaned_Procurement!$M:$M,"Y") -> 0 | G8: =B8-F8 -> 2401261.6
A9: IT & Telecoms | B9: =SUMIFS(Cleaned_Procurement!$O:$O,Cleaned_Procurement!$F:$F,A9) -> 2505155.2 | C9: =IFERROR(B9/SUM($B$5:$B$12),0) -> 0.17993338 | D9: =IFERROR(INDEX(Category_Targets!$B$2:$B$9,MATCH(A9,Category_Targets!$A$2:$A$9,0)),0) -> 0.08 | E9: =B9*D9 -> 200412.41 | F9: =SUMIFS(Cleaned_Procurement!$O:$O,Cleaned_Procurement!$F:$F,A9,Cleaned_Procurement!$M:$M,"Y") -> 879123.16 | G9: =B9-F9 -> 1626032
A10: Vehicle & Fuel | B10: =SUMIFS(Cleaned_Procurement!$O:$O,Cleaned_Procurement!$F:$F,A10) -> 1030620.3 | C10: =IFERROR(B10/SUM($B$5:$B$12),0) -> 0.074024553 | D10: =IFERROR(INDEX(Category_Targets!$B$2:$B$9,MATCH(A10,Category_Targets!$A$2:$A$9,0)),0) -> 0.05 | E10: =B10*D10 -> 51531.015 | F10: =SUMIFS(Cleaned_Procurement!$O:$O,Cleaned_Procurement!$F:$F,A10,Cleaned_Procurement!$M:$M,"Y") -> 314243.92 | G10: =B10-F10 -> 716376.38
A11: Agency Labour | B11: =SUMIFS(Cleaned_Procurement!$O:$O,Cleaned_Procurement!$F:$F,A11) -> 3193367.1 | C11: =IFERROR(B11/SUM($B$5:$B$12),0) -> 0.22936437 | D11: =IFERROR(INDEX(Category_Targets!$B$2:$B$9,MATCH(A11,Category_Targets!$A$2:$A$9,0)),0) -> 0.07 | E11: =B11*D11 -> 223535.7 | F11: =SUMIFS(Cleaned_Procurement!$O:$O,Cleaned_Procurement!$F:$F,A11,Cleaned_Procurement!$M:$M,"Y") -> 0 | G11: =B11-F11 -> 3193367.1
A12: Office & Training | B12: =SUMIFS(Cleaned_Procurement!$O:$O,Cleaned_Procurement!$F:$F,A12) -> 728629.96 | C12: =IFERROR(B12/SUM($B$5:$B$12),0) -> 0.052334024 | D12: =IFERROR(INDEX(Category_Targets!$B$2:$B$9,MATCH(A12,Category_Targets!$A$2:$A$9,0)),0) -> 0.04 | E12: =B12*D12 -> 29145.198 | F12: =SUMIFS(Cleaned_Procurement!$O:$O,Cleaned_Procurement!$F:$F,A12,Cleaned_Procurement!$M:$M,"Y") -> 0 | G12: =B12-F12 -> 728629.96
A15: Spend by Region
A16: Region | B16: Spend | C16: Invoices | D16: Avg Invoice | E16: Potential Saving
A17: North | B17: =SUMIFS(Cleaned_Procurement!$O:$O,Cleaned_Procurement!$D:$D,A17) -> 3330923.9 | C17: =COUNTIFS(Cleaned_Procurement!$D:$D,A17) -> 430 | D17: =IFERROR(B17/C17,0) -> 7746.3346 | E17: =SUMIFS(Cleaned_Procurement!$R:$R,Cleaned_Procurement!$D:$D,A17) -> 187081.69
A18: Midlands | B18: =SUMIFS(Cleaned_Procurement!$O:$O,Cleaned_Procurement!$D:$D,A18) -> 3517504.9 | C18: =COUNTIFS(Cleaned_Procurement!$D:$D,A18) -> 475 | D18: =IFERROR(B18/C18,0) -> 7405.2735 | E18: =SUMIFS(Cleaned_Procurement!$R:$R,Cleaned_Procurement!$D:$D,A18) -> 197841.61
A19: South | B19: =SUMIFS(Cleaned_Procurement!$O:$O,Cleaned_Procurement!$D:$D,A19) -> 3350069.5 | C19: =COUNTIFS(Cleaned_Procurement!$D:$D,A19) -> 429 | D19: =IFERROR(B19/C19,0) -> 7809.0198 | E19: =SUMIFS(Cleaned_Procurement!$R:$R,Cleaned_Procurement!$D:$D,A19) -> 188355.79
A20: Wales | B20: =SUMIFS(Cleaned_Procurement!$O:$O,Cleaned_Procurement!$D:$D,A20) -> 3724183.5 | C20: =COUNTIFS(Cleaned_Procurement!$D:$D,A20) -> 466 | D20: =IFERROR(B20/C20,0) -> 7991.81 | E20: =SUMIFS(Cleaned_Procurement!$R:$R,Cleaned_Procurement!$D:$D,A20) -> 209159.87
A23: Monthly Finance Performance
A24: Month | B24: Revenue | C24: Actual Opex | D24: Budget Opex | E24: Variance | F24: EBITDA | G24: Margin
A25: 45658 | B25: =SUMIFS(Finance_Raw!$E:$E,Finance_Raw!$A:$A,A25) -> 6859245.2 | C25: =SUMIFS(Finance_Raw!$L:$L,Finance_Raw!$A:$A,A25) -> 4833404.3 | D25: =SUMIFS(Finance_Raw!$K:$K,Finance_Raw!$A:$A,A25) -> 4836088.8 | E25: =D25-C25 -> 2684.4533 | F25: =B25-C25 -> 2025840.9 | G25: =IFERROR(F25/B25,0) -> 0.29534458
A26: 45689 | B26: =SUMIFS(Finance_Raw!$E:$E,Finance_Raw!$A:$A,A26) -> 7476589.8 | C26: =SUMIFS(Finance_Raw!$L:$L,Finance_Raw!$A:$A,A26) -> 5235379.8 | D26: =SUMIFS(Finance_Raw!$K:$K,Finance_Raw!$A:$A,A26) -> 5267039.7 | E26: =D26-C26 -> 31659.923 | F26: =B26-C26 -> 2241210 | G26: =IFERROR(F26/B26,0) -> 0.29976367
A27: 45717 | B27: =SUMIFS(Finance_Raw!$E:$E,Finance_Raw!$A:$A,A27) -> 7345583.3 | C27: =SUMIFS(Finance_Raw!$L:$L,Finance_Raw!$A:$A,A27) -> 5087641.7 | D27: =SUMIFS(Finance_Raw!$K:$K,Finance_Raw!$A:$A,A27) -> 5095798.3 | E27: =D27-C27 -> 8156.6533 | F27: =B27-C27 -> 2257941.6 | G27: =IFERROR(F27/B27,0) -> 0.30738766
A28: 45748 | B28: =SUMIFS(Finance_Raw!$E:$E,Finance_Raw!$A:$A,A28) -> 7658852.2 | C28: =SUMIFS(Finance_Raw!$L:$L,Finance_Raw!$A:$A,A28) -> 5279230.4 | D28: =SUMIFS(Finance_Raw!$K:$K,Finance_Raw!$A:$A,A28) -> 5236666.6 | E28: =D28-C28 -> -42563.747 | F28: =B28-C28 -> 2379621.9 | G28: =IFERROR(F28/B28,0) -> 0.31070215
A29: 45778 | B29: =SUMIFS(Finance_Raw!$E:$E,Finance_Raw!$A:$A,A29) -> 6576496.4 | C29: =SUMIFS(Finance_Raw!$L:$L,Finance_Raw!$A:$A,A29) -> 4543655.4 | D29: =SUMIFS(Finance_Raw!$K:$K,Finance_Raw!$A:$A,A29) -> 4562622.3 | E29: =D29-C29 -> 18966.897 | F29: =B29-C29 -> 2032841 | G29: =IFERROR(F29/B29,0) -> 0.30910699
A30: 45809 | B30: =SUMIFS(Finance_Raw!$E:$E,Finance_Raw!$A:$A,A30) -> 7065637.8 | C30: =SUMIFS(Finance_Raw!$L:$L,Finance_Raw!$A:$A,A30) -> 4919918.3 | D30: =SUMIFS(Finance_Raw!$K:$K,Finance_Raw!$A:$A,A30) -> 4907337.8 | E30: =D30-C30 -> -12580.503 | F30: =B30-C30 -> 2145719.5 | G30: =IFERROR(F30/B30,0) -> 0.30368377
A31: 45839 | B31: =SUMIFS(Finance_Raw!$E:$E,Finance_Raw!$A:$A,A31) -> 6953277 | C31: =SUMIFS(Finance_Raw!$L:$L,Finance_Raw!$A:$A,A31) -> 4875601.1 | D31: =SUMIFS(Finance_Raw!$K:$K,Finance_Raw!$A:$A,A31) -> 4898226.2 | E31: =D31-C31 -> 22625.13 | F31: =B31-C31 -> 2077675.9 | G31: =IFERROR(F31/B31,0) -> 0.29880529
A32: 45870 | B32: =SUMIFS(Finance_Raw!$E:$E,Finance_Raw!$A:$A,A32) -> 7044378.2 | C32: =SUMIFS(Finance_Raw!$L:$L,Finance_Raw!$A:$A,A32) -> 4979875.7 | D32: =SUMIFS(Finance_Raw!$K:$K,Finance_Raw!$A:$A,A32) -> 4993843.2 | E32: =D32-C32 -> 13967.497 | F32: =B32-C32 -> 2064502.5 | G32: =IFERROR(F32/B32,0) -> 0.29307093
A33: 45901 | B33: =SUMIFS(Finance_Raw!$E:$E,Finance_Raw!$A:$A,A33) -> 6899634.7 | C33: =SUMIFS(Finance_Raw!$L:$L,Finance_Raw!$A:$A,A33) -> 4818773.5 | D33: =SUMIFS(Finance_Raw!$K:$K,Finance_Raw!$A:$A,A33) -> 4850993.2 | E33: =D33-C33 -> 32219.643 | F33: =B33-C33 -> 2080861.1 | G33: =IFERROR(F33/B33,0) -> 0.30159004
A34: 45931 | B34: =SUMIFS(Finance_Raw!$E:$E,Finance_Raw!$A:$A,A34) -> 8051254.3 | C34: =SUMIFS(Finance_Raw!$L:$L,Finance_Raw!$A:$A,A34) -> 5558744.3 | D34: =SUMIFS(Finance_Raw!$K:$K,Finance_Raw!$A:$A,A34) -> 5591688.3 | E34: =D34-C34 -> 32944.003 | F34: =B34-C34 -> 2492510 | G34: =IFERROR(F34/B34,0) -> 0.30958034
A35: 45962 | B35: =SUMIFS(Finance_Raw!$E:$E,Finance_Raw!$A:$A,A35) -> 6479152 | C35: =SUMIFS(Finance_Raw!$L:$L,Finance_Raw!$A:$A,A35) -> 4606613.7 | D35: =SUMIFS(Finance_Raw!$K:$K,Finance_Raw!$A:$A,A35) -> 4585980.7 | E35: =D35-C35 -> -20633.017 | F35: =B35-C35 -> 1872538.3 | G35: =IFERROR(F35/B35,0) -> 0.28900979
A36: 45992 | B36: =SUMIFS(Finance_Raw!$E:$E,Finance_Raw!$A:$A,A36) -> 8066416.4 | C36: =SUMIFS(Finance_Raw!$L:$L,Finance_Raw!$A:$A,A36) -> 5614126.6 | D36: =SUMIFS(Finance_Raw!$K:$K,Finance_Raw!$A:$A,A36) -> 5575536.7 | E36: =D36-C36 -> -38589.957 | F36: =B36-C36 -> 2452289.7 | G36: =IFERROR(F36/B36,0) -> 0.30401229

Sheet Actual_Pivot
B2: Genuine Excel PivotTable on tblCleanProc (refreshes on open). Use it to cross-check Pivot_Analysis.
B3: Filter
D5: Region
B6: Category | C6: Data | D6: Midlands | E6: North | F6: South | G6: Wales | H6: Total Result
B7: Agency Labour
C8: Sum - NetSpend_Clean | D8: 908801.36 | E8: 909631.92 | F8: 573632.97 | G8: 801300.89 | H8: 3193367.1
C9: Count - InvoiceID | D9: 71 | E9: 61 | F9: 47 | G9: 63 | H9: 242
B10: Facilities
C11: Sum - NetSpend_Clean | D11: 507503.34 | E11: 527974.36 | F11: 535792.4 | G11: 557510.83 | H11: 2128780.9
C12: Count - InvoiceID | D12: 61 | E12: 59 | F12: 47 | G12: 50 | H12: 217
B13: Food & Catering
C14: Sum - NetSpend_Clean | D14: 235271.73 | E14: 229341.28 | F14: 184595.52 | G14: 188505.1 | H14: 837713.63
C15: Count - InvoiceID | D15: 64 | E15: 59 | F15: 62 | G15: 63 | H15: 248
B16: IT & Telecoms
C17: Sum - NetSpend_Clean | D17: 569180.44 | E17: 467580.07 | F17: 747410.31 | G17: 720984.36 | H17: 2505155.2
C18: Count - InvoiceID | D18: 56 | E18: 51 | F18: 66 | G18: 66 | H18: 239
B19: Medical Supplies
C20: Sum - NetSpend_Clean | D20: 235168.46 | E20: 271997.11 | F20: 280015.5 | G20: 309971.94 | H20: 1097153
C21: Count - InvoiceID | D21: 46 | E21: 49 | F21: 54 | G21: 56 | H21: 205
B22: Office & Training
C23: Sum - NetSpend_Clean | D23: 201318.8 | E23: 191459.22 | F23: 192086.25 | G23: 143765.69 | H23: 728629.96
C24: Count - InvoiceID | D24: 62 | E24: 52 | F24: 55 | G24: 53 | H24: 222
B25: Utilities
C26: Sum - NetSpend_Clean | D26: 563542.93 | E26: 509825.77 | F26: 603799.51 | G26: 724093.39 | H26: 2401261.6
C27: Count - InvoiceID | D27: 49 | E27: 49 | F27: 54 | G27: 54 | H27: 206
B28: Vehicle & Fuel
C29: Sum - NetSpend_Clean | D29: 296717.86 | E29: 223114.15 | F29: 232737.02 | G29: 278051.27 | H29: 1030620.3
C30: Count - InvoiceID | D30: 66 | E30: 50 | F30: 44 | G30: 61 | H30: 221
B31: Total Sum - NetSpend_Clean | D31: 3517504.9 | E31: 3330923.9 | F31: 3350069.5 | G31: 3724183.5 | H31: 13922682
B32: Total Count - InvoiceID | D32: 475 | E32: 430 | F32: 429 | G32: 466 | H32: 1800

Sheet Data_Quality
A1: Data Quality & Reconciliation Controls
A2: Every figure is a live formula over the raw and cleaned tables. Source values are never overwritten; issues are flagged, logged and treated.
A4: 1. Exception summary (procurement) | F4: 5. Exception log (first 12 exceptions, live)
A5: Flag | B5: Records | C5: Spend affected | D5: Treatment | F5: # | G5: InvoiceID | H5: Date | I5: Supplier | J5: SiteID | K5: Category | L5: GrossSpend | M5: Flag
A6: Missing supplier | B6: =COUNTIF(Cleaned_Procurement!$N$2:$N$1801,A6) -> 1 | C6: =SUMIFS(Cleaned_Procurement!$J$2:$J$1801,Cleaned_Procurement!$N$2:$N$1801,A6) -> 699.89 | D6: Spend retained; supplier shown as blank. Chase AP for supplier master record. | F6: 1 | G6: =IFERROR(INDEX(Cleaned_Procurement!$G$2:$G$1801,MATCH($F6,Cleaned_Procurement!$U$2:$U$1801,0)),"") -> INV-2025-00078 | H6: =IFERROR(INDEX(Cleaned_Procurement!$A$2:$A$1801,MATCH($F6,Cleaned_Procurement!$U$2:$U$1801,0)),"") -> 45744 | I6: =IFERROR(INDEX(Cleaned_Procurement!$E$2:$E$1801,MATCH($F6,Cleaned_Procurement!$U$2:$U$1801,0)),"") | J6: =IFERROR(INDEX(Cleaned_Procurement!$B$2:$B$1801,MATCH($F6,Cleaned_Procurement!$U$2:$U$1801,0)),"") -> S005 | K6: =IFERROR(INDEX(Cleaned_Procurement!$F$2:$F$1801,MATCH($F6,Cleaned_Procurement!$U$2:$U$1801,0)),"") -> Office & Training | L6: =IFERROR(INDEX(Cleaned_Procurement!$J$2:$J$1801,MATCH($F6,Cleaned_Procurement!$U$2:$U$1801,0)),"") -> 699.89 | M6: =IFERROR(INDEX(Cleaned_Procurement!$N$2:$N$1801,MATCH($F6,Cleaned_Procurement!$U$2:$U$1801,0)),"") -> Missing supplier
A7: Missing site | B7: =COUNTIF(Cleaned_Procurement!$N$2:$N$1801,A7) -> 1 | C7: =SUMIFS(Cleaned_Procurement!$J$2:$J$1801,Cleaned_Procurement!$N$2:$N$1801,A7) -> 5662.41 | D7: Spend retained at company level; excluded from site analysis. Confirm cost centre. | F7: 2 | G7: =IFERROR(INDEX(Cleaned_Procurement!$G$2:$G$1801,MATCH($F7,Cleaned_Procurement!$U$2:$U$1801,0)),"") -> INV-2025-00249 | H7: =IFERROR(INDEX(Cleaned_Procurement!$A$2:$A$1801,MATCH($F7,Cleaned_Procurement!$U$2:$U$1801,0)),"") -> 45816 | I7: =IFERROR(INDEX(Cleaned_Procurement!$E$2:$E$1801,MATCH($F7,Cleaned_Procurement!$U$2:$U$1801,0)),"") -> SafeGuard FM | J7: =IFERROR(INDEX(Cleaned_Procurement!$B$2:$B$1801,MATCH($F7,Cleaned_Procurement!$U$2:$U$1801,0)),"") -> S017 | K7: =IFERROR(INDEX(Cleaned_Procurement!$F$2:$F$1801,MATCH($F7,Cleaned_Procurement!$U$2:$U$1801,0)),"") -> Facilities | L7: =IFERROR(INDEX(Cleaned_Procurement!$J$2:$J$1801,MATCH($F7,Cleaned_Procurement!$U$2:$U$1801,0)),"") -> 24240.55 | M7: =IFERROR(INDEX(Cleaned_Procurement!$N$2:$N$1801,MATCH($F7,Cleaned_Procurement!$U$2:$U$1801,0)),"") -> Duplicate ID - review
A8: Missing spend | B8: =COUNTIF(Cleaned_Procurement!$N$2:$N$1801,A8) -> 1 | C8: =SUMIFS(Cleaned_Procurement!$J$2:$J$1801,Cleaned_Procurement!$N$2:$N$1801,A8) -> 0 | D8: Excluded (value unknown). Request invoice copy from source system. | F8: 3 | G8: =IFERROR(INDEX(Cleaned_Procurement!$G$2:$G$1801,MATCH($F8,Cleaned_Procurement!$U$2:$U$1801,0)),"") -> INV-2025-00249 | H8: =IFERROR(INDEX(Cleaned_Procurement!$A$2:$A$1801,MATCH($F8,Cleaned_Procurement!$U$2:$U$1801,0)),"") -> 46001 | I8: =IFERROR(INDEX(Cleaned_Procurement!$E$2:$E$1801,MATCH($F8,Cleaned_Procurement!$U$2:$U$1801,0)),"") -> KitchenPro | J8: =IFERROR(INDEX(Cleaned_Procurement!$B$2:$B$1801,MATCH($F8,Cleaned_Procurement!$U$2:$U$1801,0)),"") -> S020 | K8: =IFERROR(INDEX(Cleaned_Procurement!$F$2:$F$1801,MATCH($F8,Cleaned_Procurement!$U$2:$U$1801,0)),"") -> Food & Catering | L8: =IFERROR(INDEX(Cleaned_Procurement!$J$2:$J$1801,MATCH($F8,Cleaned_Procurement!$U$2:$U$1801,0)),"") -> 1786.89 | M8: =IFERROR(INDEX(Cleaned_Procurement!$N$2:$N$1801,MATCH($F8,Cleaned_Procurement!$U$2:$U$1801,0)),"") -> Duplicate ID - review
A9: Duplicate invoice | B9: =COUNTIF(Cleaned_Procurement!$N$2:$N$1801,A9) -> 0 | C9: =SUMIFS(Cleaned_Procurement!$J$2:$J$1801,Cleaned_Procurement!$N$2:$N$1801,A9) -> 0 | D9: Same ID + supplier + amount. Second occurrence excluded from spend. | F9: 4 | G9: =IFERROR(INDEX(Cleaned_Procurement!$G$2:$G$1801,MATCH($F9,Cleaned_Procurement!$U$2:$U$1801,0)),"") -> INV-2025-00512 | H9: =IFERROR(INDEX(Cleaned_Procurement!$A$2:$A$1801,MATCH($F9,Cleaned_Procurement!$U$2:$U$1801,0)),"") -> 45816 | I9: =IFERROR(INDEX(Cleaned_Procurement!$E$2:$E$1801,MATCH($F9,Cleaned_Procurement!$U$2:$U$1801,0)),"") -> CloudLink | J9: =IFERROR(INDEX(Cleaned_Procurement!$B$2:$B$1801,MATCH($F9,Cleaned_Procurement!$U$2:$U$1801,0)),"") -> S003 | K9: =IFERROR(INDEX(Cleaned_Procurement!$F$2:$F$1801,MATCH($F9,Cleaned_Procurement!$U$2:$U$1801,0)),"") -> Medical Supplies | L9: =IFERROR(INDEX(Cleaned_Procurement!$J$2:$J$1801,MATCH($F9,Cleaned_Procurement!$U$2:$U$1801,0)),"") -> 2354.05 | M9: =IFERROR(INDEX(Cleaned_Procurement!$N$2:$N$1801,MATCH($F9,Cleaned_Procurement!$U$2:$U$1801,0)),"") -> Category mismatch
A10: Duplicate ID - review | B10: =COUNTIF(Cleaned_Procurement!$N$2:$N$1801,A10) -> 2 | C10: =SUMIFS(Cleaned_Procurement!$J$2:$J$1801,Cleaned_Procurement!$N$2:$N$1801,A10) -> 26027.44 | D10: Same ID, different supplier/amount: likely ID collision, both retained and referred. | F10: 5 | G10: =IFERROR(INDEX(Cleaned_Procurement!$G$2:$G$1801,MATCH($F10,Cleaned_Procurement!$U$2:$U$1801,0)),"") -> INV-2025-00902 | H10: =IFERROR(INDEX(Cleaned_Procurement!$A$2:$A$1801,MATCH($F10,Cleaned_Procurement!$U$2:$U$1801,0)),"") -> 45901 | I10: =IFERROR(INDEX(Cleaned_Procurement!$E$2:$E$1801,MATCH($F10,Cleaned_Procurement!$U$2:$U$1801,0)),"") -> FleetFuel | J10: =IFERROR(INDEX(Cleaned_Procurement!$B$2:$B$1801,MATCH($F10,Cleaned_Procurement!$U$2:$U$1801,0)),"") | K10: =IFERROR(INDEX(Cleaned_Procurement!$F$2:$F$1801,MATCH($F10,Cleaned_Procurement!$U$2:$U$1801,0)),"") -> Vehicle & Fuel | L10: =IFERROR(INDEX(Cleaned_Procurement!$J$2:$J$1801,MATCH($F10,Cleaned_Procurement!$U$2:$U$1801,0)),"") -> 5662.41 | M10: =IFERROR(INDEX(Cleaned_Procurement!$N$2:$N$1801,MATCH($F10,Cleaned_Procurement!$U$2:$U$1801,0)),"") -> Missing site
A11: Category mismatch | B11: =COUNTIF(Cleaned_Procurement!$N$2:$N$1801,A11) -> 1 | C11: =SUMIFS(Cleaned_Procurement!$J$2:$J$1801,Cleaned_Procurement!$N$2:$N$1801,A11) -> 2354.05 | D11: Invoice category differs from supplier master. Retained as invoiced, referred to category owner. | F11: 6 | G11: =IFERROR(INDEX(Cleaned_Procurement!$G$2:$G$1801,MATCH($F11,Cleaned_Procurement!$U$2:$U$1801,0)),"") -> INV-2025-01101 | H11: =IFERROR(INDEX(Cleaned_Procurement!$A$2:$A$1801,MATCH($F11,Cleaned_Procurement!$U$2:$U$1801,0)),"") -> 45761 | I11: =IFERROR(INDEX(Cleaned_Procurement!$E$2:$E$1801,MATCH($F11,Cleaned_Procurement!$U$2:$U$1801,0)),"") -> RoadReady | J11: =IFERROR(INDEX(Cleaned_Procurement!$B$2:$B$1801,MATCH($F11,Cleaned_Procurement!$U$2:$U$1801,0)),"") -> S020 | K11: =IFERROR(INDEX(Cleaned_Procurement!$F$2:$F$1801,MATCH($F11,Cleaned_Procurement!$U$2:$U$1801,0)),"") -> Vehicle & Fuel | L11: =IFERROR(INDEX(Cleaned_Procurement!$J$2:$J$1801,MATCH($F11,Cleaned_Procurement!$U$2:$U$1801,0)),"") | M11: =IFERROR(INDEX(Cleaned_Procurement!$N$2:$N$1801,MATCH($F11,Cleaned_Procurement!$U$2:$U$1801,0)),"") -> Missing spend
A12: OK | B12: =COUNTIF(Cleaned_Procurement!$N$2:$N$1801,A12) -> 1794 | C12: =SUMIFS(Cleaned_Procurement!$J$2:$J$1801,Cleaned_Procurement!$N$2:$N$1801,A12) -> 13887938 | D12: Passed all checks. | F12: 7 | G12: =IFERROR(INDEX(Cleaned_Procurement!$G$2:$G$1801,MATCH($F12,Cleaned_Procurement!$U$2:$U$1801,0)),"") | H12: =IFERROR(INDEX(Cleaned_Procurement!$A$2:$A$1801,MATCH($F12,Cleaned_Procurement!$U$2:$U$1801,0)),"") | I12: =IFERROR(INDEX(Cleaned_Procurement!$E$2:$E$1801,MATCH($F12,Cleaned_Procurement!$U$2:$U$1801,0)),"") | J12: =IFERROR(INDEX(Cleaned_Procurement!$B$2:$B$1801,MATCH($F12,Cleaned_Procurement!$U$2:$U$1801,0)),"") | K12: =IFERROR(INDEX(Cleaned_Procurement!$F$2:$F$1801,MATCH($F12,Cleaned_Procurement!$U$2:$U$1801,0)),"") | L12: =IFERROR(INDEX(Cleaned_Procurement!$J$2:$J$1801,MATCH($F12,Cleaned_Procurement!$U$2:$U$1801,0)),"") | M12: =IFERROR(INDEX(Cleaned_Procurement!$N$2:$N$1801,MATCH($F12,Cleaned_Procurement!$U$2:$U$1801,0)),"")
A13: Total records | B13: =SUM(B6:B12) -> 1800 | F13: 8 | G13: =IFERROR(INDEX(Cleaned_Procurement!$G$2:$G$1801,MATCH($F13,Cleaned_Procurement!$U$2:$U$1801,0)),"") | H13: =IFERROR(INDEX(Cleaned_Procurement!$A$2:$A$1801,MATCH($F13,Cleaned_Procurement!$U$2:$U$1801,0)),"") | I13: =IFERROR(INDEX(Cleaned_Procurement!$E$2:$E$1801,MATCH($F13,Cleaned_Procurement!$U$2:$U$1801,0)),"") | J13: =IFERROR(INDEX(Cleaned_Procurement!$B$2:$B$1801,MATCH($F13,Cleaned_Procurement!$U$2:$U$1801,0)),"") | K13: =IFERROR(INDEX(Cleaned_Procurement!$F$2:$F$1801,MATCH($F13,Cleaned_Procurement!$U$2:$U$1801,0)),"") | L13: =IFERROR(INDEX(Cleaned_Procurement!$J$2:$J$1801,MATCH($F13,Cleaned_Procurement!$U$2:$U$1801,0)),"") | M13: =IFERROR(INDEX(Cleaned_Procurement!$N$2:$N$1801,MATCH($F13,Cleaned_Procurement!$U$2:$U$1801,0)),"")
A14: Exception rate | B14: =IFERROR(1-B12/B13,0) -> 0.0033333333 | F14: 9 | G14: =IFERROR(INDEX(Cleaned_Procurement!$G$2:$G$1801,MATCH($F14,Cleaned_Procurement!$U$2:$U$1801,0)),"") | H14: =IFERROR(INDEX(Cleaned_Procurement!$A$2:$A$1801,MATCH($F14,Cleaned_Procurement!$U$2:$U$1801,0)),"") | I14: =IFERROR(INDEX(Cleaned_Procurement!$E$2:$E$1801,MATCH($F14,Cleaned_Procurement!$U$2:$U$1801,0)),"") | J14: =IFERROR(INDEX(Cleaned_Procurement!$B$2:$B$1801,MATCH($F14,Cleaned_Procurement!$U$2:$U$1801,0)),"") | K14: =IFERROR(INDEX(Cleaned_Procurement!$F$2:$F$1801,MATCH($F14,Cleaned_Procurement!$U$2:$U$1801,0)),"") | L14: =IFERROR(INDEX(Cleaned_Procurement!$J$2:$J$1801,MATCH($F14,Cleaned_Procurement!$U$2:$U$1801,0)),"") | M14: =IFERROR(INDEX(Cleaned_Procurement!$N$2:$N$1801,MATCH($F14,Cleaned_Procurement!$U$2:$U$1801,0)),"")
F15: 10 | G15: =IFERROR(INDEX(Cleaned_Procurement!$G$2:$G$1801,MATCH($F15,Cleaned_Procurement!$U$2:$U$1801,0)),"") | H15: =IFERROR(INDEX(Cleaned_Procurement!$A$2:$A$1801,MATCH($F15,Cleaned_Procurement!$U$2:$U$1801,0)),"") | I15: =IFERROR(INDEX(Cleaned_Procurement!$E$2:$E$1801,MATCH($F15,Cleaned_Procurement!$U$2:$U$1801,0)),"") | J15: =IFERROR(INDEX(Cleaned_Procurement!$B$2:$B$1801,MATCH($F15,Cleaned_Procurement!$U$2:$U$1801,0)),"") | K15: =IFERROR(INDEX(Cleaned_Procurement!$F$2:$F$1801,MATCH($F15,Cleaned_Procurement!$U$2:$U$1801,0)),"") | L15: =IFERROR(INDEX(Cleaned_Procurement!$J$2:$J$1801,MATCH($F15,Cleaned_Procurement!$U$2:$U$1801,0)),"") | M15: =IFERROR(INDEX(Cleaned_Procurement!$N$2:$N$1801,MATCH($F15,Cleaned_Procurement!$U$2:$U$1801,0)),"")
A16: 2. Reconciliation: raw -> cleaned -> finance ledger | F16: 11 | G16: =IFERROR(INDEX(Cleaned_Procurement!$G$2:$G$1801,MATCH($F16,Cleaned_Procurement!$U$2:$U$1801,0)),"") | H16: =IFERROR(INDEX(Cleaned_Procurement!$A$2:$A$1801,MATCH($F16,Cleaned_Procurement!$U$2:$U$1801,0)),"") | I16: =IFERROR(INDEX(Cleaned_Procurement!$E$2:$E$1801,MATCH($F16,Cleaned_Procurement!$U$2:$U$1801,0)),"") | J16: =IFERROR(INDEX(Cleaned_Procurement!$B$2:$B$1801,MATCH($F16,Cleaned_Procurement!$U$2:$U$1801,0)),"") | K16: =IFERROR(INDEX(Cleaned_Procurement!$F$2:$F$1801,MATCH($F16,Cleaned_Procurement!$U$2:$U$1801,0)),"") | L16: =IFERROR(INDEX(Cleaned_Procurement!$J$2:$J$1801,MATCH($F16,Cleaned_Procurement!$U$2:$U$1801,0)),"") | M16: =IFERROR(INDEX(Cleaned_Procurement!$N$2:$N$1801,MATCH($F16,Cleaned_Procurement!$U$2:$U$1801,0)),"")
A17: Check | B17: Value | C17: Compare to | D17: Status | F17: 12 | G17: =IFERROR(INDEX(Cleaned_Procurement!$G$2:$G$1801,MATCH($F17,Cleaned_Procurement!$U$2:$U$1801,0)),"") | H17: =IFERROR(INDEX(Cleaned_Procurement!$A$2:$A$1801,MATCH($F17,Cleaned_Procurement!$U$2:$U$1801,0)),"") | I17: =IFERROR(INDEX(Cleaned_Procurement!$E$2:$E$1801,MATCH($F17,Cleaned_Procurement!$U$2:$U$1801,0)),"") | J17: =IFERROR(INDEX(Cleaned_Procurement!$B$2:$B$1801,MATCH($F17,Cleaned_Procurement!$U$2:$U$1801,0)),"") | K17: =IFERROR(INDEX(Cleaned_Procurement!$F$2:$F$1801,MATCH($F17,Cleaned_Procurement!$U$2:$U$1801,0)),"") | L17: =IFERROR(INDEX(Cleaned_Procurement!$J$2:$J$1801,MATCH($F17,Cleaned_Procurement!$U$2:$U$1801,0)),"") | M17: =IFERROR(INDEX(Cleaned_Procurement!$N$2:$N$1801,MATCH($F17,Cleaned_Procurement!$U$2:$U$1801,0)),"")
A18: Raw procurement rows | B18: =COUNTA(Procurement_Raw!G2:G1801) -> 1800 | C18: =COUNTA(Cleaned_Procurement!G2:G1801) -> 1800 | D18: =IF(ROUND(B18-C18,2)=0,"PASS","FAIL") -> PASS
A19: Raw GrossSpend total | B19: =SUM(Procurement_Raw!J2:J1801) -> 13922682
A20: Less: excluded duplicates | B20: =SUMIFS(Cleaned_Procurement!$J$2:$J$1801,Cleaned_Procurement!$N$2:$N$1801,"Duplicate invoice") -> 0
A21: Cleaned NetSpend total | B21: =SUM(Cleaned_Procurement!O2:O1801) -> 13922682 | C21: =B19-B20 -> 13922682 | D21: =IF(ROUND(B21-C21,2)=0,"PASS","FAIL") -> PASS
A22: Procurement per finance ledger | B22: =SUM(Finance_Raw!G:G) -> 13917019 | C22: =B21 -> 13922682 | D22: =IF(ABS(B22-C22)<=ABS(C22)*$B$28,"PASS","FAIL - "&TEXT(B22-C22,"£#,##0")) -> PASS
A23: Fleet: Fleet_Raw vs ledger | B23: =SUM(Fleet_Raw!L:L) -> 882007.36 | C23: =SUM(Finance_Raw!H:H) -> 882007.36 | D23: =IF(ABS(B23-C23)<=ABS(C23)*$B$28,"PASS","FAIL - "&TEXT(B23-C23,"£#,##0")) -> PASS
A24: Agency: Agency_Raw vs ledger | B24: =SUM(Agency_Raw!I:I) -> 1341086 | C24: =SUM(Finance_Raw!I:I) -> 1341086 | D24: =IF(ABS(B24-C24)<=ABS(C24)*$B$28,"PASS","FAIL - "&TEXT(B24-C24,"£#,##0")) -> PASS
A25: Payroll: Workforce_Raw vs ledger | B25: =SUM(Workforce_Raw!L:L) -> 38123646 | C25: =SUM(Finance_Raw!F:F) -> 38123646 | D25: =IF(ABS(B25-C25)<=ABS(C25)*$B$28,"PASS","FAIL - "&TEXT(B25-C25,"£#,##0")) -> PASS
A26: Opex: components vs ActualOpex | B26: =SUM(Finance_Raw!F:J) -> 60352965 | C26: =SUM(Finance_Raw!L:L) -> 60352965 | D26: =IF(ABS(B26-C26)<=ABS(C26)*$B$28,"PASS","FAIL - "&TEXT(B26-C26,"£#,##0")) -> PASS
A28: Reconciliation tolerance | B28: 0.001
A30: 3. Standardisation
A31: Invoices with supplier/category casing or whitespace corrected | B31: =SUM(Cleaned_Procurement!V2:V1801) -> 15
A32: Invoices whose supplier is not in the master | B32: =COUNTIFS(Cleaned_Procurement!P2:P1801,"Unmapped",Cleaned_Procurement!E2:E1801,"<>") -> 1
A33: Supplier master rows removed (duplicates / conflicts) | B33: 14
A35: 4. Completeness of key raw fields
A36: Field | B36: Blank values | C36: Completeness
A37: SiteID | B37: =COUNTBLANK(Procurement_Raw!B2:B1801) -> 1 | C37: =1-B37/($B$13) -> 0.99944444
A38: Supplier | B38: =COUNTBLANK(Procurement_Raw!E2:E1801) -> 1 | C38: =1-B38/($B$13) -> 0.99944444
A39: Category | B39: =COUNTBLANK(Procurement_Raw!F2:F1801) -> 0 | C39: =1-B39/($B$13) -> 1
A40: InvoiceID | B40: =COUNTBLANK(Procurement_Raw!G2:G1801) -> 0 | C40: =1-B40/($B$13) -> 1
A41: GrossSpend | B41: =COUNTBLANK(Procurement_Raw!J2:J1801) -> 1 | C41: =1-B41/($B$13) -> 0.99944444

Sheet Cleaned_Procurement
A1: InvoiceDate | B1: SiteID | C1: SiteName | D1: Region | E1: Supplier | F1: Category | G1: InvoiceID | H1: Quantity | I1: UnitCost | J1: GrossSpend | K1: PaymentTermsDays | L1: SourceSystem | M1: Contracted | N1: DataQualityFlag | O1: NetSpend_Clean | P1: Supplier_Category_Lookup | Q1: Savings_Target | R1: Potential_Saving | S1: Month | T1: Town | U1: ExceptionNo | V1: StandardisedFlag
A2: =Procurement_Raw!A2 -> 45798 | B2: =TRIM(Procurement_Raw!B2) -> S006 | C2: =Procurement_Raw!C2 -> Birmingham Care & Education Centre | D2: =Procurement_Raw!D2 -> Midlands | E2: =IF(TRIM(Procurement_Raw!E2)="","",IFERROR(INDEX(Supplier_Lookup!$A$2:$A$25,MATCH(TRIM(Procurement_Raw!E2),Supplier_Lookup!$A$2:$A$25,0)),TRIM(Procurement_Raw!E2))) -> FreshServe | F2: =IFERROR(INDEX(Category_Targets!$A$2:$A$9,MATCH(TRIM(Procurement_Raw!F2),Category_Targets!$A$2:$A$9,0)),"Unmapped") -> Food & Catering | G2: =TRIM(Procurement_Raw!G2) -> INV-2025-00001 | H2: =Procurement_Raw!H2 -> 32 | I2: =Procurement_Raw!I2 -> 85.42 | J2: =IF(Procurement_Raw!J2="","",Procurement_Raw!J2) -> 2733.44 | K2: =Procurement_Raw!K2 -> 30 | L2: =Procurement_Raw!L2 -> ERP | M2: =Procurement_Raw!O2 -> Y | N2: =IF(E2="","Missing supplier",IF(B2="","Missing site",IF(J2="","Missing spend",IF(COUNTIFS($G$2:G2,G2,$E$2:E2,E2,$J$2:J2,J2)>1,"Duplicate invoice",IF(COUNTIF($G$2:$G$1801,G2)>1,"Duplicate ID - review",IF(AND(P2<>"Unmapped",P2<>F2),"Category mismatch","OK")))))) -> OK | O2: =IF(OR(N2="Missing spend",N2="Duplicate invoice"),0,J2) -> 2733.44 | P2: =IF(E2="","Unmapped",IFERROR(INDEX(Supplier_Lookup!$B$2:$B$25,MATCH(E2,Supplier_Lookup!$A$2:$A$25,0)),"Unmapped")) -> Food & Catering | Q2: =IFERROR(INDEX(Category_Targets!$B$2:$B$9,MATCH(F2,Category_Targets!$A$2:$A$9,0)),0) -> 0.04 | R2: =O2*Q2 -> 109.3376 | S2: =DATE(YEAR(A2),MONTH(A2),1) -> 45778 | T2: =IFERROR(VLOOKUP(B2,Sites!$A$2:$D$21,4,FALSE()),"Unknown") -> Birmingham | U2: =IF(N2="OK","",COUNTIF($N$2:N2,"<>OK")) | V2: =IF(OR(NOT(EXACT(E2,TRIM(Procurement_Raw!E2))),NOT(EXACT(F2,TRIM(Procurement_Raw!F2)))),1,0) -> 1
A3: =Procurement_Raw!A3 -> 45937 | B3: =TRIM(Procurement_Raw!B3) -> S008 | C3: =Procurement_Raw!C3 -> Leicester Care & Education Centre | D3: =Procurement_Raw!D3 -> Midlands | E3: =IF(TRIM(Procurement_Raw!E3)="","",IFERROR(INDEX(Supplier_Lookup!$A$2:$A$25,MATCH(TRIM(Procurement_Raw!E3),Supplier_Lookup!$A$2:$A$25,0)),TRIM(Procurement_Raw!E3))) -> KitchenPro | F3: =IFERROR(INDEX(Category_Targets!$A$2:$A$9,MATCH(TRIM(Procurement_Raw!F3),Category_Targets!$A$2:$A$9,0)),"Unmapped") -> Food & Catering | G3: =TRIM(Procurement_Raw!G3) -> INV-2025-00002 | H3: =Procurement_Raw!H3 -> 12 | I3: =Procurement_Raw!I3 -> 60.24 | J3: =IF(Procurement_Raw!J3="","",Procurement_Raw!J3) -> 722.88 | K3: =Procurement_Raw!K3 -> 60 | L3: =Procurement_Raw!L3 -> Procurement Portal | M3: =Procurement_Raw!O3 -> N | N3: =IF(E3="","Missing supplier",IF(B3="","Missing site",IF(J3="","Missing spend",IF(COUNTIFS($G$2:G3,G3,$E$2:E3,E3,$J$2:J3,J3)>1,"Duplicate invoice",IF(COUNTIF($G$2:$G$1801,G3)>1,"Duplicate ID - review",IF(AND(P3<>"Unmapped",P3<>F3),"Category mismatch","OK")))))) -> OK | O3: =IF(OR(N3="Missing spend",N3="Duplicate invoice"),0,J3) -> 722.88 | P3: =IF(E3="","Unmapped",IFERROR(INDEX(Supplier_Lookup!$B$2:$B$25,MATCH(E3,Supplier_Lookup!$A$2:$A$25,0)),"Unmapped")) -> Food & Catering | Q3: =IFERROR(INDEX(Category_Targets!$B$2:$B$9,MATCH(F3,Category_Targets!$A$2:$A$9,0)),0) -> 0.04 | R3: =O3*Q3 -> 28.9152 | S3: =DATE(YEAR(A3),MONTH(A3),1) -> 45931 | T3: =IFERROR(VLOOKUP(B3,Sites!$A$2:$D$21,4,FALSE()),"Unknown") -> Leicester | U3: =IF(N3="OK","",COUNTIF($N$2:N3,"<>OK")) | V3: =IF(OR(NOT(EXACT(E3,TRIM(Procurement_Raw!E3))),NOT(EXACT(F3,TRIM(Procurement_Raw!F3)))),1,0) -> 0
A4: =Procurement_Raw!A4 -> 45769 | B4: =TRIM(Procurement_Raw!B4) -> S009 | C4: =Procurement_Raw!C4 -> Derby Care & Education Centre | D4: =Procurement_Raw!D4 -> Midlands | E4: =IF(TRIM(Procurement_Raw!E4)="","",IFERROR(INDEX(Supplier_Lookup!$A$2:$A$25,MATCH(TRIM(Procurement_Raw!E4),Supplier_Lookup!$A$2:$A$25,0)),TRIM(Procurement_Raw!E4))) -> MediSure | F4: =IFERROR(INDEX(Category_Targets!$A$2:$A$9,MATCH(TRIM(Procurement_Raw!F4),Category_Targets!$A$2:$A$9,0)),"Unmapped") -> Medical Supplies | G4: =TRIM(Procurement_Raw!G4) -> INV-2025-00003 | H4: =Procurement_Raw!H4 -> 30 | I4: =Procurement_Raw!I4 -> 171.35 | J4: =IF(Procurement_Raw!J4="","",Procurement_Raw!J4) -> 5140.56 | K4: =Procurement_Raw!K4 -> 60 | L4: =Procurement_Raw!L4 -> Legacy Spend File | M4: =Procurement_Raw!O4 -> Y | N4: =IF(E4="","Missing supplier",IF(B4="","Missing site",IF(J4="","Missing spend",IF(COUNTIFS($G$2:G4,G4,$E$2:E4,E4,$J$2:J4,J4)>1,"Duplicate invoice",IF(COUNTIF($G$2:$G$1801,G4)>1,"Duplicate ID - review",IF(AND(P4<>"Unmapped",P4<>F4),"Category mismatch","OK")))))) -> OK | O4: =IF(OR(N4="Missing spend",N4="Duplicate invoice"),0,J4) -> 5140.56 | P4: =IF(E4="","Unmapped",IFERROR(INDEX(Supplier_Lookup!$B$2:$B$25,MATCH(E4,Supplier_Lookup!$A$2:$A$25,0)),"Unmapped")) -> Medical Supplies | Q4: =IFERROR(INDEX(Category_Targets!$B$2:$B$9,MATCH(F4,Category_Targets!$A$2:$A$9,0)),0) -> 0.06 | R4: =O4*Q4 -> 308.4336 | S4: =DATE(YEAR(A4),MONTH(A4),1) -> 45748 | T4: =IFERROR(VLOOKUP(B4,Sites!$A$2:$D$21,4,FALSE()),"Unknown") -> Derby | U4: =IF(N4="OK","",COUNTIF($N$2:N4,"<>OK")) | V4: =IF(OR(NOT(EXACT(E4,TRIM(Procurement_Raw!E4))),NOT(EXACT(F4,TRIM(Procurement_Raw!F4)))),1,0) -> 0
A5: =Procurement_Raw!A5 -> 45990 | B5: =TRIM(Procurement_Raw!B5) -> S006 | C5: =Procurement_Raw!C5 -> Birmingham Care & Education Centre | D5: =Procurement_Raw!D5 -> Midlands | E5: =IF(TRIM(Procurement_Raw!E5)="","",IFERROR(INDEX(Supplier_Lookup!$A$2:$A$25,MATCH(TRIM(Procurement_Raw!E5),Supplier_Lookup!$A$2:$A$25,0)),TRIM(Procurement_Raw!E5))) -> PowerDirect | F5: =IFERROR(INDEX(Category_Targets!$A$2:$A$9,MATCH(TRIM(Procurement_Raw!F5),Category_Targets!$A$2:$A$9,0)),"Unmapped") -> Utilities | G5: =TRIM(Procurement_Raw!G5) -> INV-2025-00004 | H5: =Procurement_Raw!H5 -> 70 | I5: =Procurement_Raw!I5 -> 577.74 | J5: =IF(Procurement_Raw!J5="","",Procurement_Raw!J5) -> 40441.94 | K5: =Procurement_Raw!K5 -> 45 | L5: =Procurement_Raw!L5 -> ERP | M5: =Procurement_Raw!O5 -> N | N5: =IF(E5="","Missing supplier",IF(B5="","Missing site",IF(J5="","Missing spend",IF(COUNTIFS($G$2:G5,G5,$E$2:E5,E5,$J$2:J5,J5)>1,"Duplicate invoice",IF(COUNTIF($G$2:$G$1801,G5)>1,"Duplicate ID - review",IF(AND(P5<>"Unmapped",P5<>F5),"Category mismatch","OK")))))) -> OK | O5: =IF(OR(N5="Missing spend",N5="Duplicate invoice"),0,J5) -> 40441.94 | P5: =IF(E5="","Unmapped",IFERROR(INDEX(Supplier_Lookup!$B$2:$B$25,MATCH(E5,Supplier_Lookup!$A$2:$A$25,0)),"Unmapped")) -> Utilities | Q5: =IFERROR(INDEX(Category_Targets!$B$2:$B$9,MATCH(F5,Category_Targets!$A$2:$A$9,0)),0) -> 0.03 | R5: =O5*Q5 -> 1213.2582 | S5: =DATE(YEAR(A5),MONTH(A5),1) -> 45962 | T5: =IFERROR(VLOOKUP(B5,Sites!$A$2:$D$21,4,FALSE()),"Unknown") -> Birmingham | U5: =IF(N5="OK","",COUNTIF($N$2:N5,"<>OK")) | V5: =IF(OR(NOT(EXACT(E5,TRIM(Procurement_Raw!E5))),NOT(EXACT(F5,TRIM(Procurement_Raw!F5)))),1,0) -> 0
A6: =Procurement_Raw!A6 -> 45739 | B6: =TRIM(Procurement_Raw!B6) -> S016 | C6: =Procurement_Raw!C6 -> Cardiff Care & Education Centre | D6: =Procurement_Raw!D6 -> Wales | E6: =IF(TRIM(Procurement_Raw!E6)="","",IFERROR(INDEX(Supplier_Lookup!$A$2:$A$25,MATCH(TRIM(Procurement_Raw!E6),Supplier_Lookup!$A$2:$A$25,0)),TRIM(Procurement_Raw!E6))) -> CloudLink | F6: =IFERROR(INDEX(Category_Targets!$A$2:$A$9,MATCH(TRIM(Procurement_Raw!F6),Category_Targets!$A$2:$A$9,0)),"Unmapped") -> IT & Telecoms | G6: =TRIM(Procurement_Raw!G6) -> INV-2025-00005 | H6: =Procurement_Raw!H6 -> 55 | I6: =Procurement_Raw!I6 -> 193.42 | J6: =IF(Procurement_Raw!J6="","",Procurement_Raw!J6) -> 10637.88 | K6: =Procurement_Raw!K6 -> 45 | L6: =Procurement_Raw!L6 -> Procurement Portal | M6: =Procurement_Raw!O6 -> Y | N6: =IF(E6="","Missing supplier",IF(B6="","Missing site",IF(J6="","Missing spend",IF(COUNTIFS($G$2:G6,G6,$E$2:E6,E6,$J$2:J6,J6)>1,"Duplicate invoice",IF(COUNTIF($G$2:$G$1801,G6)>1,"Duplicate ID - review",IF(AND(P6<>"Unmapped",P6<>F6),"Category mismatch","OK")))))) -> OK | O6: =IF(OR(N6="Missing spend",N6="Duplicate invoice"),0,J6) -> 10637.88 | P6: =IF(E6="","Unmapped",IFERROR(INDEX(Supplier_Lookup!$B$2:$B$25,MATCH(E6,Supplier_Lookup!$A$2:$A$25,0)),"Unmapped")) -> IT & Telecoms | Q6: =IFERROR(INDEX(Category_Targets!$B$2:$B$9,MATCH(F6,Category_Targets!$A$2:$A$9,0)),0) -> 0.08 | R6: =O6*Q6 -> 851.0304 | S6: =DATE(YEAR(A6),MONTH(A6),1) -> 45717 | T6: =IFERROR(VLOOKUP(B6,Sites!$A$2:$D$21,4,FALSE()),"Unknown") -> Cardiff | U6: =IF(N6="OK","",COUNTIF($N$2:N6,"<>OK")) | V6: =IF(OR(NOT(EXACT(E6,TRIM(Procurement_Raw!E6))),NOT(EXACT(F6,TRIM(Procurement_Raw!F6)))),1,0) -> 0
A7: =Procurement_Raw!A7 -> 45710 | B7: =TRIM(Procurement_Raw!B7) -> S013 | C7: =Procurement_Raw!C7 -> Reading Care & Education Centre | D7: =Procurement_Raw!D7 -> South | E7: =IF(TRIM(Procurement_Raw!E7)="","",IFERROR(INDEX(Supplier_Lookup!$A$2:$A$25,MATCH(TRIM(Procurement_Raw!E7),Supplier_Lookup!$A$2:$A$25,0)),TRIM(Procurement_Raw!E7))) -> WaterGrid | F7: =IFERROR(INDEX(Category_Targets!$A$2:$A$9,MATCH(TRIM(Procurement_Raw!F7),Category_Targets!$A$2:$A$9,0)),"Unmapped") -> Utilities | G7: =TRIM(Procurement_Raw!G7) -> INV-2025-00006 | H7: =Procurement_Raw!H7 -> 12 | I7: =Procurement_Raw!I7 -> 219.79 | J7: =IF(Procurement_Raw!J7="","",Procurement_Raw!J7) -> 2637.51 | K7: =Procurement_Raw!K7 -> 45 | L7: =Procurement_Raw!L7 -> ERP | M7: =Procurement_Raw!O7 -> N | N7: =IF(E7="","Missing supplier",IF(B7="","Missing site",IF(J7="","Missing spend",IF(COUNTIFS($G$2:G7,G7,$E$2:E7,E7,$J$2:J7,J7)>1,"Duplicate invoice",IF(COUNTIF($G$2:$G$1801,G7)>1,"Duplicate ID - review",IF(AND(P7<>"Unmapped",P7<>F7),"Category mismatch","OK")))))) -> OK | O7: =IF(OR(N7="Missing spend",N7="Duplicate invoice"),0,J7) -> 2637.51 | P7: =IF(E7="","Unmapped",IFERROR(INDEX(Supplier_Lookup!$B$2:$B$25,MATCH(E7,Supplier_Lookup!$A$2:$A$25,0)),"Unmapped")) -> Utilities | Q7: =IFERROR(INDEX(Category_Targets!$B$2:$B$9,MATCH(F7,Category_Targets!$A$2:$A$9,0)),0) -> 0.03 | R7: =O7*Q7 -> 79.1253 | S7: =DATE(YEAR(A7),MONTH(A7),1) -> 45689 | T7: =IFERROR(VLOOKUP(B7,Sites!$A$2:$D$21,4,FALSE()),"Unknown") -> Reading | U7: =IF(N7="OK","",COUNTIF($N$2:N7,"<>OK")) | V7: =IF(OR(NOT(EXACT(E7,TRIM(Procurement_Raw!E7))),NOT(EXACT(F7,TRIM(Procurement_Raw!F7)))),1,0) -> 0
A8: =Procurement_Raw!A8 -> 45793 | B8: =TRIM(Procurement_Raw!B8) -> S005 | C8: =Procurement_Raw!C8 -> Sheffield Care & Education Centre | D8: =Procurement_Raw!D8 -> North | E8: =IF(TRIM(Procurement_Raw!E8)="","",IFERROR(INDEX(Supplier_Lookup!$A$2:$A$25,MATCH(TRIM(Procurement_Raw!E8),Supplier_Lookup!$A$2:$A$25,0)),TRIM(Procurement_Raw!E8))) -> AutoCare | F8: =IFERROR(INDEX(Category_Targets!$A$2:$A$9,MATCH(TRIM(Procurement_Raw!F8),Category_Targets!$A$2:$A$9,0)),"Unmapped") -> Vehicle & Fuel | G8: =TRIM(Procurement_Raw!G8) -> INV-2025-00007 | H8: =Procurement_Raw!H8 -> 6 | I8: =Procurement_Raw!I8 -> 226.43 | J8: =IF(Procurement_Raw!J8="","",Procurement_Raw!J8) -> 1358.59 | K8: =Procurement_Raw!K8 -> 60 | L8: =Procurement_Raw!L8 -> Procurement Portal | M8: =Procurement_Raw!O8 -> N | N8: =IF(E8="","Missing supplier",IF(B8="","Missing site",IF(J8="","Missing spend",IF(COUNTIFS($G$2:G8,G8,$E$2:E8,E8,$J$2:J8,J8)>1,"Duplicate invoice",IF(COUNTIF($G$2:$G$1801,G8)>1,"Duplicate ID - review",IF(AND(P8<>"Unmapped",P8<>F8),"Category mismatch","OK")))))) -> OK | O8: =IF(OR(N8="Missing spend",N8="Duplicate invoice"),0,J8) -> 1358.59 | P8: =IF(E8="","Unmapped",IFERROR(INDEX(Supplier_Lookup!$B$2:$B$25,MATCH(E8,Supplier_Lookup!$A$2:$A$25,0)),"Unmapped")) -> Vehicle & Fuel | Q8: =IFERROR(INDEX(Category_Targets!$B$2:$B$9,MATCH(F8,Category_Targets!$A$2:$A$9,0)),0) -> 0.05 | R8: =O8*Q8 -> 67.9295 | S8: =DATE(YEAR(A8),MONTH(A8),1) -> 45778 | T8: =IFERROR(VLOOKUP(B8,Sites!$A$2:$D$21,4,FALSE()),"Unknown") -> Sheffield | U8: =IF(N8="OK","",COUNTIF($N$2:N8,"<>OK")) | V8: =IF(OR(NOT(EXACT(E8,TRIM(Procurement_Raw!E8))),NOT(EXACT(F8,TRIM(Procurement_Raw!F8)))),1,0) -> 0
A9: =Procurement_Raw!A9 -> 45698 | B9: =TRIM(Procurement_Raw!B9) -> S004 | C9: =Procurement_Raw!C9 -> Newcastle Care & Education Centre | D9: =Procurement_Raw!D9 -> North | E9: =IF(TRIM(Procurement_Raw!E9)="","",IFERROR(INDEX(Supplier_Lookup!$A$2:$A$25,MATCH(TRIM(Procurement_Raw!E9),Supplier_Lookup!$A$2:$A$25,0)),TRIM(Procurement_Raw!E9))) -> NourishCo | F9: =IFERROR(INDEX(Category_Targets!$A$2:$A$9,MATCH(TRIM(Procurement_Raw!F9),Category_Targets!$A$2:$A$9,0)),"Unmapped") -> Food & Catering | G9: =TRIM(Procurement_Raw!G9) -> INV-2025-00008 | H9: =Procurement_Raw!H9 -> 71 | I9: =Procurement_Raw!I9 -> 99.13 | J9: =IF(Procurement_Raw!J9="","",Procurement_Raw!J9) -> 7038.54 | K9: =Procurement_Raw!K9 -> 45 | L9: =Procurement_Raw!L9 -> Legacy Spend File | M9: =Procurement_Raw!O9 -> N | N9: =IF(E9="","Missing supplier",IF(B9="","Missing site",IF(J9="","Missing spend",IF(COUNTIFS($G$2:G9,G9,$E$2:E9,E9,$J$2:J9,J9)>1,"Duplicate invoice",IF(COUNTIF($G$2:$G$1801,G9)>1,"Duplicate ID - review",IF(AND(P9<>"Unmapped",P9<>F9),"Category mismatch","OK")))))) -> OK | O9: =IF(OR(N9="Missing spend",N9="Duplicate invoice"),0,J9) -> 7038.54 | P9: =IF(E9="","Unmapped",IFERROR(INDEX(Supplier_Lookup!$B$2:$B$25,MATCH(E9,Supplier_Lookup!$A$2:$A$25,0)),"Unmapped")) -> Food & Catering | Q9: =IFERROR(INDEX(Category_Targets!$B$2:$B$9,MATCH(F9,Category_Targets!$A$2:$A$9,0)),0) -> 0.04 | R9: =O9*Q9 -> 281.5416 | S9: =DATE(YEAR(A9),MONTH(A9),1) -> 45689 | T9: =IFERROR(VLOOKUP(B9,Sites!$A$2:$D$21,4,FALSE()),"Unknown") -> Newcastle | U9: =IF(N9="OK","",COUNTIF($N$2:N9,"<>OK")) | V9: =IF(OR(NOT(EXACT(E9,TRIM(Procurement_Raw!E9))),NOT(EXACT(F9,TRIM(Procurement_Raw!F9)))),1,0) -> 0
A10: =Procurement_Raw!A10 -> 45756 | B10: =TRIM(Procurement_Raw!B10) -> S017 | C10: =Procurement_Raw!C10 -> Swansea Care & Education Centre | D10: =Procurement_Raw!D10 -> Wales | E10: =IF(TRIM(Procurement_Raw!E10)="","",IFERROR(INDEX(Supplier_Lookup!$A$2:$A$25,MATCH(TRIM(Procurement_Raw!E10),Supplier_Lookup!$A$2:$A$25,0)),TRIM(Procurement_Raw!E10))) -> AutoCare | F10: =IFERROR(INDEX(Category_Targets!$A$2:$A$9,MATCH(TRIM(Procurement_Raw!F10),Category_Targets!$A$2:$A$9,0)),"Unmapped") -> Vehicle & Fuel | G10: =TRIM(Procurement_Raw!G10) -> INV-2025-00009 | H10: =Procurement_Raw!H10 -> 9 | I10: =Procurement_Raw!I10 -> 73.38 | J10: =IF(Procurement_Raw!J10="","",Procurement_Raw!J10) -> 660.43 | K10: =Procurement_Raw!K10 -> 30 | L10: =Procurement_Raw!L10 -> Legacy Spend File | M10: =Procurement_Raw!O10 -> N | N10: =IF(E10="","Missing supplier",IF(B10="","Missing site",IF(J10="","Missing spend",IF(COUNTIFS($G$2:G10,G10,$E$2:E10,E10,$J$2:J10,J10)>1,"Duplicate invoice",IF(COUNTIF($G$2:$G$1801,G10)>1,"Duplicate ID - review",IF(AND(P10<>"Unmapped",P10<>F10),"Category mismatch","OK")))))) -> OK | O10: =IF(OR(N10="Missing spend",N10="Duplicate invoice"),0,J10) -> 660.43 | P10: =IF(E10="","Unmapped",IFERROR(INDEX(Supplier_Lookup!$B$2:$B$25,MATCH(E10,Supplier_Lookup!$A$2:$A$25,0)),"Unmapped")) -> Vehicle & Fuel | Q10: =IFERROR(INDEX(Category_Targets!$B$2:$B$9,MATCH(F10,Category_Targets!$A$2:$A$9,0)),0) -> 0.05 | R10: =O10*Q10 -> 33.0215 | S10: =DATE(YEAR(A10),MONTH(A10),1) -> 45748 | T10: =IFERROR(VLOOKUP(B10,Sites!$A$2:$D$21,4,FALSE()),"Unknown") -> Swansea | U10: =IF(N10="OK","",COUNTIF($N$2:N10,"<>OK")) | V10: =IF(OR(NOT(EXACT(E10,TRIM(Procurement_Raw!E10))),NOT(EXACT(F10,TRIM(Procurement_Raw!F10)))),1,0) -> 0
A11: =Procurement_Raw!A11 -> 45777 | B11: =TRIM(Procurement_Raw!B11) -> S015 | C11: =Procurement_Raw!C11 -> Brighton Care & Education Centre | D11: =Procurement_Raw!D11 -> South | E11: =IF(TRIM(Procurement_Raw!E11)="","",IFERROR(INDEX(Supplier_Lookup!$A$2:$A$25,MATCH(TRIM(Procurement_Raw!E11),Supplier_Lookup!$A$2:$A$25,0)),TRIM(Procurement_Raw!E11))) -> CloudLink | F11: =IFERROR(INDEX(Category_Targets!$A$2:$A$9,MATCH(TRIM(Procurement_Raw!F11),Category_Targets!$A$2:$A$9,0)),"Unmapped") -> IT & Telecoms | G11: =TRIM(Procurement_Raw!G11) -> INV-2025-00010 | H11: =Procurement_Raw!H11 -> 13 | I11: =Procurement_Raw!I11 -> 296.5 | J11: =IF(Procurement_Raw!J11="","",Procurement_Raw!J11) -> 3854.46 | K11: =Procurement_Raw!K11 -> 45 | L11: =Procurement_Raw!L11 -> Procurement Portal | M11: =Procurement_Raw!O11 -> Y | N11: =IF(E11="","Missing supplier",IF(B11="","Missing site",IF(J11="","Missing spend",IF(COUNTIFS($G$2:G11,G11,$E$2:E11,E11,$J$2:J11,J11)>1,"Duplicate invoice",IF(COUNTIF($G$2:$G$1801,G11)>1,"Duplicate ID - review",IF(AND(P11<>"Unmapped",P11<>F11),"Category mismatch","OK")))))) -> OK | O11: =IF(OR(N11="Missing spend",N11="Duplicate invoice"),0,J11) -> 3854.46 | P11: =IF(E11="","Unmapped",IFERROR(INDEX(Supplier_Lookup!$B$2:$B$25,MATCH(E11,Supplier_Lookup!$A$2:$A$25,0)),"Unmapped")) -> IT & Telecoms | Q11: =IFERROR(INDEX(Category_Targets!$B$2:$B$9,MATCH(F11,Category_Targets!$A$2:$A$9,0)),0) -> 0.08 | R11: =O11*Q11 -> 308.3568 | S11: =DATE(YEAR(A11),MONTH(A11),1) -> 45748 | T11: =IFERROR(VLOOKUP(B11,Sites!$A$2:$D$21,4,FALSE()),"Unknown") -> Brighton | U11: =IF(N11="OK","",COUNTIF($N$2:N11,"<>OK")) | V11: =IF(OR(NOT(EXACT(E11,TRIM(Procurement_Raw!E11))),NOT(EXACT(F11,TRIM(Procurement_Raw!F11)))),1,0) -> 0
A12: =Procurement_Raw!A12 -> 45847 | B12: =TRIM(Procurement_Raw!B12) -> S016 | C12: =Procurement_Raw!C12 -> Cardiff Care & Education Centre | D12: =Procurement_Raw!D12 -> Wales | E12: =IF(TRIM(Procurement_Raw!E12)="","",IFERROR(INDEX(Supplier_Lookup!$A$2:$A$25,MATCH(TRIM(Procurement_Raw!E12),Supplier_Lookup!$A$2:$A$25,0)),TRIM(Procurement_Raw!E12))) -> FleetFuel | F12: =IFERROR(INDEX(Category_Targets!$A$2:$A$9,MATCH(TRIM(Procurement_Raw!F12),Category_Targets!$A$2:$A$9,0)),"Unmapped") -> Vehicle & Fuel | G12: =TRIM(Procurement_Raw!G12) -> INV-2025-00011 | H12: =Procurement_Raw!H12 -> 46 | I12: =Procurement_Raw!I12 -> 73.63 | J12: =IF(Procurement_Raw!J12="","",Procurement_Raw!J12) -> 3386.79 | K12: =Procurement_Raw!K12 -> 30 | L12: =Procurement_Raw!L12 -> Legacy Spend File | M12: =Procurement_Raw!O12 -> Y | N12: =IF(E12="","Missing supplier",IF(B12="","Missing site",IF(J12="","Missing spend",IF(COUNTIFS($G$2:G12,G12,$E$2:E12,E12,$J$2:J12,J12)>1,"Duplicate invoice",IF(COUNTIF($G$2:$G$1801,G12)>1,"Duplicate ID - review",IF(AND(P12<>"Unmapped",P12<>F12),"Category mismatch","OK")))))) -> OK | O12: =IF(OR(N12="Missing spend",N12="Duplicate invoice"),0,J12) -> 3386.79 | P12: =IF(E12="","Unmapped",IFERROR(INDEX(Supplier_Lookup!$B$2:$B$25,MATCH(E12,Supplier_Lookup!$A$2:$A$25,0)),"Unmapped")) -> Vehicle & Fuel | Q12: =IFERROR(INDEX(Category_Targets!$B$2:$B$9,MATCH(F12,Category_Targets!$A$2:$A$9,0)),0) -> 0.05 | R12: =O12*Q12 -> 169.3395 | S12: =DATE(YEAR(A12),MONTH(A12),1) -> 45839 | T12: =IFERROR(VLOOKUP(B12,Sites!$A$2:$D$21,4,FALSE()),"Unknown") -> Cardiff | U12: =IF(N12="OK","",COUNTIF($N$2:N12,"<>OK")) | V12: =IF(OR(NOT(EXACT(E12,TRIM(Procurement_Raw!E12))),NOT(EXACT(F12,TRIM(Procurement_Raw!F12)))),1,0) -> 0
A13: =Procurement_Raw!A13 -> 45983 | B13: =TRIM(Procurement_Raw!B13) -> S019 | C13: =Procurement_Raw!C13 -> Wrexham Care & Education Centre | D13: =Procurement_Raw!D13 -> Wales | E13: =IF(TRIM(Procurement_Raw!E13)="","",IFERROR(INDEX(Supplier_Lookup!$A$2:$A$25,MATCH(TRIM(Procurement_Raw!E13),Supplier_Lookup!$A$2:$A$25,0)),TRIM(Procurement_Raw!E13))) -> KitchenPro | F13: =IFERROR(INDEX(Category_Targets!$A$2:$A$9,MATCH(TRIM(Procurement_Raw!F13),Category_Targets!$A$2:$A$9,0)),"Unmapped") -> Food & Catering | G13: =TRIM(Procurement_Raw!G13) -> INV-2025-00012 | H13: =Procurement_Raw!H13 -> 22 | I13: =Procurement_Raw!I13 -> 50.31 | J13: =IF(Procurement_Raw!J13="","",Procurement_Raw!J13) -> 1106.86 | K13: =Procurement_Raw!K13 -> 60 | L13: =Procurement_Raw!L13 -> Legacy Spend File | M13: =Procurement_Raw!O13 -> N | N13: =IF(E13="","Missing supplier",IF(B13="","Missing site",IF(J13="","Missing spend",IF(COUNTIFS($G$2:G13,G13,$E$2:E13,E13,$J$2:J13,J13)>1,"Duplicate invoice",IF(COUNTIF($G$2:$G$1801,G13)>1,"Duplicate ID - review",IF(AND(P13<>"Unmapped",P13<>F13),"Category mismatch","OK")))))) -> OK | O13: =IF(OR(N13="Missing spend",N13="Duplicate invoice"),0,J13) -> 1106.86 | P13: =IF(E13="","Unmapped",IFERROR(INDEX(Supplier_Lookup!$B$2:$B$25,MATCH(E13,Supplier_Lookup!$A$2:$A$25,0)),"Unmapped")) -> Food & Catering | Q13: =IFERROR(INDEX(Category_Targets!$B$2:$B$9,MATCH(F13,Category_Targets!$A$2:$A$9,0)),0) -> 0.04 | R13: =O13*Q13 -> 44.2744 | S13: =DATE(YEAR(A13),MONTH(A13),1) -> 45962 | T13: =IFERROR(VLOOKUP(B13,Sites!$A$2:$D$21,4,FALSE()),"Unknown") -> Wrexham | U13: =IF(N13="OK","",COUNTIF($N$2:N13,"<>OK")) | V13: =IF(OR(NOT(EXACT(E13,TRIM(Procurement_Raw!E13))),NOT(EXACT(F13,TRIM(Procurement_Raw!F13)))),1,0) -> 0
... A1801: =Procurement_Raw!A1801 -> 45981 | B1801: =TRIM(Procurement_Raw!B1801) -> S020 | C1801: =Procurement_Raw!C1801 -> Bangor Care & Education Centre | D1801: =Procurement_Raw!D1801 -> Wales | E1801: =IF(TRIM(Procurement_Raw!E1801)="","",IFERROR(INDEX(Supplier_Lookup!$A$2:$A$25,MATCH(TRIM(Procurement_Raw!E1801),Supplier_Lookup!$A$2:$A$25,0)),TRIM(Procurement_Raw!E1801))) -> PrintCo | F1801: =IFERROR(INDEX(Category_Targets!$A$2:$A$9,MATCH(TRIM(Procurement_Raw!F1801),Category_Targets!$A$2:$A$9,0)),"Unmapped") -> Office & Training | G1801: =TRIM(Procurement_Raw!G1801) -> INV-2025-01800 | H1801: =Procurement_Raw!H1801 -> 46 | I1801: =Procurement_Raw!I1801 -> 75.88 | J1801: =IF(Procurement_Raw!J1801="","",Procurement_Raw!J1801) -> 3490.68 | K1801: =Procurement_Raw!K1801 -> 30 | L1801: =Procurement_Raw!L1801 -> ERP | M1801: =Procurement_Raw!O1801 -> N | N1801: =IF(E1801="","Missing supplier",IF(B1801="","Missing site",IF(J1801="","Missing spend",IF(COUNTIFS($G$2:G1801,G1801,$E$2:E1801,E1801,$J$2:J1801,J1801)>1,"Duplicate invoice",IF(COUNTIF($G$2:$G$1801,G1801)>1,"Duplicate ID - review",IF(AND(P1801<>"Unmapped",P1801<>F1801),"Category mismatch","OK")))))) -> OK | O1801: =IF(OR(N1801="Missing spend",N1801="Duplicate invoice"),0,J1801) -> 3490.68 | P1801: =IF(E1801="","Unmapped",IFERROR(INDEX(Supplier_Lookup!$B$2:$B$25,MATCH(E1801,Supplier_Lookup!$A$2:$A$25,0)),"Unmapped")) -> Office & Training | Q1801: =IFERROR(INDEX(Category_Targets!$B$2:$B$9,MATCH(F1801,Category_Targets!$A$2:$A$9,0)),0) -> 0.04 | R1801: =O1801*Q1801 -> 139.6272 | S1801: =DATE(YEAR(A1801),MONTH(A1801),1) -> 45962 | T1801: =IFERROR(VLOOKUP(B1801,Sites!$A$2:$D$21,4,FALSE()),"Unknown") -> Bangor | U1801: =IF(N1801="OK","",COUNTIF($N$2:N1801,"<>OK")) | V1801: =IF(OR(NOT(EXACT(E1801,TRIM(Procurement_Raw!E1801))),NOT(EXACT(F1801,TRIM(Procurement_Raw!F1801)))),1,0) -> 0

Sheet Procurement_Raw
A1: InvoiceDate | B1: SiteID | C1: SiteName | D1: Region | E1: Supplier | F1: Category | G1: InvoiceID | H1: Quantity | I1: UnitCost | J1: GrossSpend | K1: PaymentTermsDays | L1: SourceSystem | M1: VAT | N1: NetSpend | O1: Contracted | P1: DataQualityFlag
A2: 45798 | B2: S006 | C2: Birmingham Care & Education Centre | D2: Midlands | E2: freshserve | F2: Food & Catering | G2: INV-2025-00001 | H2: 32 | I2: 85.42 | J2: 2733.44 | K2: 30 | L2: ERP | M2: 546.688 | N2: 2733.44 | O2: Y | P2: OK
A3: 45937 | B3: S008 | C3: Leicester Care & Education Centre | D3: Midlands | E3: KitchenPro | F3: Food & Catering | G3: INV-2025-00002 | H3: 12 | I3: 60.24 | J3: 722.88 | K3: 60 | L3: Procurement Portal | M3: 144.576 | N3: 722.88 | O3: N | P3: OK
A4: 45769 | B4: S009 | C4: Derby Care & Education Centre | D4: Midlands | E4: MediSure | F4: Medical Supplies | G4: INV-2025-00003 | H4: 30 | I4: 171.35 | J4: 5140.56 | K4: 60 | L4: Legacy Spend File | M4: 1028.112 | N4: 5140.56 | O4: Y | P4: OK
A5: 45990 | B5: S006 | C5: Birmingham Care & Education Centre | D5: Midlands | E5: PowerDirect | F5: Utilities | G5: INV-2025-00004 | H5: 70 | I5: 577.74 | J5: 40441.94 | K5: 45 | L5: ERP | M5: 8088.388 | N5: 40441.94 | O5: N | P5: OK
A6: 45739 | B6: S016 | C6: Cardiff Care & Education Centre | D6: Wales | E6: CloudLink | F6: IT & Telecoms | G6: INV-2025-00005 | H6: 55 | I6: 193.42 | J6: 10637.88 | K6: 45 | L6: Procurement Portal | M6: 2127.576 | N6: 10637.88 | O6: Y | P6: OK
A7: 45710 | B7: S013 | C7: Reading Care & Education Centre | D7: South | E7: WaterGrid | F7: Utilities | G7: INV-2025-00006 | H7: 12 | I7: 219.79 | J7: 2637.51 | K7: 45 | L7: ERP | M7: 527.502 | N7: 2637.51 | O7: N | P7: OK
A8: 45793 | B8: S005 | C8: Sheffield Care & Education Centre | D8: North | E8: AutoCare | F8: Vehicle & Fuel | G8: INV-2025-00007 | H8: 6 | I8: 226.43 | J8: 1358.59 | K8: 60 | L8: Procurement Portal | M8: 271.718 | N8: 1358.59 | O8: N | P8: OK
A9: 45698 | B9: S004 | C9: Newcastle Care & Education Centre | D9: North | E9: NourishCo | F9: Food & Catering | G9: INV-2025-00008 | H9: 71 | I9: 99.13 | J9: 7038.54 | K9: 45 | L9: Legacy Spend File | M9: 1407.708 | N9: 7038.54 | O9: N | P9: OK
A10: 45756 | B10: S017 | C10: Swansea Care & Education Centre | D10: Wales | E10: AutoCare | F10: Vehicle & Fuel | G10: INV-2025-00009 | H10: 9 | I10: 73.38 | J10: 660.43 | K10: 30 | L10: Legacy Spend File | M10: 132.086 | N10: 660.43 | O10: N | P10: OK
A11: 45777 | B11: S015 | C11: Brighton Care & Education Centre | D11: South | E11: CloudLink | F11: IT & Telecoms | G11: INV-2025-00010 | H11: 13 | I11: 296.5 | J11: 3854.46 | K11: 45 | L11: Procurement Portal | M11: 770.892 | N11: 3854.46 | O11: Y | P11: OK
A12: 45847 | B12: S016 | C12: Cardiff Care & Education Centre | D12: Wales | E12: FleetFuel | F12: Vehicle & Fuel | G12: INV-2025-00011 | H12: 46 | I12: 73.63 | J12: 3386.79 | K12: 30 | L12: Legacy Spend File | M12: 677.358 | N12: 3386.79 | O12: Y | P12: OK
A13: 45983 | B13: S019 | C13: Wrexham Care & Education Centre | D13: Wales | E13: KitchenPro | F13: Food & Catering | G13: INV-2025-00012 | H13: 22 | I13: 50.31 | J13: 1106.86 | K13: 60 | L13: Legacy Spend File | M13: 221.372 | N13: 1106.86 | O13: N | P13: OK
... A78: 45884 | B78: S014 | C78: Southampton Care & Education Centre | D78: South | E78: RoadReady | F78: Vehicle & Fuel | G78: INV-2025-00077 | H78: 57 | I78: 99.66 | J78: 5680.55 | K78: 60 | L78: ERP | M78: 1136.11 | N78: 5680.55 | O78: N | P78: OK
A79: 45744 | B79: S005 | C79: Sheffield Care & Education Centre | D79: North | F79: Office & Training | G79: INV-2025-00078 | H79: 11 | I79: 63.63 | J79: 699.89 | K79: 45 | L79: Legacy Spend File | M79: 139.978 | N79: 699.89 | O79: N | P79: Missing supplier
A80: 45778 | B80: S020 | C80: Bangor Care & Education Centre | D80: Wales | E80: FleetFuel | F80: Vehicle & Fuel | G80: INV-2025-00079 | H80: 40 | I80: 99.92 | J80: 3996.7 | K80: 30 | L80: ERP | M80: 799.34 | N80: 3996.7 | O80: Y | P80: OK
A81: 45783 | B81: S017 | C81: Swansea Care & Education Centre | D81: Wales | E81: MediSure | F81: Medical Supplies | G81: INV-2025-00080 | H81: 61 | I81: 40.22 | J81: 2453.33 | K81: 60 | L81: ERP | M81: 490.666 | N81: 2453.33 | O81: Y | P81: OK
A82: 45952 | B82: S008 | C82: Leicester Care & Education Centre | D82: Midlands | E82: NurseLink | F82: Agency Labour | G82: INV-2025-00081 | H82: 25 | I82: 265.86 | J82: 6646.45 | K82: 60 | L82: Legacy Spend File | M82: 1329.29 | N82: 6646.45 | O82: N | P82: OK
A83: 45782 | B83: S019 | C83: Wrexham Care & Education Centre | D83: Wales | E83: LearnWell | F83: Office & Training | G83: INV-2025-00082 | H83: 19 | I83: 91.28 | J83: 1734.27 | K83: 60 | L83: Legacy Spend File | M83: 346.854 | N83: 1734.27 | O83: N | P83: OK
A84: 45770 | B84: S008 | C84: Leicester Care & Education Centre | D84: Midlands | E84: NourishCo | F84: Food & Catering | G84: INV-2025-00083 | H84: 23 | I84: 146.53 | J84: 3370.19 | K84: 60 | L84: Legacy Spend File | M84: 674.038 | N84: 3370.19 | O84: N | P84: OK
A85: 45785 | B85: S014 | C85: Southampton Care & Education Centre | D85: South | E85: ClinEquip | F85: Medical Supplies | G85: INV-2025-00084 | H85: 16 | I85: 90.24 | J85: 1443.8 | K85: 45 | L85: ERP | M85: 288.76 | N85: 1443.8 | O85: N | P85: OK
A86: 45971 | B86: S012 | C86: Bristol Care & Education Centre | D86: South | E86: RoadReady | F86: Vehicle & Fuel | G86: INV-2025-00085 | H86: 65 | I86: 60.9 | J86: 3958.39 | K86: 45 | L86: Legacy Spend File | M86: 791.678 | N86: 3958.39 | O86: N | P86: OK
A87: 45901 | B87: S008 | C87: Leicester Care & Education Centre | D87: Midlands | E87: BuildCare | F87: Facilities | G87: INV-2025-00086 | H87: 58 | I87: 136.59 | J87: 7922.27 | K87: 45 | L87: ERP | M87: 1584.454 | N87: 7922.27 | O87: N | P87: OK
A88: 45906 | B88: S007 | C88: Nottingham Care & Education Centre | D88: Midlands | E88: NetServe | F88: IT & Telecoms | G88: INV-2025-00087 | H88: 31 | I88: 363.98 | J88: 11283.38 | K88: 45 | L88: Procurement Portal | M88: 2256.676 | N88: 11283.38 | O88: N | P88: OK
A89: 45797 | B89: S005 | C89: Sheffield Care & Education Centre | D89: North | E89: CloudLink | F89: IT & Telecoms | G89: INV-2025-00088 | H89: 43 | I89: 263.6 | J89: 11334.89 | K89: 45 | L89: Legacy Spend File | M89: 2266.978 | N89: 11334.89 | O89: Y | P89: OK
A90: 45776 | B90: S007 | C90: Nottingham Care & Education Centre | D90: Midlands | E90: CleanWorks | F90: Facilities | G90: INV-2025-00089 | H90: 50 | I90: 134.5 | J90: 6725.17 | K90: 60 | L90: ERP | M90: 1345.034 | N90: 6725.17 | O90: Y | P90: OK
A91: 45870 | B91: S011 | C91: London Care & Education Centre | D91: South | E91: UK Energy Partners | F91: Utilities | G91: INV-2025-00090 | H91: 53 | I91: 331.54 | J91: 17571.79 | K91: 45 | L91: Legacy Spend File | M91: 3514.358 | N91: 17571.79 | O91: N | P91: OK
... A902: 45879 | B902: S009 | C902: Derby Care & Education Centre | D902: Midlands | E902: FreshServe | F902: Food & Catering | G902: INV-2025-00901 | H902: 38 | I902: 79.61 | J902: 3025.23 | K902: 45 | L902: ERP | M902: 605.046 | N902: 3025.23 | O902: Y | P902: OK
A903: 45901 | C903: Preston Care & Education Centre | D903: North | E903: FleetFuel | F903: Vehicle & Fuel | G903: INV-2025-00902 | H903: 74 | I903: 76.52 | J903: 5662.41 | K903: 60 | L903: ERP | M903: 1132.482 | N903: 5662.41 | O903: Y | P903: Missing site
A904: 45701 | B904: S005 | C904: Sheffield Care & Education Centre | D904: North | E904: CareTemps | F904: Agency Labour | G904: INV-2025-00903 | H904: 52 | I904: 304.78 | J904: 15848.59 | K904: 60 | L904: Procurement Portal | M904: 3169.718 | N904: 15848.59 | O904: N | P904: OK
A905: 45904 | B905: S016 | C905: Cardiff Care & Education Centre | D905: Wales | E905: CleanWorks | F905: Facilities | G905: INV-2025-00904 | H905: 72 | I905: 363.62 | J905: 26180.54 | K905: 30 | L905: Procurement Portal | M905: 5236.108 | N905: 26180.54 | O905: Y | P905: OK
A906: 45973 | B906: S009 | C906: Derby Care & Education Centre | D906: Midlands | E906: PowerDirect | F906: Utilities | G906: INV-2025-00905 | H906: 68 | I906: 277.71 | J906: 18884.05 | K906: 30 | L906: ERP | M906: 3776.81 | N906: 18884.05 | O906: N | P906: OK
A907: 45823 | B907: S011 | C907: London Care & Education Centre | D907: South | E907: TeleCare IT | F907: IT & Telecoms | G907: INV-2025-00906 | H907: 74 | I907: 225.69 | J907: 16701.15 | K907: 30 | L907: ERP | M907: 3340.23 | N907: 16701.15 | O907: N | P907: OK
A908: 45845 | B908: S010 | C908: Coventry Care & Education Centre | D908: Midlands | E908: CareTemps | F908: Agency Labour | G908: INV-2025-00907 | H908: 45 | I908: 142 | J908: 6390.22 | K908: 30 | L908: Procurement Portal | M908: 1278.044 | N908: 6390.22 | O908: N | P908: OK
A909: 45744 | B909: S008 | C909: Leicester Care & Education Centre | D909: Midlands | E909: CareMed | F909: Medical Supplies | G909: INV-2025-00908 | H909: 45 | I909: 180.9 | J909: 8140.39 | K909: 60 | L909: Procurement Portal | M909: 1628.078 | N909: 8140.39 | O909: N | P909: OK
A910: 45680 | B910: S016 | C910: Cardiff Care & Education Centre | D910: Wales | E910: SafeGuard FM | F910: Facilities | G910: INV-2025-00909 | H910: 30 | I910: 256.72 | J910: 7701.5 | K910: 30 | L910: Legacy Spend File | M910: 1540.3 | N910: 7701.5 | O910: N | P910: OK
A911: 45701 | B911: S001 | C911: Preston Care & Education Centre | D911: North | E911: BuildCare | F911: Facilities | G911: INV-2025-00910 | H911: 15 | I911: 591.55 | J911: 8873.26 | K911: 60 | L911: ERP | M911: 1774.652 | N911: 8873.26 | O911: N | P911: OK
A912: 45665 | B912: S015 | C912: Brighton Care & Education Centre | D912: South | E912: SafeGuard FM | F912: Facilities | G912: INV-2025-00911 | H912: 44 | I912: 151.97 | J912: 6686.65 | K912: 60 | L912: ERP | M912: 1337.33 | N912: 6686.65 | O912: N | P912: OK
A913: 45669 | B913: S019 | C913: Wrexham Care & Education Centre | D913: Wales | E913: LearnWell | F913: Office & Training | G913: INV-2025-00912 | H913: 43 | I913: 84.61 | J913: 3638.11 | K913: 30 | L913: Legacy Spend File | M913: 727.622 | N913: 3638.11 | O913: N | P913: OK
A914: 45937 | B914: S015 | C914: Brighton Care & Education Centre | D914: South | E914: UK Energy Partners | F914: Utilities | G914: INV-2025-00913 | H914: 67 | I914: 286.75 | J914: 19212.46 | K914: 45 | L914: Legacy Spend File | M914: 3842.492 | N914: 19212.46 | O914: N | P914: OK
A915: 46015 | B915: S013 | C915: Reading Care & Education Centre | D915: South | E915: BuildCare | F915: Facilities | G915: INV-2025-00914 | H915: 3 | I915: 428.61 | J915: 1285.84 | K915: 45 | L915: Legacy Spend File | M915: 257.168 | N915: 1285.84 | O915: N | P915: OK
... A1101: 45849 | B1101: S001 | C1101: Preston Care & Education Centre | D1101: North | E1101: SafeGuard FM | F1101: Facilities | G1101: INV-2025-01100 | H1101: 18 | I1101: 217.79 | J1101: 3920.2 | K1101: 45 | L1101: Legacy Spend File | M1101: 784.04 | N1101: 3920.2 | O1101: N | P1101: OK
A1102: 45761 | B1102: S020 | C1102: Bangor Care & Education Centre | D1102: Wales | E1102: RoadReady | F1102: Vehicle & Fuel | G1102: INV-2025-01101 | H1102: 43 | I1102: 164.48 | K1102: 30 | L1102: ERP | M1102: 0 | N1102: 0 | O1102: N | P1102: Missing spend
A1103: 45727 | B1103: S006 | C1103: Birmingham Care & Education Centre | D1103: Midlands | E1103: CareMed | F1103: Medical Supplies | G1103: INV-2025-01102 | H1103: 15 | I1103: 24.4 | J1103: 365.99 | K1103: 45 | L1103: Procurement Portal | M1103: 73.198 | N1103: 365.99 | O1103: N | P1103: OK
A1104: 45770 | B1104: S016 | C1104: Cardiff Care & Education Centre | D1104: Wales | E1104: SafeGuard FM | F1104: Facilities | G1104: INV-2025-01103 | H1104: 38 | I1104: 567.68 | J1104: 21571.95 | K1104: 60 | L1104: ERP | M1104: 4314.39 | N1104: 21571.95 | O1104: N | P1104: OK
A1105: 45941 | B1105: S012 | C1105: Bristol Care & Education Centre | D1105: South | E1105: BuildCare | F1105: Facilities | G1105: INV-2025-01104 | H1105: 30 | I1105: 166.7 | J1105: 5000.93 | K1105: 30 | L1105: Procurement Portal | M1105: 1000.186 | N1105: 5000.93 | O1105: N | P1105: OK
A1106: 45960 | B1106: S015 | C1106: Brighton Care & Education Centre | D1106: South | E1106: OfficePlus | F1106: Office & Training | G1106: INV-2025-01105 | H1106: 61 | I1106: 137.96 | J1106: 8415.77 | K1106: 45 | L1106: Procurement Portal | M1106: 1683.154 | N1106: 8415.77 | O1106: N | P1106: OK
A1107: 45784 | B1107: S004 | C1107: Newcastle Care & Education Centre | D1107: North | E1107: NurseLink | F1107: Agency Labour | G1107: INV-2025-01106 | H1107: 32 | I1107: 169.33 | J1107: 5418.48 | K1107: 45 | L1107: Procurement Portal | M1107: 1083.696 | N1107: 5418.48 | O1107: N | P1107: OK
A1108: 45734 | B1108: S003 | C1108: Leeds Care & Education Centre | D1108: North | E1108: PowerDirect | F1108: Utilities | G1108: INV-2025-01107 | H1108: 74 | I1108: 350.19 | J1108: 25914.34 | K1108: 30 | L1108: Procurement Portal | M1108: 5182.868 | N1108: 25914.34 | O1108: N | P1108: OK
A1109: 45916 | B1109: S009 | C1109: Derby Care & Education Centre | D1109: Midlands | E1109: CareMed | F1109: Medical Supplies | G1109: INV-2025-01108 | H1109: 5 | I1109: 67.23 | J1109: 336.15 | K1109: 45 | L1109: Legacy Spend File | M1109: 67.23 | N1109: 336.15 | O1109: N | P1109: OK
A1110: 45708 | B1110: S001 | C1110: Preston Care & Education Centre | D1110: North | E1110: PrintCo | F1110: Office & Training | G1110: INV-2025-01109 | H1110: 58 | I1110: 53.22 | J1110: 3086.7 | K1110: 45 | L1110: ERP | M1110: 617.34 | N1110: 3086.7 | O1110: N | P1110: OK
A1111: 45866 | B1111: S007 | C1111: Nottingham Care & Education Centre | D1111: Midlands | E1111: ClinEquip | F1111: Medical Supplies | G1111: INV-2025-01110 | H1111: 28 | I1111: 343.85 | J1111: 9627.83 | K1111: 30 | L1111: Procurement Portal | M1111: 1925.566 | N1111: 9627.83 | O1111: N | P1111: OK
A1112: 45704 | B1112: S002 | C1112: Manchester Care & Education Centre | D1112: North | E1112: PowerDirect | F1112: Utilities | G1112: INV-2025-01111 | H1112: 3 | I1112: 225.11 | J1112: 675.33 | K1112: 45 | L1112: Legacy Spend File | M1112: 135.066 | N1112: 675.33 | O1112: N | P1112: OK
A1113: 45893 | B1113: S003 | C1113: Leeds Care & Education Centre | D1113: North | E1113: BuildCare | F1113: Facilities | G1113: INV-2025-01112 | H1113: 74 | I1113: 202.87 | J1113: 15012.07 | K1113: 60 | L1113: Legacy Spend File | M1113: 3002.414 | N1113: 15012.07 | O1113: N | P1113: OK
A1114: 45728 | B1114: S003 | C1114: Leeds Care & Education Centre | D1114: North | E1114: LearnWell | F1114: Office & Training | G1114: INV-2025-01113 | H1114: 52 | I1114: 121.03 | J1114: 6293.48 | K1114: 30 | L1114: Procurement Portal | M1114: 1258.696 | N1114: 6293.48 | O1114: N | P1114: OK
... A1801: 45981 | B1801: S020 | C1801: Bangor Care & Education Centre | D1801: Wales | E1801: PrintCo | F1801: Office & Training | G1801: INV-2025-01800 | H1801: 46 | I1801: 75.88 | J1801: 3490.68 | K1801: 30 | L1801: ERP | M1801: 698.136 | N1801: 3490.68 | O1801: N | P1801: OK

Sheet Fleet_Raw
A1: Month | B1: SiteID | C1: SiteName | D1: Region | E1: VehicleID | F1: VehicleType | G1: Miles | H1: FuelLitres | I1: FuelCost | J1: MaintenanceCost | K1: LeaseCost | L1: TotalFleetCost
A2: 45658 | B2: S001 | C2: Preston Care & Education Centre | D2: North | E2: VH0077 | F2: Van | G2: 1525 | H2: 179.4 | I2: 265.51 | J2: 145.15 | K2: 450 | L2: 860.66
A3: 45658 | B3: S001 | C3: Preston Care & Education Centre | D3: North | E3: VH0050 | F3: Car | G3: 872 | H3: 83 | I3: 122.84 | J3: 28.9 | K3: 450 | L3: 601.74
A4: 45658 | B4: S001 | C4: Preston Care & Education Centre | D4: North | E4: VH0138 | F4: Car | G4: 599 | H4: 57 | I4: 84.36 | J4: 23.27 | K4: 380 | L4: 487.63
A5: 45658 | B5: S001 | C5: Preston Care & Education Centre | D5: North | E5: VH0063 | F5: Car | G5: 1116 | H5: 106.3 | I5: 157.32 | J5: 190.7 | K5: 320 | L5: 668.02
A6: 45658 | B6: S002 | C6: Manchester Care & Education Centre | D6: North | E6: VH0118 | F6: MPV | G6: 654 | H6: 62.3 | I6: 92.2 | J6: 221.6 | K6: 450 | L6: 763.8
A7: 45658 | B7: S002 | C7: Manchester Care & Education Centre | D7: North | E7: VH0032 | F7: Minibus | G7: 929 | H7: 109.3 | I7: 161.76 | J7: 261.74 | K7: 380 | L7: 803.5
A8: 45658 | B8: S002 | C8: Manchester Care & Education Centre | D8: North | E8: VH0028 | F8: Car | G8: 1453 | H8: 138.4 | I8: 204.83 | J8: 221.75 | K8: 320 | L8: 746.58
A9: 45658 | B9: S003 | C9: Leeds Care & Education Centre | D9: North | E9: VH0093 | F9: Van | G9: 982 | H9: 115.5 | I9: 170.94 | J9: 78.7 | K9: 320 | L9: 569.64
A10: 45658 | B10: S003 | C10: Leeds Care & Education Centre | D10: North | E10: VH0054 | F10: Van | G10: 512 | H10: 60.2 | I10: 89.1 | J10: 92.47 | K10: 320 | L10: 501.57
A11: 45658 | B11: S003 | C11: Leeds Care & Education Centre | D11: North | E11: VH0101 | F11: MPV | G11: 997 | H11: 95 | I11: 140.6 | J11: 71.03 | K11: 520 | L11: 731.63
A12: 45658 | B12: S003 | C12: Leeds Care & Education Centre | D12: North | E12: VH0026 | F12: Van | G12: 1017 | H12: 119.6 | I12: 177.01 | J12: 156.15 | K12: 450 | L12: 783.16
A13: 45658 | B13: S003 | C13: Leeds Care & Education Centre | D13: North | E13: VH0126 | F13: Van | G13: 993 | H13: 116.8 | I13: 172.86 | J13: 98 | K13: 380 | L13: 650.86
... A1160: 45992 | B1160: S020 | C1160: Bangor Care & Education Centre | D1160: Wales | E1160: VH0056 | F1160: Minibus | G1160: 989 | H1160: 116.4 | I1160: 172.27 | J1160: 98.8 | K1160: 520 | L1160: 791.07

Sheet Workforce_Raw
A1: Month | B1: SiteID | C1: SiteName | D1: Region | E1: Role | F1: FTE | G1: AnnualSalary | H1: OvertimeHours | I1: OvertimeCost | J1: AbsenceDays | K1: BasePayroll | L1: TotalPayroll
A2: 45658 | B2: S001 | C2: Preston Care & Education Centre | D2: North | E2: Support Worker | F2: 16.7 | G2: 25000 | H2: 55.4 | I2: 887.82 | J2: 7.3 | K2: 34791.667 | L2: 35679.487
A3: 45658 | B3: S001 | C3: Preston Care & Education Centre | D3: North | E3: Manager | F3: 17.7 | G3: 43000 | H3: 54.7 | I3: 1507.76 | J3: 8.7 | K3: 63425 | L3: 64932.76
A4: 45658 | B4: S001 | C4: Preston Care & Education Centre | D4: North | E4: Senior Support Worker | F4: 9.3 | G4: 29000 | H4: 50.6 | I4: 940.64 | J4: 4.9 | K4: 22475 | L4: 23415.64
A5: 45658 | B5: S001 | C5: Preston Care & Education Centre | D5: North | E5: Registered Nurse | F5: 19.5 | G5: 41000 | H5: 87 | I5: 2286.54 | J5: 8.7 | K5: 66625 | L5: 68911.54
A6: 45658 | B6: S001 | C6: Preston Care & Education Centre | D6: North | E6: Administrator | F6: 4.1 | G6: 27000 | H6: 11 | I6: 190.38 | J6: 3.8 | K6: 9225 | L6: 9415.38
A7: 45658 | B7: S001 | C7: Preston Care & Education Centre | D7: North | E7: Team Leader | F7: 10.6 | G7: 35000 | H7: 30.7 | I7: 688.78 | J7: 7 | K7: 30916.667 | L7: 31605.447
A8: 45658 | B8: S002 | C8: Manchester Care & Education Centre | D8: North | E8: Senior Support Worker | F8: 13.8 | G8: 29000 | H8: 50.2 | I8: 933.21 | J8: 6.9 | K8: 33350 | L8: 34283.21
A9: 45658 | B9: S002 | C9: Manchester Care & Education Centre | D9: North | E9: Driver | F9: 18.3 | G9: 28000 | H9: 102.6 | I9: 1841.54 | J9: 10.4 | K9: 42700 | L9: 44541.54
A10: 45658 | B10: S002 | C10: Manchester Care & Education Centre | D10: North | E10: Registered Nurse | F10: 11.1 | G10: 41000 | H10: 42.6 | I10: 1119.62 | J10: 5.2 | K10: 37925 | L10: 39044.62
A11: 45658 | B11: S002 | C11: Manchester Care & Education Centre | D11: North | E11: Administrator | F11: 7.8 | G11: 27000 | H11: 30.5 | I11: 527.88 | J11: 4.2 | K11: 17550 | L11: 18077.88
A12: 45658 | B12: S002 | C12: Manchester Care & Education Centre | D12: North | E12: Team Leader | F12: 8.8 | G12: 35000 | H12: 47 | I12: 1054.49 | J12: 4.4 | K12: 25666.667 | L12: 26721.157
A13: 45658 | B13: S003 | C13: Leeds Care & Education Centre | D13: North | E13: Administrator | F13: 12.7 | G13: 27000 | H13: 62.6 | I13: 1083.46 | J13: 8 | K13: 28575 | L13: 29658.46
... A1194: 45992 | B1194: S020 | C1194: Bangor Care & Education Centre | D1194: Wales | E1194: Administrator | F1194: 13.3 | G1194: 27000 | H1194: 61.9 | I1194: 1071.35 | J1194: 5.3 | K1194: 29925 | L1194: 30996.35

Sheet Agency_Raw
A1: Month | B1: SiteID | C1: SiteName | D1: Region | E1: Agency | F1: Role | G1: Hours | H1: HourlyRate | I1: AgencySpend
A2: 45658 | B2: S001 | C2: Preston Care & Education Centre | D2: North | E2: CareTemps | F2: Registered Nurse | G2: 127 | H2: 42 | I2: 5334
A3: 45658 | B3: S001 | C3: Preston Care & Education Centre | D3: North | E3: HealthStaffing | F3: Support Worker | G3: 80 | H3: 23 | I3: 1840
A4: 45658 | B4: S001 | C4: Preston Care & Education Centre | D4: North | E4: NurseLink | F4: Senior Support Worker | G4: 134 | H4: 28 | I4: 3752
A5: 45658 | B5: S002 | C5: Manchester Care & Education Centre | D5: North | E5: NurseLink | F5: Support Worker | G5: 107 | H5: 23 | I5: 2461
A6: 45658 | B6: S002 | C6: Manchester Care & Education Centre | D6: North | E6: HealthStaffing | F6: Registered Nurse | G6: 47 | H6: 42 | I6: 1974
A7: 45658 | B7: S002 | C7: Manchester Care & Education Centre | D7: North | E7: HealthStaffing | F7: Senior Support Worker | G7: 139 | H7: 28 | I7: 3892
A8: 45658 | B8: S003 | C8: Leeds Care & Education Centre | D8: North | E8: CareTemps | F8: Registered Nurse | G8: 144 | H8: 42 | I8: 6048
A9: 45658 | B9: S003 | C9: Leeds Care & Education Centre | D9: North | E9: HealthStaffing | F9: Support Worker | G9: 120 | H9: 23 | I9: 2760
A10: 45658 | B10: S003 | C10: Leeds Care & Education Centre | D10: North | E10: CareTemps | F10: Senior Support Worker | G10: 63 | H10: 28 | I10: 1764
A11: 45658 | B11: S004 | C11: Newcastle Care & Education Centre | D11: North | E11: CareTemps | F11: Registered Nurse | G11: 79 | H11: 42 | I11: 3318
A12: 45658 | B12: S004 | C12: Newcastle Care & Education Centre | D12: North | E12: HealthStaffing | F12: Senior Support Worker | G12: 95 | H12: 28 | I12: 2660
A13: 45658 | B13: S005 | C13: Sheffield Care & Education Centre | D13: North | E13: CareTemps | F13: Senior Support Worker | G13: 65 | H13: 28 | I13: 1820
... A493: 45992 | B493: S020 | C493: Bangor Care & Education Centre | D493: Wales | E493: CareTemps | F493: Senior Support Worker | G493: 79 | H493: 28 | I493: 2212

Sheet Finance_Raw
A1: Month | B1: SiteID | C1: SiteName | D1: Region | E1: Revenue | F1: Payroll | G1: Procurement | H1: Fleet | I1: Agency | J1: OtherOpex | K1: BudgetOpex | L1: ActualOpex | M1: EBITDA | N1: EBITDA_Margin
A2: 45658 | B2: S001 | C2: Preston Care & Education Centre | D2: North | E2: 474619.09 | F2: 233960.25 | G2: 29957.93 | H2: 2618.05 | I2: 10926 | J2: 35029.32 | K2: 300615.21 | L2: 312491.55 | M2: 162127.54 | N2: 0.34159506
A3: 45658 | B3: S002 | C3: Manchester Care & Education Centre | D3: North | E3: 322229.82 | F3: 162668.41 | G3: 46147.12 | H3: 2313.88 | I3: 8327 | J3: 18848.64 | K3: 237293.33 | L3: 238305.05 | M3: 83924.773 | N3: 0.26045005
A4: 45658 | B4: S003 | C4: Leeds Care & Education Centre | D4: North | E4: 443270.86 | F4: 209015.65 | G4: 56737.51 | H4: 4026.14 | I4: 10572 | J4: 30594.89 | K4: 321242.97 | L4: 310946.19 | M4: 132324.67 | N4: 0.29851877
A5: 45658 | B5: S004 | C5: Newcastle Care & Education Centre | D5: North | E5: 225588.97 | F5: 126464.86 | G5: 19671.36 | H5: 2389.81 | I5: 5978 | J5: 17476.53 | K5: 168715.6 | L5: 171980.56 | M5: 53608.407 | N5: 0.23763753
A6: 45658 | B6: S005 | C6: Sheffield Care & Education Centre | D6: North | E6: 480577.57 | F6: 198889.36 | G6: 114638.36 | H6: 2136.15 | I6: 1820 | J6: 37508.21 | K6: 356469.83 | L6: 354992.08 | M6: 125585.49 | N6: 0.26132199
A7: 45658 | B7: S006 | C7: Birmingham Care & Education Centre | D7: Midlands | E7: 253082.63 | F7: 105935.07 | G7: 39216.38 | H7: 2082.71 | I7: 4172 | J7: 18193.51 | K7: 172312.36 | L7: 169599.67 | M7: 83482.963 | N7: 0.32986445
A8: 45658 | B8: S007 | C8: Nottingham Care & Education Centre | D8: Midlands | E8: 459390.76 | F8: 194379.62 | G8: 80306.32 | H8: 2365.07 | I8: 2890 | J8: 34864.61 | K8: 316673.53 | L8: 314805.62 | M8: 144585.14 | N8: 0.31473236
A9: 45658 | B9: S008 | C9: Leicester Care & Education Centre | D9: Midlands | E9: 408256.15 | F9: 187881.8 | G9: 70155.57 | H9: 3437.69 | I9: 4479 | J9: 30631.99 | K9: 301514.81 | L9: 296586.05 | M9: 111670.1 | N9: 0.2735295
A10: 45658 | B10: S009 | C10: Derby Care & Education Centre | D10: Midlands | E10: 257222.08 | F10: 107740.26 | G10: 46215.75 | H10: 5176.84 | I10: 8384 | J10: 15475.41 | K10: 179413.25 | L10: 182992.26 | M10: 74229.823 | N10: 0.28858263
A11: 45658 | B11: S010 | C11: Coventry Care & Education Centre | D11: Midlands | E11: 336788.75 | F11: 171773.51 | G11: 23581.27 | H11: 4097.03 | I11: 9165 | J11: 18906.29 | K11: 229154.82 | L11: 227523.1 | M11: 109265.65 | N11: 0.32443378
A12: 45658 | B12: S011 | C12: London Care & Education Centre | D12: South | E12: 275996.19 | F12: 107439.8 | G12: 49352.19 | H12: 5448.97 | I12: 7647 | J12: 20130.61 | K12: 189971.53 | L12: 190018.57 | M12: 85977.62 | N12: 0.31151742
A13: 45658 | B13: S012 | C13: Bristol Care & Education Centre | D13: South | E13: 323384.21 | F13: 148083.27 | G13: 34609.06 | H13: 2439.87 | I13: 5498 | J13: 25385.59 | K13: 216520.19 | L13: 216015.79 | M13: 107368.42 | N13: 0.33201505
... A241: 45992 | B241: S020 | C241: Bangor Care & Education Centre | D241: Wales | E241: 308061.88 | F241: 102978.73 | G241: 86456.91 | H241: 3087.47 | I241: 5026 | J241: 20533.07 | K241: 217368.84 | L241: 218082.18 | M241: 89979.703 | N241: 0.29208321

Sheet Sites
A1: SiteID | B1: SiteName | C1: Region | D1: Town
A2: S001 | B2: Preston Care & Education Centre | C2: North | D2: Preston
A3: S002 | B3: Manchester Care & Education Centre | C3: North | D3: Manchester
A4: S003 | B4: Leeds Care & Education Centre | C4: North | D4: Leeds
A5: S004 | B5: Newcastle Care & Education Centre | C5: North | D5: Newcastle
A6: S005 | B6: Sheffield Care & Education Centre | C6: North | D6: Sheffield
A7: S006 | B7: Birmingham Care & Education Centre | C7: Midlands | D7: Birmingham
A8: S007 | B8: Nottingham Care & Education Centre | C8: Midlands | D8: Nottingham
A9: S008 | B9: Leicester Care & Education Centre | C9: Midlands | D9: Leicester
A10: S009 | B10: Derby Care & Education Centre | C10: Midlands | D10: Derby
A11: S010 | B11: Coventry Care & Education Centre | C11: Midlands | D11: Coventry
A12: S011 | B12: London Care & Education Centre | C12: South | D12: London
... A21: S020 | B21: Bangor Care & Education Centre | C21: Wales | D21: Bangor

Sheet Category_Targets
A1: Category | B1: TargetSavingsPct | C1: Owner
A2: Medical Supplies | B2: 0.06 | C2: Procurement
A3: Food & Catering | B3: 0.04 | C3: Procurement
A4: Facilities | B4: 0.05 | C4: Facilities
A5: Utilities | B5: 0.03 | C5: Procurement
A6: IT & Telecoms | B6: 0.08 | C6: IT
A7: Vehicle & Fuel | B7: 0.05 | C7: Fleet
A8: Agency Labour | B8: 0.07 | C8: Workforce
A9: Office & Training | B9: 0.04 | C9: Commercial

Sheet Supplier_Lookup
A1: Supplier | B1: Category | C1: Contracted | E1: Reference-data fix (v2)
A2: AutoCare | B2: Vehicle & Fuel | C2: N | E2: Original lookup held 37 rows: 13 lower-case duplicates of existing suppliers and one conflicting mapping (CloudLink -> "medical supplies"). Rebuilt as a 24-row master, one row per supplier. MATCH is case-insensitive, so casing variants in invoices still resolve.
A3: BuildCare | B3: Facilities | C3: N
A4: CareMed | B4: Medical Supplies | C4: N
A5: CareTemps | B5: Agency Labour | C5: N
A6: CleanWorks | B6: Facilities | C6: Y
A7: ClinEquip | B7: Medical Supplies | C7: N
A8: CloudLink | B8: IT & Telecoms | C8: Y
A9: FleetFuel | B9: Vehicle & Fuel | C9: Y
A10: FreshServe | B10: Food & Catering | C10: Y
A11: HealthStaffing | B11: Agency Labour | C11: N
A12: KitchenPro | B12: Food & Catering | C12: N
A13: LearnWell | B13: Office & Training | C13: N
A14: MediSure | B14: Medical Supplies | C14: Y
... A25: WaterGrid | B25: Utilities | C25: N

Sheet Dash_Calc
A1: Dashboard calculation engine
A2: Reads the four selectors on the Dashboard and returns filtered measures. Nothing here needs editing.
G3: Measure | H3: Value
A4: Regions | B4: Categories | C4: Months | D4: Month date | E4: Scenarios | G4: Region selected | H4: =selRegion -> All | J4: Month | K4: Date | L4: Revenue | M4: Opex | N4: EBITDA | O4: Agency | P4: Overtime | R4: Category | S4: Other | T4: Selected | U4: Total | W4: Supplier | X4: Filtered spend | Y4: Rank key | AA4: Rank | AB4: Top supplier | AC4: Spend | AE4: Region | AF4: Budget Opex | AG4: Actual Opex | AI4: Scenario | AJ4: EBITDA | AK4: Selected | AL4: Other | AN4: Bridge step | AO4: Base | AP4: Increase | AQ4: Decrease | AR4: Total | AS4: Category | AT4: Target | AU4: FY forecast
A5: All | B5: All | C5: All | E5: Conservative | G5: Region criterion | H5: =IF($H$4="All","*",$H$4) -> * | J5: Jan | K5: 45658 | L5: =SUMIFS(Finance_Raw!$E:$E,Finance_Raw!$D:$D,critRegion,Finance_Raw!$A:$A,$K5) -> 6859245.2 | M5: =SUMIFS(Finance_Raw!$L:$L,Finance_Raw!$D:$D,critRegion,Finance_Raw!$A:$A,$K5) -> 4833404.3 | N5: =L5-M5 -> 2025840.9 | O5: =SUMIFS(Agency_Raw!$I:$I,Agency_Raw!$D:$D,critRegion,Agency_Raw!$A:$A,$K5) -> 107437 | P5: =SUMIFS(Workforce_Raw!$I:$I,Workforce_Raw!$D:$D,critRegion,Workforce_Raw!$A:$A,$K5) -> 86782.57 | R5: Medical Supplies | S5: =IF(R5=$H$6,0,U5) -> 1097153 | T5: =IF(R5=$H$6,U5,0) -> 0 | U5: =SUMIFS(Cleaned_Procurement!$O$2:$O$1801,Cleaned_Procurement!$F$2:$F$1801,R5,Cleaned_Procurement!$D$2:$D$1801,critRegion,Cleaned_Procurement!$A$2:$A$1801,">="&dStart,Cleaned_Procurement!$A$2:$A$1801,"<="&dEnd) -> 1097153 | W5: =Supplier_Lookup!A2 -> AutoCare | X5: =SUMIFS(Cleaned_Procurement!$O$2:$O$1801,Cleaned_Procurement!$E$2:$E$1801,W5,Cleaned_Procurement!$D$2:$D$1801,critRegion,Cleaned_Procurement!$F$2:$F$1801,critCategory,Cleaned_Procurement!$A$2:$A$1801,">="&dStart,Cleaned_Procurement!$A$2:$A$1801,"<="&dEnd) -> 284264.57 | Y5: =X5+ROW()/1000000 -> 284264.57 | AA5: 1 | AB5: =IF(AC5<=0,"",INDEX($W$5:$W$28,MATCH(LARGE($Y$5:$Y$28,AA5),$Y$5:$Y$28,0))) -> NurseLink | AC5: =INDEX($X$5:$X$28,MATCH(LARGE($Y$5:$Y$28,AA5),$Y$5:$Y$28,0)) -> 1161388.4 | AE5: North | AF5: =SUMIFS(Finance_Raw!$K:$K,Finance_Raw!$D:$D,AE5,Finance_Raw!$A:$A,">="&dStart,Finance_Raw!$A:$A,"<="&dEnd) -> 15121342 | AG5: =SUMIFS(Finance_Raw!$L:$L,Finance_Raw!$D:$D,AE5,Finance_Raw!$A:$A,">="&dStart,Finance_Raw!$A:$A,"<="&dEnd) -> 15147826 | AI5: Conservative | AJ5: =Financial_Model!B36 -> 25617117 | AK5: =IF(AI5=$H$11,AJ5,0) -> 0 | AL5: =IF(AI5=$H$11,0,AJ5) -> 25617117 | AN5: 2025 | AO5: =Financial_Model!C42 -> 0 | AP5: =Financial_Model!D42 -> 0 | AQ5: =Financial_Model!E42 -> 0 | AR5: =Financial_Model!F42 -> 26123553 | AS5: =Savings_Tracker!A7 -> Medical Supplies | AT5: =Savings_Tracker!E7 -> 65829.181 | AU5: =Savings_Tracker!G7 -> 69150
A6: North | B6: Medical Supplies | C6: Jan-2025 | D6: 45658 | E6: Base | G6: Category selected | H6: =selCategory -> All | J6: Feb | K6: 45689 | L6: =SUMIFS(Finance_Raw!$E:$E,Finance_Raw!$D:$D,critRegion,Finance_Raw!$A:$A,$K6) -> 7476589.8 | M6: =SUMIFS(Finance_Raw!$L:$L,Finance_Raw!$D:$D,critRegion,Finance_Raw!$A:$A,$K6) -> 5235379.8 | N6: =L6-M6 -> 2241210 | O6: =SUMIFS(Agency_Raw!$I:$I,Agency_Raw!$D:$D,critRegion,Agency_Raw!$A:$A,$K6) -> 121421 | P6: =SUMIFS(Workforce_Raw!$I:$I,Workforce_Raw!$D:$D,critRegion,Workforce_Raw!$A:$A,$K6) -> 96726.69 | R6: Food & Catering | S6: =IF(R6=$H$6,0,U6) -> 837713.63 | T6: =IF(R6=$H$6,U6,0) -> 0 | U6: =SUMIFS(Cleaned_Procurement!$O$2:$O$1801,Cleaned_Procurement!$F$2:$F$1801,R6,Cleaned_Procurement!$D$2:$D$1801,critRegion,Cleaned_Procurement!$A$2:$A$1801,">="&dStart,Cleaned_Procurement!$A$2:$A$1801,"<="&dEnd) -> 837713.63 | W6: =Supplier_Lookup!A3 -> BuildCare | X6: =SUMIFS(Cleaned_Procurement!$O$2:$O$1801,Cleaned_Procurement!$E$2:$E$1801,W6,Cleaned_Procurement!$D$2:$D$1801,critRegion,Cleaned_Procurement!$F$2:$F$1801,critCategory,Cleaned_Procurement!$A$2:$A$1801,">="&dStart,Cleaned_Procurement!$A$2:$A$1801,"<="&dEnd) -> 647209.95 | Y6: =X6+ROW()/1000000 -> 647209.95 | AA6: 2 | AB6: =IF(AC6<=0,"",INDEX($W$5:$W$28,MATCH(LARGE($Y$5:$Y$28,AA6),$Y$5:$Y$28,0))) -> HealthStaffing | AC6: =INDEX($X$5:$X$28,MATCH(LARGE($Y$5:$Y$28,AA6),$Y$5:$Y$28,0)) -> 1072844.7 | AE6: Midlands | AF6: =SUMIFS(Finance_Raw!$K:$K,Finance_Raw!$D:$D,AE6,Finance_Raw!$A:$A,">="&dStart,Finance_Raw!$A:$A,"<="&dEnd) -> 15390373 | AG6: =SUMIFS(Finance_Raw!$L:$L,Finance_Raw!$D:$D,AE6,Finance_Raw!$A:$A,">="&dStart,Finance_Raw!$A:$A,"<="&dEnd) -> 15403842 | AI6: Base | AJ6: =Financial_Model!C36 -> 28098167 | AK6: =IF(AI6=$H$11,AJ6,0) -> 28098167 | AL6: =IF(AI6=$H$11,0,AJ6) -> 0 | AN6: Revenue | AO6: =Financial_Model!C43 -> 26123553 | AP6: =Financial_Model!D43 -> 2594295.5 | AQ6: =Financial_Model!E43 -> 0 | AR6: =Financial_Model!F43 -> 0 | AS6: =Savings_Tracker!A8 -> Food & Catering | AT6: =Savings_Tracker!E8 -> 33508.545 | AU6: =Savings_Tracker!G8 -> 30150
A7: Midlands | B7: Food & Catering | C7: Feb-2025 | D7: 45689 | E7: Aggressive | G7: Category criterion | H7: =IF($H$6="All","*",$H$6) -> * | J7: Mar | K7: 45717 | L7: =SUMIFS(Finance_Raw!$E:$E,Finance_Raw!$D:$D,critRegion,Finance_Raw!$A:$A,$K7) -> 7345583.3 | M7: =SUMIFS(Finance_Raw!$L:$L,Finance_Raw!$D:$D,critRegion,Finance_Raw!$A:$A,$K7) -> 5087641.7 | N7: =L7-M7 -> 2257941.6 | O7: =SUMIFS(Agency_Raw!$I:$I,Agency_Raw!$D:$D,critRegion,Agency_Raw!$A:$A,$K7) -> 103588 | P7: =SUMIFS(Workforce_Raw!$I:$I,Workforce_Raw!$D:$D,critRegion,Workforce_Raw!$A:$A,$K7) -> 96705.13 | R7: Facilities | S7: =IF(R7=$H$6,0,U7) -> 2128780.9 | T7: =IF(R7=$H$6,U7,0) -> 0 | U7: =SUMIFS(Cleaned_Procurement!$O$2:$O$1801,Cleaned_Procurement!$F$2:$F$1801,R7,Cleaned_Procurement!$D$2:$D$1801,critRegion,Cleaned_Procurement!$A$2:$A$1801,">="&dStart,Cleaned_Procurement!$A$2:$A$1801,"<="&dEnd) -> 2128780.9 | W7: =Supplier_Lookup!A4 -> CareMed | X7: =SUMIFS(Cleaned_Procurement!$O$2:$O$1801,Cleaned_Procurement!$E$2:$E$1801,W7,Cleaned_Procurement!$D$2:$D$1801,critRegion,Cleaned_Procurement!$F$2:$F$1801,critCategory,Cleaned_Procurement!$A$2:$A$1801,">="&dStart,Cleaned_Procurement!$A$2:$A$1801,"<="&dEnd) -> 311670.19 | Y7: =X7+ROW()/1000000 -> 311670.19 | AA7: 3 | AB7: =IF(AC7<=0,"",INDEX($W$5:$W$28,MATCH(LARGE($Y$5:$Y$28,AA7),$Y$5:$Y$28,0))) -> PowerDirect | AC7: =INDEX($X$5:$X$28,MATCH(LARGE($Y$5:$Y$28,AA7),$Y$5:$Y$28,0)) -> 1048249.1 | AE7: South | AF7: =SUMIFS(Finance_Raw!$K:$K,Finance_Raw!$D:$D,AE7,Finance_Raw!$A:$A,">="&dStart,Finance_Raw!$A:$A,"<="&dEnd) -> 14775058 | AG7: =SUMIFS(Finance_Raw!$L:$L,Finance_Raw!$D:$D,AE7,Finance_Raw!$A:$A,">="&dStart,Finance_Raw!$A:$A,"<="&dEnd) -> 14726020 | AI7: Aggressive | AJ7: =Financial_Model!D36 -> 30541180 | AK7: =IF(AI7=$H$11,AJ7,0) -> 0 | AL7: =IF(AI7=$H$11,0,AJ7) -> 30541180 | AN7: Procurement | AO7: =Financial_Model!C44 -> 28717848 | AP7: =Financial_Model!D44 -> 556680.77 | AQ7: =Financial_Model!E44 -> 0 | AR7: =Financial_Model!F44 -> 0 | AS7: =Savings_Tracker!A9 -> Facilities | AT7: =Savings_Tracker!E9 -> 106439.05 | AU7: =Savings_Tracker!G9 -> 74550
A8: South | B8: Facilities | C8: Mar-2025 | D8: 45717 | E8: Custom | G8: Month selected | H8: =selMonth -> All | J8: Apr | K8: 45748 | L8: =SUMIFS(Finance_Raw!$E:$E,Finance_Raw!$D:$D,critRegion,Finance_Raw!$A:$A,$K8) -> 7658852.2 | M8: =SUMIFS(Finance_Raw!$L:$L,Finance_Raw!$D:$D,critRegion,Finance_Raw!$A:$A,$K8) -> 5279230.4 | N8: =L8-M8 -> 2379621.9 | O8: =SUMIFS(Agency_Raw!$I:$I,Agency_Raw!$D:$D,critRegion,Agency_Raw!$A:$A,$K8) -> 132145 | P8: =SUMIFS(Workforce_Raw!$I:$I,Workforce_Raw!$D:$D,critRegion,Workforce_Raw!$A:$A,$K8) -> 96930.42 | R8: Utilities | S8: =IF(R8=$H$6,0,U8) -> 2401261.6 | T8: =IF(R8=$H$6,U8,0) -> 0 | U8: =SUMIFS(Cleaned_Procurement!$O$2:$O$1801,Cleaned_Procurement!$F$2:$F$1801,R8,Cleaned_Procurement!$D$2:$D$1801,critRegion,Cleaned_Procurement!$A$2:$A$1801,">="&dStart,Cleaned_Procurement!$A$2:$A$1801,"<="&dEnd) -> 2401261.6 | W8: =Supplier_Lookup!A5 -> CareTemps | X8: =SUMIFS(Cleaned_Procurement!$O$2:$O$1801,Cleaned_Procurement!$E$2:$E$1801,W8,Cleaned_Procurement!$D$2:$D$1801,critRegion,Cleaned_Procurement!$F$2:$F$1801,critCategory,Cleaned_Procurement!$A$2:$A$1801,">="&dStart,Cleaned_Procurement!$A$2:$A$1801,"<="&dEnd) -> 959134.04 | Y8: =X8+ROW()/1000000 -> 959134.04 | AA8: 4 | AB8: =IF(AC8<=0,"",INDEX($W$5:$W$28,MATCH(LARGE($Y$5:$Y$28,AA8),$Y$5:$Y$28,0))) -> CareTemps | AC8: =INDEX($X$5:$X$28,MATCH(LARGE($Y$5:$Y$28,AA8),$Y$5:$Y$28,0)) -> 959134.04 | AE8: Wales | AF8: =SUMIFS(Finance_Raw!$K:$K,Finance_Raw!$D:$D,AE8,Finance_Raw!$A:$A,">="&dStart,Finance_Raw!$A:$A,"<="&dEnd) -> 15115049 | AG8: =SUMIFS(Finance_Raw!$L:$L,Finance_Raw!$D:$D,AE8,Finance_Raw!$A:$A,">="&dStart,Finance_Raw!$A:$A,"<="&dEnd) -> 15075277 | AI8: Custom | AJ8: =Financial_Model!E36 -> 28098167 | AK8: =IF(AI8=$H$11,AJ8,0) -> 0 | AL8: =IF(AI8=$H$11,0,AJ8) -> 28098167 | AN8: Agency | AO8: =Financial_Model!C45 -> 29207474 | AP8: =Financial_Model!D45 -> 0 | AQ8: =Financial_Model!E45 -> 67054.3 | AR8: =Financial_Model!F45 -> 0 | AS8: =Savings_Tracker!A10 -> Utilities | AT8: =Savings_Tracker!E10 -> 72037.848 | AU8: =Savings_Tracker!G10 -> 79200
A9: Wales | B9: Utilities | C9: Apr-2025 | D9: 45748 | G9: Period start | H9: =IF($H$8="All",DATE(2025,1,1),INDEX($D$6:$D$17,MATCH($H$8,$C$6:$C$17,0))) -> 45658 | J9: May | K9: 45778 | L9: =SUMIFS(Finance_Raw!$E:$E,Finance_Raw!$D:$D,critRegion,Finance_Raw!$A:$A,$K9) -> 6576496.4 | M9: =SUMIFS(Finance_Raw!$L:$L,Finance_Raw!$D:$D,critRegion,Finance_Raw!$A:$A,$K9) -> 4543655.4 | N9: =L9-M9 -> 2032841 | O9: =SUMIFS(Agency_Raw!$I:$I,Agency_Raw!$D:$D,critRegion,Agency_Raw!$A:$A,$K9) -> 99849 | P9: =SUMIFS(Workforce_Raw!$I:$I,Workforce_Raw!$D:$D,critRegion,Workforce_Raw!$A:$A,$K9) -> 87244.73 | R9: IT & Telecoms | S9: =IF(R9=$H$6,0,U9) -> 2505155.2 | T9: =IF(R9=$H$6,U9,0) -> 0 | U9: =SUMIFS(Cleaned_Procurement!$O$2:$O$1801,Cleaned_Procurement!$F$2:$F$1801,R9,Cleaned_Procurement!$D$2:$D$1801,critRegion,Cleaned_Procurement!$A$2:$A$1801,">="&dStart,Cleaned_Procurement!$A$2:$A$1801,"<="&dEnd) -> 2505155.2 | W9: =Supplier_Lookup!A6 -> CleanWorks | X9: =SUMIFS(Cleaned_Procurement!$O$2:$O$1801,Cleaned_Procurement!$E$2:$E$1801,W9,Cleaned_Procurement!$D$2:$D$1801,critRegion,Cleaned_Procurement!$F$2:$F$1801,critCategory,Cleaned_Procurement!$A$2:$A$1801,">="&dStart,Cleaned_Procurement!$A$2:$A$1801,"<="&dEnd) -> 591363.92 | Y9: =X9+ROW()/1000000 -> 591363.92 | AA9: 5 | AB9: =IF(AC9<=0,"",INDEX($W$5:$W$28,MATCH(LARGE($Y$5:$Y$28,AA9),$Y$5:$Y$28,0))) -> SafeGuard FM | AC9: =INDEX($X$5:$X$28,MATCH(LARGE($Y$5:$Y$28,AA9),$Y$5:$Y$28,0)) -> 890207.06 | AN9: Fleet | AO9: =Financial_Model!C46 -> 29207474 | AP9: =Financial_Model!D46 -> 26460.221 | AQ9: =Financial_Model!E46 -> 0 | AR9: =Financial_Model!F46 -> 0 | AS9: =Savings_Tracker!A11 -> IT & Telecoms | AT9: =Savings_Tracker!E11 -> 200412.41 | AU9: =Savings_Tracker!G11 -> 160350
B10: IT & Telecoms | C10: May-2025 | D10: 45778 | G10: Period end | H10: =IF($H$8="All",DATE(2025,12,31),EOMONTH($H$9,0)) -> 46022 | J10: Jun | K10: 45809 | L10: =SUMIFS(Finance_Raw!$E:$E,Finance_Raw!$D:$D,critRegion,Finance_Raw!$A:$A,$K10) -> 7065637.8 | M10: =SUMIFS(Finance_Raw!$L:$L,Finance_Raw!$D:$D,critRegion,Finance_Raw!$A:$A,$K10) -> 4919918.3 | N10: =L10-M10 -> 2145719.5 | O10: =SUMIFS(Agency_Raw!$I:$I,Agency_Raw!$D:$D,critRegion,Agency_Raw!$A:$A,$K10) -> 106117 | P10: =SUMIFS(Workforce_Raw!$I:$I,Workforce_Raw!$D:$D,critRegion,Workforce_Raw!$A:$A,$K10) -> 93237.38 | R10: Vehicle & Fuel | S10: =IF(R10=$H$6,0,U10) -> 1030620.3 | T10: =IF(R10=$H$6,U10,0) -> 0 | U10: =SUMIFS(Cleaned_Procurement!$O$2:$O$1801,Cleaned_Procurement!$F$2:$F$1801,R10,Cleaned_Procurement!$D$2:$D$1801,critRegion,Cleaned_Procurement!$A$2:$A$1801,">="&dStart,Cleaned_Procurement!$A$2:$A$1801,"<="&dEnd) -> 1030620.3 | W10: =Supplier_Lookup!A7 -> ClinEquip | X10: =SUMIFS(Cleaned_Procurement!$O$2:$O$1801,Cleaned_Procurement!$E$2:$E$1801,W10,Cleaned_Procurement!$D$2:$D$1801,critRegion,Cleaned_Procurement!$F$2:$F$1801,critCategory,Cleaned_Procurement!$A$2:$A$1801,">="&dStart,Cleaned_Procurement!$A$2:$A$1801,"<="&dEnd) -> 359940.88 | Y10: =X10+ROW()/1000000 -> 359940.88 | AA10: 6 | AB10: =IF(AC10<=0,"",INDEX($W$5:$W$28,MATCH(LARGE($Y$5:$Y$28,AA10),$Y$5:$Y$28,0))) -> CloudLink | AC10: =INDEX($X$5:$X$28,MATCH(LARGE($Y$5:$Y$28,AA10),$Y$5:$Y$28,0)) -> 881477.21 | AN10: Payroll | AO10: =Financial_Model!C47 -> 28280844 | AP10: =Financial_Model!D47 -> 0 | AQ10: =Financial_Model!E47 -> 953091.15 | AR10: =Financial_Model!F47 -> 0 | AS10: =Savings_Tracker!A12 -> Vehicle & Fuel | AT10: =Savings_Tracker!E12 -> 51531.015 | AU10: =Savings_Tracker!G12 -> 48900
B11: Vehicle & Fuel | C11: Jun-2025 | D11: 45809 | G11: Scenario | H11: =selScenario -> Base | J11: Jul | K11: 45839 | L11: =SUMIFS(Finance_Raw!$E:$E,Finance_Raw!$D:$D,critRegion,Finance_Raw!$A:$A,$K11) -> 6953277 | M11: =SUMIFS(Finance_Raw!$L:$L,Finance_Raw!$D:$D,critRegion,Finance_Raw!$A:$A,$K11) -> 4875601.1 | N11: =L11-M11 -> 2077675.9 | O11: =SUMIFS(Agency_Raw!$I:$I,Agency_Raw!$D:$D,critRegion,Agency_Raw!$A:$A,$K11) -> 118232 | P11: =SUMIFS(Workforce_Raw!$I:$I,Workforce_Raw!$D:$D,critRegion,Workforce_Raw!$A:$A,$K11) -> 76968.2 | R11: Agency Labour | S11: =IF(R11=$H$6,0,U11) -> 3193367.1 | T11: =IF(R11=$H$6,U11,0) -> 0 | U11: =SUMIFS(Cleaned_Procurement!$O$2:$O$1801,Cleaned_Procurement!$F$2:$F$1801,R11,Cleaned_Procurement!$D$2:$D$1801,critRegion,Cleaned_Procurement!$A$2:$A$1801,">="&dStart,Cleaned_Procurement!$A$2:$A$1801,"<="&dEnd) -> 3193367.1 | W11: =Supplier_Lookup!A8 -> CloudLink | X11: =SUMIFS(Cleaned_Procurement!$O$2:$O$1801,Cleaned_Procurement!$E$2:$E$1801,W11,Cleaned_Procurement!$D$2:$D$1801,critRegion,Cleaned_Procurement!$F$2:$F$1801,critCategory,Cleaned_Procurement!$A$2:$A$1801,">="&dStart,Cleaned_Procurement!$A$2:$A$1801,"<="&dEnd) -> 881477.21 | Y11: =X11+ROW()/1000000 -> 881477.21 | AA11: 7 | AB11: =IF(AC11<=0,"",INDEX($W$5:$W$28,MATCH(LARGE($Y$5:$Y$28,AA11),$Y$5:$Y$28,0))) -> NetServe | AC11: =INDEX($X$5:$X$28,MATCH(LARGE($Y$5:$Y$28,AA11),$Y$5:$Y$28,0)) -> 851726.08 | AN11: Other | AO11: =Financial_Model!C48 -> 28098167 | AP11: =Financial_Model!D48 -> 0 | AQ11: =Financial_Model!E48 -> 182676.18 | AR11: =Financial_Model!F48 -> 0 | AS11: =Savings_Tracker!A13 -> Agency Labour | AT11: =Savings_Tracker!E13 -> 223535.7 | AU11: =Savings_Tracker!G13 -> 134100
B12: Agency Labour | C12: Jul-2025 | D12: 45839 | J12: Aug | K12: 45870 | L12: =SUMIFS(Finance_Raw!$E:$E,Finance_Raw!$D:$D,critRegion,Finance_Raw!$A:$A,$K12) -> 7044378.2 | M12: =SUMIFS(Finance_Raw!$L:$L,Finance_Raw!$D:$D,critRegion,Finance_Raw!$A:$A,$K12) -> 4979875.7 | N12: =L12-M12 -> 2064502.5 | O12: =SUMIFS(Agency_Raw!$I:$I,Agency_Raw!$D:$D,critRegion,Agency_Raw!$A:$A,$K12) -> 99862 | P12: =SUMIFS(Workforce_Raw!$I:$I,Workforce_Raw!$D:$D,critRegion,Workforce_Raw!$A:$A,$K12) -> 99012 | R12: Office & Training | S12: =IF(R12=$H$6,0,U12) -> 728629.96 | T12: =IF(R12=$H$6,U12,0) -> 0 | U12: =SUMIFS(Cleaned_Procurement!$O$2:$O$1801,Cleaned_Procurement!$F$2:$F$1801,R12,Cleaned_Procurement!$D$2:$D$1801,critRegion,Cleaned_Procurement!$A$2:$A$1801,">="&dStart,Cleaned_Procurement!$A$2:$A$1801,"<="&dEnd) -> 728629.96 | W12: =Supplier_Lookup!A9 -> FleetFuel | X12: =SUMIFS(Cleaned_Procurement!$O$2:$O$1801,Cleaned_Procurement!$E$2:$E$1801,W12,Cleaned_Procurement!$D$2:$D$1801,critRegion,Cleaned_Procurement!$F$2:$F$1801,critCategory,Cleaned_Procurement!$A$2:$A$1801,">="&dStart,Cleaned_Procurement!$A$2:$A$1801,"<="&dEnd) -> 314243.92 | Y12: =X12+ROW()/1000000 -> 314243.92 | AA12: 8 | AB12: =IF(AC12<=0,"",INDEX($W$5:$W$28,MATCH(LARGE($Y$5:$Y$28,AA12),$Y$5:$Y$28,0))) -> UK Energy Partners | AC12: =INDEX($X$5:$X$28,MATCH(LARGE($Y$5:$Y$28,AA12),$Y$5:$Y$28,0)) -> 833961.1 | AN12: 2026 | AO12: =Financial_Model!C49 -> 0 | AP12: =Financial_Model!D49 -> 0 | AQ12: =Financial_Model!E49 -> 0 | AR12: =Financial_Model!F49 -> 28098167 | AS12: =Savings_Tracker!A14 -> Office & Training | AT12: =Savings_Tracker!E14 -> 29145.198 | AU12: =Savings_Tracker!G14 -> 34950
B13: Office & Training | C13: Aug-2025 | D13: 45870 | G13: Revenue | H13: =SUMIFS(Finance_Raw!$E:$E,Finance_Raw!$D:$D,critRegion,Finance_Raw!$A:$A,">="&dStart,Finance_Raw!$A:$A,"<="&dEnd) -> 86476517 | J13: Sep | K13: 45901 | L13: =SUMIFS(Finance_Raw!$E:$E,Finance_Raw!$D:$D,critRegion,Finance_Raw!$A:$A,$K13) -> 6899634.7 | M13: =SUMIFS(Finance_Raw!$L:$L,Finance_Raw!$D:$D,critRegion,Finance_Raw!$A:$A,$K13) -> 4818773.5 | N13: =L13-M13 -> 2080861.1 | O13: =SUMIFS(Agency_Raw!$I:$I,Agency_Raw!$D:$D,critRegion,Agency_Raw!$A:$A,$K13) -> 120617 | P13: =SUMIFS(Workforce_Raw!$I:$I,Workforce_Raw!$D:$D,critRegion,Workforce_Raw!$A:$A,$K13) -> 87250.03 | W13: =Supplier_Lookup!A10 -> FreshServe | X13: =SUMIFS(Cleaned_Procurement!$O$2:$O$1801,Cleaned_Procurement!$E$2:$E$1801,W13,Cleaned_Procurement!$D$2:$D$1801,critRegion,Cleaned_Procurement!$F$2:$F$1801,critCategory,Cleaned_Procurement!$A$2:$A$1801,">="&dStart,Cleaned_Procurement!$A$2:$A$1801,"<="&dEnd) -> 238615.67 | Y13: =X13+ROW()/1000000 -> 238615.67 | AA13: 9 | AB13: =IF(AC13<=0,"",INDEX($W$5:$W$28,MATCH(LARGE($Y$5:$Y$28,AA13),$Y$5:$Y$28,0))) -> TeleCare IT | AC13: =INDEX($X$5:$X$28,MATCH(LARGE($Y$5:$Y$28,AA13),$Y$5:$Y$28,0)) -> 774305.94
C14: Sep-2025 | D14: 45901 | G14: Actual Opex | H14: =SUMIFS(Finance_Raw!$L:$L,Finance_Raw!$D:$D,critRegion,Finance_Raw!$A:$A,">="&dStart,Finance_Raw!$A:$A,"<="&dEnd) -> 60352965 | J14: Oct | K14: 45931 | L14: =SUMIFS(Finance_Raw!$E:$E,Finance_Raw!$D:$D,critRegion,Finance_Raw!$A:$A,$K14) -> 8051254.3 | M14: =SUMIFS(Finance_Raw!$L:$L,Finance_Raw!$D:$D,critRegion,Finance_Raw!$A:$A,$K14) -> 5558744.3 | N14: =L14-M14 -> 2492510 | O14: =SUMIFS(Agency_Raw!$I:$I,Agency_Raw!$D:$D,critRegion,Agency_Raw!$A:$A,$K14) -> 103394 | P14: =SUMIFS(Workforce_Raw!$I:$I,Workforce_Raw!$D:$D,critRegion,Workforce_Raw!$A:$A,$K14) -> 108904.98 | W14: =Supplier_Lookup!A11 -> HealthStaffing | X14: =SUMIFS(Cleaned_Procurement!$O$2:$O$1801,Cleaned_Procurement!$E$2:$E$1801,W14,Cleaned_Procurement!$D$2:$D$1801,critRegion,Cleaned_Procurement!$F$2:$F$1801,critCategory,Cleaned_Procurement!$A$2:$A$1801,">="&dStart,Cleaned_Procurement!$A$2:$A$1801,"<="&dEnd) -> 1072844.7 | Y14: =X14+ROW()/1000000 -> 1072844.7 | AA14: 10 | AB14: =IF(AC14<=0,"",INDEX($W$5:$W$28,MATCH(LARGE($Y$5:$Y$28,AA14),$Y$5:$Y$28,0))) -> BuildCare | AC14: =INDEX($X$5:$X$28,MATCH(LARGE($Y$5:$Y$28,AA14),$Y$5:$Y$28,0)) -> 647209.95
C15: Oct-2025 | D15: 45931 | G15: Budget Opex | H15: =SUMIFS(Finance_Raw!$K:$K,Finance_Raw!$D:$D,critRegion,Finance_Raw!$A:$A,">="&dStart,Finance_Raw!$A:$A,"<="&dEnd) -> 60401822 | J15: Nov | K15: 45962 | L15: =SUMIFS(Finance_Raw!$E:$E,Finance_Raw!$D:$D,critRegion,Finance_Raw!$A:$A,$K15) -> 6479152 | M15: =SUMIFS(Finance_Raw!$L:$L,Finance_Raw!$D:$D,critRegion,Finance_Raw!$A:$A,$K15) -> 4606613.7 | N15: =L15-M15 -> 1872538.3 | O15: =SUMIFS(Agency_Raw!$I:$I,Agency_Raw!$D:$D,critRegion,Agency_Raw!$A:$A,$K15) -> 109315 | P15: =SUMIFS(Workforce_Raw!$I:$I,Workforce_Raw!$D:$D,critRegion,Workforce_Raw!$A:$A,$K15) -> 91455.04 | W15: =Supplier_Lookup!A12 -> KitchenPro | X15: =SUMIFS(Cleaned_Procurement!$O$2:$O$1801,Cleaned_Procurement!$E$2:$E$1801,W15,Cleaned_Procurement!$D$2:$D$1801,critRegion,Cleaned_Procurement!$F$2:$F$1801,critCategory,Cleaned_Procurement!$A$2:$A$1801,">="&dStart,Cleaned_Procurement!$A$2:$A$1801,"<="&dEnd) -> 279264.56 | Y15: =X15+ROW()/1000000 -> 279264.56
C16: Nov-2025 | D16: 45962 | G16: EBITDA | H16: =H13-H14 -> 26123553 | J16: Dec | K16: 45992 | L16: =SUMIFS(Finance_Raw!$E:$E,Finance_Raw!$D:$D,critRegion,Finance_Raw!$A:$A,$K16) -> 8066416.4 | M16: =SUMIFS(Finance_Raw!$L:$L,Finance_Raw!$D:$D,critRegion,Finance_Raw!$A:$A,$K16) -> 5614126.6 | N16: =L16-M16 -> 2452289.7 | O16: =SUMIFS(Agency_Raw!$I:$I,Agency_Raw!$D:$D,critRegion,Agency_Raw!$A:$A,$K16) -> 119109 | P16: =SUMIFS(Workforce_Raw!$I:$I,Workforce_Raw!$D:$D,critRegion,Workforce_Raw!$A:$A,$K16) -> 95670.62 | W16: =Supplier_Lookup!A13 -> LearnWell | X16: =SUMIFS(Cleaned_Procurement!$O$2:$O$1801,Cleaned_Procurement!$E$2:$E$1801,W16,Cleaned_Procurement!$D$2:$D$1801,critRegion,Cleaned_Procurement!$F$2:$F$1801,critCategory,Cleaned_Procurement!$A$2:$A$1801,">="&dStart,Cleaned_Procurement!$A$2:$A$1801,"<="&dEnd) -> 236027.71 | Y16: =X16+ROW()/1000000 -> 236027.71
C17: Dec-2025 | D17: 45992 | G17: EBITDA margin | H17: =IFERROR(H16/H13,0) -> 0.3020884 | W17: =Supplier_Lookup!A14 -> MediSure | X17: =SUMIFS(Cleaned_Procurement!$O$2:$O$1801,Cleaned_Procurement!$E$2:$E$1801,W17,Cleaned_Procurement!$D$2:$D$1801,critRegion,Cleaned_Procurement!$F$2:$F$1801,critCategory,Cleaned_Procurement!$A$2:$A$1801,">="&dStart,Cleaned_Procurement!$A$2:$A$1801,"<="&dEnd) -> 423187.89 | Y17: =X17+ROW()/1000000 -> 423187.89
G18: Budget variance (+ fav) | H18: =H15-H14 -> 48856.977 | W18: =Supplier_Lookup!A15 -> NetServe | X18: =SUMIFS(Cleaned_Procurement!$O$2:$O$1801,Cleaned_Procurement!$E$2:$E$1801,W18,Cleaned_Procurement!$D$2:$D$1801,critRegion,Cleaned_Procurement!$F$2:$F$1801,critCategory,Cleaned_Procurement!$A$2:$A$1801,">="&dStart,Cleaned_Procurement!$A$2:$A$1801,"<="&dEnd) -> 851726.08 | Y18: =X18+ROW()/1000000 -> 851726.08
G19: Budget variance % | H19: =IFERROR(H18/H15,0) -> 0.00080886595 | W19: =Supplier_Lookup!A16 -> NourishCo | X19: =SUMIFS(Cleaned_Procurement!$O$2:$O$1801,Cleaned_Procurement!$E$2:$E$1801,W19,Cleaned_Procurement!$D$2:$D$1801,critRegion,Cleaned_Procurement!$F$2:$F$1801,critCategory,Cleaned_Procurement!$A$2:$A$1801,">="&dStart,Cleaned_Procurement!$A$2:$A$1801,"<="&dEnd) -> 319833.4 | Y19: =X19+ROW()/1000000 -> 319833.4
G20: Payroll | H20: =SUMIFS(Finance_Raw!$F:$F,Finance_Raw!$D:$D,critRegion,Finance_Raw!$A:$A,">="&dStart,Finance_Raw!$A:$A,"<="&dEnd) -> 38123646 | W20: =Supplier_Lookup!A17 -> NurseLink | X20: =SUMIFS(Cleaned_Procurement!$O$2:$O$1801,Cleaned_Procurement!$E$2:$E$1801,W20,Cleaned_Procurement!$D$2:$D$1801,critRegion,Cleaned_Procurement!$F$2:$F$1801,critCategory,Cleaned_Procurement!$A$2:$A$1801,">="&dStart,Cleaned_Procurement!$A$2:$A$1801,"<="&dEnd) -> 1161388.4 | Y20: =X20+ROW()/1000000 -> 1161388.4
G21: Agency (ledger) | H21: =SUMIFS(Finance_Raw!$I:$I,Finance_Raw!$D:$D,critRegion,Finance_Raw!$A:$A,">="&dStart,Finance_Raw!$A:$A,"<="&dEnd) -> 1341086 | W21: =Supplier_Lookup!A18 -> OfficePlus | X21: =SUMIFS(Cleaned_Procurement!$O$2:$O$1801,Cleaned_Procurement!$E$2:$E$1801,W21,Cleaned_Procurement!$D$2:$D$1801,critRegion,Cleaned_Procurement!$F$2:$F$1801,critCategory,Cleaned_Procurement!$A$2:$A$1801,">="&dStart,Cleaned_Procurement!$A$2:$A$1801,"<="&dEnd) -> 294325.78 | Y21: =X21+ROW()/1000000 -> 294325.78
G22: Group revenue (period) | H22: =SUMIFS(Finance_Raw!$E:$E,Finance_Raw!$A:$A,">="&dStart,Finance_Raw!$A:$A,"<="&dEnd) -> 86476517 | W22: =Supplier_Lookup!A19 -> PowerDirect | X22: =SUMIFS(Cleaned_Procurement!$O$2:$O$1801,Cleaned_Procurement!$E$2:$E$1801,W22,Cleaned_Procurement!$D$2:$D$1801,critRegion,Cleaned_Procurement!$F$2:$F$1801,critCategory,Cleaned_Procurement!$A$2:$A$1801,">="&dStart,Cleaned_Procurement!$A$2:$A$1801,"<="&dEnd) -> 1048249.1 | Y22: =X22+ROW()/1000000 -> 1048249.1
G23: Procurement spend | H23: =SUMIFS(Cleaned_Procurement!$O$2:$O$1801,Cleaned_Procurement!$D$2:$D$1801,critRegion,Cleaned_Procurement!$F$2:$F$1801,critCategory,Cleaned_Procurement!$A$2:$A$1801,">="&dStart,Cleaned_Procurement!$A$2:$A$1801,"<="&dEnd) -> 13922682 | W23: =Supplier_Lookup!A20 -> PrintCo | X23: =SUMIFS(Cleaned_Procurement!$O$2:$O$1801,Cleaned_Procurement!$E$2:$E$1801,W23,Cleaned_Procurement!$D$2:$D$1801,critRegion,Cleaned_Procurement!$F$2:$F$1801,critCategory,Cleaned_Procurement!$A$2:$A$1801,">="&dStart,Cleaned_Procurement!$A$2:$A$1801,"<="&dEnd) -> 197576.58 | Y23: =X23+ROW()/1000000 -> 197576.58
G24: Savings potential | H24: =SUMIFS(Cleaned_Procurement!$R$2:$R$1801,Cleaned_Procurement!$D$2:$D$1801,critRegion,Cleaned_Procurement!$F$2:$F$1801,critCategory,Cleaned_Procurement!$A$2:$A$1801,">="&dStart,Cleaned_Procurement!$A$2:$A$1801,"<="&dEnd) -> 782438.95 | W24: =Supplier_Lookup!A21 -> RoadReady | X24: =SUMIFS(Cleaned_Procurement!$O$2:$O$1801,Cleaned_Procurement!$E$2:$E$1801,W24,Cleaned_Procurement!$D$2:$D$1801,critRegion,Cleaned_Procurement!$F$2:$F$1801,critCategory,Cleaned_Procurement!$A$2:$A$1801,">="&dStart,Cleaned_Procurement!$A$2:$A$1801,"<="&dEnd) -> 432111.81 | Y24: =X24+ROW()/1000000 -> 432111.81
G25: Off-contract spend | H25: =SUMIFS(Cleaned_Procurement!$O$2:$O$1801,Cleaned_Procurement!$D$2:$D$1801,critRegion,Cleaned_Procurement!$F$2:$F$1801,critCategory,Cleaned_Procurement!$A$2:$A$1801,">="&dStart,Cleaned_Procurement!$A$2:$A$1801,"<="&dEnd,Cleaned_Procurement!$M$2:$M$1801,"N") -> 11473793 | W25: =Supplier_Lookup!A22 -> SafeGuard FM | X25: =SUMIFS(Cleaned_Procurement!$O$2:$O$1801,Cleaned_Procurement!$E$2:$E$1801,W25,Cleaned_Procurement!$D$2:$D$1801,critRegion,Cleaned_Procurement!$F$2:$F$1801,critCategory,Cleaned_Procurement!$A$2:$A$1801,">="&dStart,Cleaned_Procurement!$A$2:$A$1801,"<="&dEnd) -> 890207.06 | Y25: =X25+ROW()/1000000 -> 890207.06
G26: Off-contract % | H26: =IFERROR(H25/H23,0) -> 0.82410798 | W26: =Supplier_Lookup!A23 -> TeleCare IT | X26: =SUMIFS(Cleaned_Procurement!$O$2:$O$1801,Cleaned_Procurement!$E$2:$E$1801,W26,Cleaned_Procurement!$D$2:$D$1801,critRegion,Cleaned_Procurement!$F$2:$F$1801,critCategory,Cleaned_Procurement!$A$2:$A$1801,">="&dStart,Cleaned_Procurement!$A$2:$A$1801,"<="&dEnd) -> 774305.94 | Y26: =X26+ROW()/1000000 -> 774305.94
G27: Invoices | H27: =COUNTIFS(Cleaned_Procurement!$D$2:$D$1801,critRegion,Cleaned_Procurement!$F$2:$F$1801,critCategory,Cleaned_Procurement!$A$2:$A$1801,">="&dStart,Cleaned_Procurement!$A$2:$A$1801,"<="&dEnd) -> 1800 | W27: =Supplier_Lookup!A24 -> UK Energy Partners | X27: =SUMIFS(Cleaned_Procurement!$O$2:$O$1801,Cleaned_Procurement!$E$2:$E$1801,W27,Cleaned_Procurement!$D$2:$D$1801,critRegion,Cleaned_Procurement!$F$2:$F$1801,critCategory,Cleaned_Procurement!$A$2:$A$1801,">="&dStart,Cleaned_Procurement!$A$2:$A$1801,"<="&dEnd) -> 833961.1 | Y27: =X27+ROW()/1000000 -> 833961.1
G28: DQ exceptions | H28: =COUNTIFS(Cleaned_Procurement!$D$2:$D$1801,critRegion,Cleaned_Procurement!$F$2:$F$1801,critCategory,Cleaned_Procurement!$A$2:$A$1801,">="&dStart,Cleaned_Procurement!$A$2:$A$1801,"<="&dEnd,Cleaned_Procurement!$N$2:$N$1801,"<>OK") -> 6 | W28: =Supplier_Lookup!A25 -> WaterGrid | X28: =SUMIFS(Cleaned_Procurement!$O$2:$O$1801,Cleaned_Procurement!$E$2:$E$1801,W28,Cleaned_Procurement!$D$2:$D$1801,critRegion,Cleaned_Procurement!$F$2:$F$1801,critCategory,Cleaned_Procurement!$A$2:$A$1801,">="&dStart,Cleaned_Procurement!$A$2:$A$1801,"<="&dEnd) -> 519051.38 | Y28: =X28+ROW()/1000000 -> 519051.38
G29: Average invoice | H29: =IFERROR(H23/H27,0) -> 7734.8232
G31: Fleet miles | H31: =SUMIFS(Fleet_Raw!$G:$G,Fleet_Raw!$D:$D,critRegion,Fleet_Raw!$A:$A,">="&dStart,Fleet_Raw!$A:$A,"<="&dEnd) -> 1212529
G32: Fleet cost | H32: =SUMIFS(Fleet_Raw!$L:$L,Fleet_Raw!$D:$D,critRegion,Fleet_Raw!$A:$A,">="&dStart,Fleet_Raw!$A:$A,"<="&dEnd) -> 882007.36
G33: Fleet cost per mile | H33: =IFERROR(H32/H31,0) -> 0.72741135
G34: Payroll (workforce) | H34: =SUMIFS(Workforce_Raw!$L:$L,Workforce_Raw!$D:$D,critRegion,Workforce_Raw!$A:$A,">="&dStart,Workforce_Raw!$A:$A,"<="&dEnd) -> 38123646
G35: Overtime cost | H35: =SUMIFS(Workforce_Raw!$I:$I,Workforce_Raw!$D:$D,critRegion,Workforce_Raw!$A:$A,">="&dStart,Workforce_Raw!$A:$A,"<="&dEnd) -> 1116887.8
G36: Overtime % payroll | H36: =IFERROR(H35/H34,0) -> 0.029296458
G37: Agency spend | H37: =SUMIFS(Agency_Raw!$I:$I,Agency_Raw!$D:$D,critRegion,Agency_Raw!$A:$A,">="&dStart,Agency_Raw!$A:$A,"<="&dEnd) -> 1341086
G38: Agency % staff cost | H38: =IFERROR(H37/(H37+H34),0) -> 0.033981885
G40: 2026 EBITDA | H40: =Financial_Model!C23 -> 28098167
G41: 2026 EBITDA margin | H41: =Financial_Model!C24 -> 0.31545875
G42: 2026 Revenue | H42: =Financial_Model!C16 -> 89070813
G43: EBITDA change vs 2025 | H43: =Financial_Model!D23 -> 1974614.9
G44: Savings FY forecast | H44: =Savings_Tracker!G15 -> 631350
G45: Savings target | H45: =Savings_Tracker!E15 -> 782438.95
G46: Group 2025 margin | H46: =Financial_Model!B24 -> 0.3020884
G47: Region label | H47: =IF($H$4="All","all regions",$H$4) -> all regions
G48: Period label | H48: =IF($H$8="All","FY 2025",$H$8) -> FY 2025
G50: Insight sentences
G51: Insight 1 | H51: =IFERROR("Largest spend category in "&$H$47&", "&$H$48&": "&INDEX($R$5:$R$12,MATCH(MAX($U$5:$U$12),$U$5:$U$12,0))&" at "&TEXT(MAX($U$5:$U$12),"£#,##0")&" ("&TEXT(MAX($U$5:$U$12)/SUM($U$5:$U$12),"0%")&" of procurement spend).","No procurement spend for this selection.") -> Largest spend category in all regions, FY 2025: Agency Labour at £3,193,367 (23% of procurement spend).
G52: Insight 2 | H52: =IF($H$23=0,"No invoices match this selection.","Top supplier for this selection is "&$AB$5&" at "&TEXT($AC$5,"£#,##0")&"; "&TEXT($H$26,"0%")&" of selected spend is off-contract ("&TEXT($H$25,"£#,##0")&"). Category targets applied to this spend are worth "&TEXT($H$24,"£#,##0")&".") -> Top supplier for this selection is NurseLink at £1,161,388; 82% of selected spend is off-contract (£11,473,793). Category targets applied to this spend are worth £782,439.
G53: Insight 3 | H53: ="Opex for "&$H$47&", "&$H$48&" is "&TEXT(ABS($H$18),"£#,##0")&IF($H$18>=0," under"," over")&" budget ("&TEXT($H$19,"+0.0%;-0.0%")&"); EBITDA margin "&TEXT($H$17,"0.0%")&" against a group 2025 margin of "&TEXT($H$46,"0.0%")&"." -> Opex for all regions, FY 2025 is £48,857 under budget (+0.1%); EBITDA margin 30.2% against a group 2025 margin of 30.2%.
G54: Insight 4 | H54: ="2026 "&$H$11&" scenario: EBITDA "&TEXT($H$40/1000000,"£0.0")&"m ("&TEXT($H$41,"0.0%")&" margin), "&IF($H$43>=0,"up ","down ")&TEXT(ABS($H$43)/1000000,"£0.0")&"m on 2025. The savings tracker forecasts "&TEXT($H$44/$H$45,"0%")&" of the category target." -> 2026 Base scenario: EBITDA £28.1m (31.5% margin), up £2.0m on 2025. The savings tracker forecasts 81% of the category target.

Sheet Formula_Audit
A1: Advanced Excel technique catalogue
A2: Open the cell listed to see the live formula.
A3: Technique | B3: Where to look | C3: What it does here
A4: SUMIFS / COUNTIFS (multi-criteria) | B4: Dash_Calc!H23, Pivot_Analysis!B5 | C4: Spend by region x category x date window; invoice and exception counts.
A5: Wildcard criteria ("*") | B5: Dash_Calc!H5, H7 | C5: "All" selections become "*" so one SUMIFS serves every filter combination.
A6: Date-window criteria (">="&start) | B6: Dash_Calc!H9:H10, H13 | C6: Month selector converted to start/end dates with INDEX/MATCH and EOMONTH.
A7: INDEX + MATCH | B7: Cleaned_Procurement!E2, Supplier_Analysis!L6 | C7: Case-insensitive supplier standardisation; top-N retrieval.
A8: VLOOKUP (exact match) | B8: Cleaned_Procurement!T2 | C8: Site town enrichment from the Sites table. XLOOKUP equivalent: XLOOKUP(B2,Sites[SiteID],Sites[Town],"Unknown").
A9: LARGE + tie-break key | B9: Dash_Calc!Y5, AB5:AC14 | C9: Dynamic top 10 suppliers that respects all filters; ROW()/1e6 breaks ties.
A10: RANK | B10: Supplier_Analysis!H5, Site_Performance!J5 | C10: Supplier and site ranking.
A11: CHOOSE + MATCH | B11: Financial_Model!F6 | C11: Scenario selector maps to the selected driver column.
A12: Running COUNTIFS | B12: Cleaned_Procurement!N2, U2 | C12: Flags only the 2nd+ occurrence of a true duplicate; numbers exceptions for the log.
A13: EXACT / TRIM / PROPER logic | B13: Cleaned_Procurement!V2 | C13: Counts records whose casing or whitespace was corrected.
A14: IFERROR / defensive formulas | B14: Data_Quality!G6 | C14: Exception log returns blanks rather than lookup errors once exceptions run out.
... A24: Reconciliation controls | B24: Data_Quality!D18:D26 | C24: PASS/FAIL ties between raw, cleaned and ledger with an input tolerance.

Sheet VBA_Code
A1: VBA automation catalogue
A2: Import the .bas files into a macro-enabled copy (.xlsm). Excel desktop for Windows; Excel Online cannot run VBA.
A3: Module | B3: Macro | C3: What it automates | D3: Typical use
A4: Module_CleanseData | B4: CleanseProcurementData | C4: Array-based validation of tblProcurement with a Dictionary duplicate check. Writes flags to DataQualityFlag and a timestamped DQ_Log sheet. Raw supplier/category text is left untouched. | D4: After each new extract
A5: Module_ConsolidateCSVs | B5: ConsolidateCSVFiles | C5: Loops a chosen folder, checks each CSV header against the first file, appends matching files with a SourceFile column, skips and reports mismatches. | D5: Monthly supplier-spend files
A6: Module_RefreshDashboard | B6: RefreshCommercialModel | C6: RefreshAll, PivotTable refresh, full recalculation, reconciliation status check and a timestamp on the Dashboard. | D6: Before any report run
A7: Module_ExportReport | B7: ExportDashboardToPDF | C7: Landscape, fit-to-width PDF of the Dashboard with a dated file name. | D7: Ad-hoc stakeholder requests
A8: Module_ExportReport | B8: ExportRegionalReportPack | C8: Sets the Region selector to each region in turn and saves one PDF per region, then restores the original selection. | D8: Monthly regional pack
A9: Module_ScenarioRunner | B9: RunAllScenarios | C9: Cycles every scenario through the model and logs revenue, Opex, EBITDA and margin to Scenario_Log. | D9: Budget season, board papers
A10: Module_DashboardControls | B10: ResetDashboardFilters / AddDashboardButtons | C10: Resets selectors to All/Base; one-off macro that draws clickable buttons on the Dashboard and assigns the macros. | D10: Setup and daily use
A13: Setup
A14: 1. Save a copy as .xlsm (File > Save As > Excel Macro-Enabled Workbook).
A15: 2. Alt+F11 > File > Import File > import all six .bas files.
A16: 3. Alt+F8 > AddDashboardButtons (run once) to create the Dashboard buttons.
A17: 4. Test CleanseProcurementData and ConsolidateCSVFiles on a copy first (use the Sample_Procurement_Files folder).

Sheet Methodology
A1: Methodology, assumptions and limitations
A3: Topic | B3: Detail
A4: Data provenance | B4: All data is synthetic, generated for this portfolio project. 20 sites, 4 regions, calendar 2025. Figures are illustrative and are not CareTech data.
A5: Cleansing principle | B5: Raw tables are never overwritten by formulas. Cleaning happens in Cleaned_Procurement; every exception keeps its source value, gets a flag and a documented treatment on Data_Quality.
A6: Duplicate rule | B6: A true duplicate needs the same invoice ID, supplier and amount; only the second occurrence is excluded. A shared ID with a different supplier or amount is an ID collision: both lines stay in, flagged for review.
A7: Reference data | B7: The supplier lookup was rebuilt from 37 rows to a 24-row master after finding 13 lower-case duplicates and one conflicting mapping. A lookup with conflicting rows silently picks the first match.
A8: Reconciliation | B8: Cleaned procurement ties to raw less exclusions. Procurement, fleet, agency and payroll extracts reconcile to the finance ledger within an input tolerance (0.1%).
A9: Model structure | B9: 2026 = 2025 actual x (1 +/- driver) per cost line. Four scenarios; Custom is user-defined. Monthly phasing follows 2025 seasonality. Budget = 2025 budget x (1 + uplift).
A10: Savings forecast | B10: Straight-line run rate: realised YTD / months elapsed x 12. Realised YTD figures are synthetic inputs, as they would come from a savings register.
A11: Simplifications | B11: No volume growth in costs, no working capital, no depreciation or tax (EBITDA only). Procurement saving applied to the 2025 base without price inflation.
A12: GDPR-first design | B12: No names, addresses, NHS numbers, payroll numbers or dates of birth. Workforce data is aggregated by site, month and role. Sites and vehicles use synthetic IDs. In live use: role-based access, data minimisation, agreed retention and no personal data in exported PDFs.
A13: Tooling choices | B13: INDEX/MATCH over XLOOKUP for compatibility with older Excel builds used across large estates. Formula sensitivity grids instead of Data Tables so they recalculate with manual calc mode off.
